Workbook

Sheet Global
A1: Mes | B1: Opc/Futuros | C1: Acciones | D1: Bonos | E1: Cedear | F1: ON | G1: FCI | H1: Letras | I1: Cripto | J1: Efectivo | K1: Total | L1: Variacion | M1: Inflacion | O1: Variacion Total | P1: Inflacion Total | Q1: P&L Final
A2: Enero | B2: =IFERROR(INDIRECT($A2&"!$N1"),0) -> 0 | C2: =IFERROR(INDIRECT($A2&"!$N2"),0) -> 478288.5 | D2: =IFERROR(INDIRECT($A2&"!$N3"),0) -> 225608 | E2: =IFERROR(INDIRECT($A2&"!$N4"),0) -> 493990 | F2: =IFERROR(INDIRECT($A2&"!$N5"),0) -> 31148 | G2: =IFERROR(INDIRECT($A2&"!$N6"),0) -> 1338770.1 | H2: =IFERROR(INDIRECT($A2&"!$N7"),0) -> 28744.249 | I2: =IFERROR(INDIRECT($A2&"!$N8"),0) -> 22000 | J2: =IFERROR(INDIRECT($A2&"!$N9"),0) -> 50856.87 | K2: =SUM(B2:J2) -> 2669405.7 | L2: =Enero!D2 -> 0.01610312 | M2: 0.022 | O2: =SUM(L2:L13) -> 0.43860346 | P2: =SUM(M2:M13) -> 0.1572
A3: Febrero | B3: =IFERROR(INDIRECT($A3&"!$N1"),0) -> 0 | C3: =IFERROR(INDIRECT($A3&"!$N2"),0) -> 429801.5 | D3: =IFERROR(INDIRECT($A3&"!$N3"),0) -> 728440.79 | E3: =IFERROR(INDIRECT($A3&"!$N4"),0) -> 478840 | F3: =IFERROR(INDIRECT($A3&"!$N5"),0) -> 37599 | G3: =IFERROR(INDIRECT($A3&"!$N6"),0) -> 1307699.7 | H3: =IFERROR(INDIRECT($A3&"!$N7"),0) -> 1126576.5 | I3: =IFERROR(INDIRECT($A3&"!$N8"),0) -> 22160 | J3: =IFERROR(INDIRECT($A3&"!$N9"),0) -> 50856.87 | K3: =SUM(B3:J3) -> 4181974.4 | L3: =Febrero!D2 -> -0.0063999368 | M3: 0.024
A4: Marzo | B4: =IFERROR(INDIRECT($A4&"!$N1"),0) -> 0 | C4: =IFERROR(INDIRECT($A4&"!$N2"),0) -> 410678 | D4: =IFERROR(INDIRECT($A4&"!$N3"),0) -> 650045.56 | E4: =IFERROR(INDIRECT($A4&"!$N4"),0) -> 440171 | F4: =IFERROR(INDIRECT($A4&"!$N5"),0) -> 39142 | G4: =IFERROR(INDIRECT($A4&"!$N6"),0) -> 6336846.3 | H4: =IFERROR(INDIRECT($A4&"!$N7"),0) -> 1134591.6 | I4: =IFERROR(INDIRECT($A4&"!$N8"),0) -> 21408 | J4: =IFERROR(INDIRECT($A4&"!$N9"),0) -> 107420 | K4: =SUM(B4:J4) -> 9140302.4 | L4: =Marzo!D2 -> 0.12993873 | M4: 0.03 | O4: 5Y | P4: =TODAY()-1825 -> 44162
A5: Abril | B5: =IFERROR(INDIRECT($A5&"!$N1"),0) -> 0 | C5: =IFERROR(INDIRECT($A5&"!$N2"),0) -> 438914 | D5: =IFERROR(INDIRECT($A5&"!$N3"),0) -> 169700 | E5: =IFERROR(INDIRECT($A5&"!$N4"),0) -> 458655 | F5: =IFERROR(INDIRECT($A5&"!$N5"),0) -> 332880 | G5: =IFERROR(INDIRECT($A5&"!$N6"),0) -> 6549611.8 | H5: =IFERROR(INDIRECT($A5&"!$N7"),0) -> 2185113 | I5: =IFERROR(INDIRECT($A5&"!$N8"),0) -> 23867 | J5: =IFERROR(INDIRECT($A5&"!$N9"),0) -> 107420 | K5: =SUM(B5:J5) -> 10266161 | L5: =Abril!D2 -> 0.030982204 | M5: 0.028 | O5: HOY | P5: =TODAY() -> 45987
A6: Mayo | B6: =IFERROR(INDIRECT($A6&"!$N1"),0) -> 0 | C6: =IFERROR(INDIRECT($A6&"!$N2"),0) -> 397929 | D6: =IFERROR(INDIRECT($A6&"!$N3"),0) -> 51180 | E6: =IFERROR(INDIRECT($A6&"!$N4"),0) -> 461810 | F6: =IFERROR(INDIRECT($A6&"!$N5"),0) -> 341521.4 | G6: =IFERROR(INDIRECT($A6&"!$N6"),0) -> 6685655.9 | H6: =IFERROR(INDIRECT($A6&"!$N7"),0) -> 2205766.2 | I6: =IFERROR(INDIRECT($A6&"!$N8"),0) -> 24930.7 | J6: =IFERROR(INDIRECT($A6&"!$N9"),0) -> 29244.57 | K6: =SUM(B6:J6) -> 10198038 | L6: =Mayo!D2 -> 0.04517191 | M6: 0.0172
A7: Junio | B7: =IFERROR(INDIRECT($A7&"!$N1"),0) -> 0 | C7: =IFERROR(INDIRECT($A7&"!$N2"),0) -> 365441 | D7: =IFERROR(INDIRECT($A7&"!$N3"),0) -> 52740 | E7: =IFERROR(INDIRECT($A7&"!$N4"),0) -> 505953 | F7: =IFERROR(INDIRECT($A7&"!$N5"),0) -> 353492 | G7: =IFERROR(INDIRECT($A7&"!$N6"),0) -> 6724481.9 | H7: =IFERROR(INDIRECT($A7&"!$N7"),0) -> 3259732.2 | I7: =IFERROR(INDIRECT($A7&"!$N8"),0) -> 28000 | J7: =IFERROR(INDIRECT($A7&"!$N9"),0) -> 107420 | K7: =SUM(B7:J7) -> 11397260 | L7: =Junio!D2 -> 0.035301276 | M7: 0.016
A8: Julio | B8: =IFERROR(INDIRECT($A8&"!$N1"),0) -> 0 | C8: =IFERROR(INDIRECT($A8&"!$N2"),0) -> 414838 | D8: =IFERROR(INDIRECT($A8&"!$N3"),0) -> 54780 | E8: =IFERROR(INDIRECT($A8&"!$N4"),0) -> 574225 | F8: =IFERROR(INDIRECT($A8&"!$N5"),0) -> 396699 | G8: =IFERROR(INDIRECT($A8&"!$N6"),0) -> 6911392.9 | H8: =IFERROR(INDIRECT($A8&"!$N7"),0) -> 3375673.7 | I8: =IFERROR(INDIRECT($A8&"!$N8"),0) -> 31114.52 | J8: =IFERROR(INDIRECT($A8&"!$N9"),0) -> 107420 | K8: =SUM(B8:J8) -> 11866143 | L8: =Julio!D2 -> 0.078298801 | M8: 0.02
A9: Agosto | B9: =IFERROR(INDIRECT($A9&"!$N1"),0) -> 0 | C9: =IFERROR(INDIRECT($A9&"!$N2"),0) -> 305751.82 | D9: =IFERROR(INDIRECT($A9&"!$N3"),0) -> 51180 | E9: =IFERROR(INDIRECT($A9&"!$N4"),0) -> 683313 | F9: =IFERROR(INDIRECT($A9&"!$N5"),0) -> 340811.4 | G9: =IFERROR(INDIRECT($A9&"!$N6"),0) -> 6685655.9 | H9: =IFERROR(INDIRECT($A9&"!$N7"),0) -> 2344814 | I9: =IFERROR(INDIRECT($A9&"!$N8"),0) -> 31430 | J9: =IFERROR(INDIRECT($A9&"!$N9"),0) -> 107420 | K9: =SUM(B9:J9) -> 10550376 | L9: =Agosto!D2 -> 0.035332511
A10: Septiembre | B10: =IFERROR(INDIRECT($A10&"!$N1"),0) -> 0 | C10: =IFERROR(INDIRECT($A10&"!$N2"),0) -> 449236.8 | D10: =IFERROR(INDIRECT($A10&"!$N3"),0) -> 51180 | E10: =IFERROR(INDIRECT($A10&"!$N4"),0) -> 835525 | F10: =IFERROR(INDIRECT($A10&"!$N5"),0) -> 340811.4 | G10: =IFERROR(INDIRECT($A10&"!$N6"),0) -> 6685655.9 | H10: =IFERROR(INDIRECT($A10&"!$N7"),0) -> 1866788 | I10: =IFERROR(INDIRECT($A10&"!$N8"),0) -> 31430 | J10: =IFERROR(INDIRECT($A10&"!$N9"),0) -> 107420 | K10: =SUM(B10:J10) -> 10368047 | L10: =Septiembre!D2 -> 0.07387484
A11: Octubre | K11: =SUM(B11:J11) -> 0 | L11: 0
A12: Noviembre | K12: =SUM(B12:H12) -> 0 | L12: 0
A13: Diciembre | K13: =SUM(B13:H13) -> 0 | L13: 0
A53: =IFERROR(__xludf.DUMMYFUNCTION("IMPORTHTML(""https://www.ambito.com/contenidos/dolar-mep.html"",""table"",2)"),"#N/A") -> #N/A
A96: var i = 1; [].forEach.call(document.getElementsByTagName("table"),
A97: function(x) { console.log(i++, x); });

Sheet Transacciones
A1: Ticker | B1: Fecha Transaccion | C1: Tipo | D1: Unidades | E1: PCU | F1: PVU | G1: Total Compra | H1: Total Venta | I1: P&L | J1: P&L % | L1: Ventas | M1: Profit
A2: ALUA | B2: Enero | C2: Compra | D2: 15 | E2: 984 | F2: 0 | G2: =E2*D2 -> 14760 | H2: =F2*D2 -> 0 | I2: =IF(H2-G2<0,0,H2-G2) -> 0 | J2: =IFERROR(I2/G2,0) -> 0 | L2: =SUMIF(C2:C914,"Venta",H2:HI914) -> 6988165.1 | M2: =SUM(I2:I914) -> 271590.94
A3: BYMA | B3: Enero | C3: Compra | D3: 28 | E3: 368 | F3: 0 | G3: =E3*D3 -> 10304 | H3: =F3*D3 -> 0 | I3: =IF(H3-G3<0,0,H3-G3) -> 0 | J3: =IFERROR(I3/G3,0) -> 0
A4: CEPU | B4: Enero | C4: Compra | D4: 20 | E4: 1740 | G4: =E4*D4 -> 34800 | H4: =F4*D4 -> 0 | I4: =IF(H4-G4<0,0,H4-G4) -> 0 | J4: =IFERROR(I4/G4,0) -> 0
A5: COME | B5: Enero | C5: Compra | D5: 45 | E5: 234.25 | G5: =E5*D5 -> 10541.25 | H5: =F5*D5 -> 0 | I5: =IF(H5-G5<0,0,H5-G5) -> 0 | J5: =IFERROR(I5/G5,0) -> 0
A6: EDN | B6: Enero | C6: Compra | D6: 20 | E6: 942 | G6: =E6*D6 -> 18840 | H6: =F6*D6 -> 0 | I6: =IF(H6-G6<0,0,H6-G6) -> 0 | J6: =IFERROR(I6/G6,0) -> 0
A7: MORI | B7: Enero | C7: Compra | D7: 100 | E7: 394 | G7: =E7*D7 -> 39400 | H7: =F7*D7 -> 0 | I7: =IF(H7-G7<0,0,H7-G7) -> 0 | J7: =IFERROR(I7/G7,0) -> 0
A8: PAMP | B8: Enero | C8: Compra | D8: 20 | E8: 4200 | G8: =E8*D8 -> 84000 | H8: =F8*D8 -> 0 | I8: =IF(H8-G8<0,0,H8-G8) -> 0 | J8: =IFERROR(I8/G8,0) -> 0
A9: SEMI | B9: Enero | C9: Compra | D9: 7160 | E9: 40 | G9: =E9*D9 -> 286400 | H9: =F9*D9 -> 0 | I9: =IF(H9-G9<0,0,H9-G9) -> 0 | J9: =IFERROR(I9/G9,0) -> 0
A10: TGNO4 | B10: Enero | C10: Compra | D10: 10 | E10: 4435 | G10: =E10*D10 -> 44350 | H10: =F10*D10 -> 0 | I10: =IF(H10-G10<0,0,H10-G10) -> 0 | J10: =IFERROR(I10/G10,0) -> 0
A11: TXAR | B11: Enero | C11: Compra | D11: 23 | E11: 963 | G11: =E11*D11 -> 22149 | H11: =F11*D11 -> 0 | I11: =IF(H11-G11<0,0,H11-G11) -> 0 | J11: =IFERROR(I11/G11,0) -> 0
A12: AE38 | B12: Enero | C12: Compra | D12: 60 | E12: 740 | G12: =E12*D12 -> 44400 | H12: =F12*D12 -> 0 | I12: =IF(H12-G12<0,0,H12-G12) -> 0 | J12: =IFERROR(I12/G12,0) -> 0
A13: AL29 | B13: Enero | C13: Compra | D13: 60 | E13: 826 | G13: =E13*D13 -> 49560 | H13: =F13*D13 -> 0 | I13: =IF(H13-G13<0,0,H13-G13) -> 0 | J13: =IFERROR(I13/G13,0) -> 0
A14: AL30 | B14: Enero | C14: Compra | D14: 163 | E14: 770 | G14: =E14*D14 -> 125510 | H14: =F14*D14 -> 0 | I14: =IF(H14-G14<0,0,H14-G14) -> 0 | J14: =IFERROR(I14/G14,0) -> 0
A15: AMZN | B15: Enero | C15: Compra | D15: 45 | E15: 1895 | G15: =E15*D15 -> 85275 | H15: =F15*D15 -> 0 | I15: =IF(H15-G15<0,0,H15-G15) -> 0 | J15: =IFERROR(I15/G15,0) -> 0
... A36: EDN | B36: Enero | C36: Compra | D36: 5 | E36: 2585 | G36: =E36*D36 -> 12925 | H36: =F36*D36 -> 0 | I36: =IF(H36-G36<0,0,H36-G36) -> 0 | J36: =IFERROR(I36/G36,0) -> 0
A37: S14F5 | B37: Enero | C37: Venta | D37: 17014 | E37: 1.16 | F37: 1.1755 | G37: =E37*D37 -> 19736.24 | H37: =F37*D37 -> 19999.957 | I37: =IF(H37-G37<0,0,H37-G37) -> 263.717 | J37: =IFERROR(I37/G37,0) -> 0.013362069
A38: S17E5 | B38: Enero | C38: Venta | D38: 87209 | E38: 1.256 | F38: 1.31 | G38: =E38*D38 -> 109534.5 | H38: =F38*D38 -> 114243.79 | I38: =IF(H38-G38<0,0,H38-G38) -> 4709.286 | J38: =IFERROR(I38/G38,0) -> 0.042993631
A39: S28F5 | B39: Enero | C39: Compra | D39: 74389 | E39: 1.5 | G39: =E39*D39 -> 111583.5 | H39: =F39*D39 -> 0 | I39: =IF(H39-G39<0,0,H39-G39) -> 0 | J39: =IFERROR(I39/G39,0) -> 0
A40: MR39O | B40: Febrero | C40: Compra | D40: 12 | E40: 1169.9 | G40: =E40*D40 -> 14038.8 | H40: =F40*D40 -> 0 | I40: =IF(H40-G40<0,0,H40-G40) -> 0 | J40: =IFERROR(I40/G40,0) -> 0
A41: Allaria Diversificado Clase A | B41: Febrero | C41: Venta | D41: 3862 | E41: 104.14 | F41: 113.16 | G41: =E41*D41 -> 402188.68 | H41: =F41*D41 -> 437023.92 | I41: =IF(H41-G41<0,0,H41-G41) -> 34835.24 | J41: =IFERROR(I41/G41,0) -> 0.086614173
A42: S16A5 | B42: Febrero | C42: Compra | D42: 391711 | E42: 1.27 | G42: =E42*D42 -> 497472.97 | H42: =F42*D42 -> 0 | I42: =IF(H42-G42<0,0,H42-G42) -> 0 | J42: =IFERROR(I42/G42,0) -> 0
A43: T13F6 | B43: Febrero | C43: Compra | D43: 444714 | E43: 1.11175 | G43: =E43*D43 -> 494410.79 | H43: =F43*D43 -> 0 | I43: =IF(H43-G43<0,0,H43-G43) -> 0 | J43: =IFERROR(I43/G43,0) -> 0
A44: S28F5 | B44: Febrero | C44: Venta | D44: 74389 | E44: 1.5 | F44: 1.5828 | G44: =E44*D44 -> 111583.5 | H44: =F44*D44 -> 117742.91 | I44: =IF(H44-G44<0,0,H44-G44) -> 6159.4092 | J44: =IFERROR(I44/G44,0) -> 0.0552
A45: S14M5 | B45: Febrero | C45: Compra | D45: 493143 | E45: 1.25 | G45: =E45*D45 -> 616428.75 | H45: =F45*D45 -> 0 | I45: =IF(H45-G45<0,0,H45-G45) -> 0 | J45: =IFERROR(I45/G45,0) -> 0
A46: S14M5 | B46: Marzo | C46: Compra | D46: 398464 | E46: 1.26482 | G46: =E46*D46 -> 503985.24 | H46: =F46*D47 -> 0 | I46: =IF(H46-G46<0,0,H46-G46) -> 0 | J46: =IFERROR(I46/G46,0) -> 0
A47: S16A5 | B47: Marzo | C47: Compra | D47: 785211 | E47: 1.2837 | G47: =E47*D47 -> 1007975.4 | H47: =F47*D48 -> 0 | I47: =IF(H47-G47<0,0,H47-G47) -> 0 | J47: =IFERROR(I47/G47,0) -> 0
A48: TGNO4 | B48: Marzo | C48: Venta | D48: 10 | E48: 4435 | F48: 3450 | G48: =E48*D48 -> 44350 | H48: =F48*D48 -> 34500 | I48: =IF(H48-G48<0,0,H48-G48) -> 0 | J48: =IFERROR(I48/G48,0) -> 0
A49: AL29 | B49: Marzo | C49: Venta | D49: 60 | E49: 826 | F49: 854 | G49: =E49*D49 -> 49560 | H49: =F49*D49 -> 51240 | I49: =IF(H49-G49<0,0,H49-G49) -> 1680 | J49: =IFERROR(I49/G49,0) -> 0.033898305
A50: Max Ahorro Pesos Clase A | B50: Marzo | C50: Compra | D50: 93074.373 | E50: 5.34195 | G50: =E50*D50 -> 497198.65 | H50: =F50*D50 -> 0 | I50: =IF(H50-G50<0,0,H50-G50) -> 0 | J50: =IFERROR(I50/G50,0) -> 0
A51: Schroder Renta Plus Clase A | B51: Marzo | C51: Compra | D51: 6370.6252 | E51: 78.473735 | G51: =E51*D51 -> 499926.75 | H51: =F51*D51 -> 0 | I51: =IF(H51-G51<0,0,H51-G51) -> 0 | J51: =IFERROR(I51/G51,0) -> 0
A52: Fima Premium | B52: Marzo | C52: Compra | D52: 5039.09 | E52: 59.534602 | G52: =E52*D52 -> 300000.22 | H52: =F52*D52 -> 0 | I52: =IF(H52-G52<0,0,H52-G52) -> 0 | J52: =IFERROR(I52/G52,0) -> 0
A53: Fima Ahorro Plus | B53: Marzo | C53: Compra | D53: 9615.98 | E53: 103.99364 | G53: =E53*D53 -> 1000000.7 | H53: =F53*D53 -> 0 | I53: =IF(H53-G53<0,0,H53-G53) -> 0 | J53: =IFERROR(I53/G53,0) -> 0
A54: Fima Ahorro Peso | B54: Marzo | C54: Compra | D54: 2374.82 | E54: 421.08574 | G54: =E54*D54 -> 1000002.8 | H54: =F54*D54 -> 0 | I54: =IF(H54-G54<0,0,H54-G54) -> 0 | J54: =IFERROR(I54/G54,0) -> 0
A55: S14M5 | B55: Marzo | C55: Venta | D55: 891607 | E55: 1.25 | F55: 1.26 | G55: =E55*D55 -> 1114508.8 | H55: =F55*D55 -> 1123424.8 | I55: =IF(H55-G55<0,0,H55-G55) -> 8916.07 | J55: =IFERROR(I55/G55,0) -> 0.008
A56: S28A5 | B56: Marzo | C56: Compra | D56: 394448 | E56: 1.266 | G56: =E56*D56 -> 499371.17 | H56: =F56*D56 -> 0 | I56: =IF(H56-G56<0,0,H56-G56) -> 0 | J56: =IFERROR(I56/G56,0) -> 0
A57: S16Y5 | B57: Marzo | C57: Compra | D57: 476337 | E57: 1.306 | G57: =E57*D57 -> 622096.12 | H57: =F57*D57 -> 0 | I57: =IF(H57-G57<0,0,H57-G57) -> 0 | J57: =IFERROR(I57/G57,0) -> 0
A58: Adcap Ahorro Pesos Clase A | B58: Marzo | C58: Compra | D58: 38715.043 | E58: 12.9 | G58: =E58*D58 -> 499424.06 | H58: =F58*D58 -> 0 | I58: =IF(H58-G58<0,0,H58-G58) -> 0 | J58: =IFERROR(I58/G58,0) -> 0
A59: TF36 | B59: Abril | C59: Venta | D59: 444714 | E59: 1.11175 | F59: 1.047 | G59: =E59*D59 -> 494410.79 | H59: =F59*D59 -> 465615.56 | I59: =IF(H59-G59<0,0,H59-G59) -> 0 | J59: =IFERROR(I59/G59,0) -> 0
A60: RUCDD | B60: Abril | C60: Compra | D60: 99 | E60: 1315.0625 | G60: =E60*D60 -> 130191.19 | H60: =F60*D60 -> 0 | I60: =IF(H60-G60<0,0,H60-G60) -> 0 | J60: =IFERROR(I60/G60,0) -> 0
A61: YMCJD | B61: Abril | C61: Compra | D61: 98 | E61: 1197.8 | G61: =E61*D61 -> 117384.4 | H61: =F61*D61 -> 0 | I61: =IF(H61-G61<0,0,H61-G61) -> 0 | J61: =IFERROR(I61/G61,0) -> 0
A62: NDT5D | B62: Abril | C62: Compra | D62: 98 | E62: 1135 | G62: =E62*D62 -> 111230 | H62: =F62*D62 -> 0 | I62: =IF(H62-G62<0,0,H62-G62) -> 0 | J62: =IFERROR(I62/G62,0) -> 0
A63: Fima Premium | B63: Abril | C63: Compra | D63: 10805 | E63: 60.515077 | G63: =E63*D63 -> 653865.41 | H63: =F63*D63 -> 0 | I63: =IF(H63-G63<0,0,H63-G63) -> 0 | J63: =IFERROR(I63/G63,0) -> 0
A64: AL30 | B64: Abril | C64: Venta | D64: 163 | E64: 770 | F64: 740 | G64: =E64*D64 -> 125510 | H64: =F64*D64 -> 120620 | I64: =IF(H64-G64<0,0,H64-G64) -> 0 | J64: =IFERROR(I64/G64,0) -> 0
A65: Schroder Renta Plus Clase A | B65: Abril | C65: Compra | D65: 6669.1459 | E65: 82.169442 | G65: =E65*D65 -> 548000 | H65: =F65*D65 -> 0 | I65: =IF(H65-G65<0,0,H65-G65) -> 0 | J65: =IFERROR(I65/G65,0) -> 0
A66: S16A5 | B66: Abril | C66: Venta | D66: 1203922 | E66: 1.2837 | F66: 1.2859217 | G66: =E66*D66 -> 1545474.7 | H66: =F66*D66 -> 1548149.4 | I66: =IF(H66-G66<0,0,H66-G66) -> 2674.7286 | J66: =IFERROR(I66/G66,0) -> 0.0017306842
A67: S31L5 | B67: Abril | C67: Compra | D67: 732312 | E67: 1.363 | G67: =E67*D67 -> 998141.26 | H67: =F67*D67 -> 0 | I67: =IF(H67-G67<0,0,H67-G67) -> 0 | J67: =IFERROR(I67/G67,0) -> 0
A68: VIST | B68: Abril | C68: Compra | D68: 1 | E68: 18375 | G68: =E68*D68 -> 18375 | H68: =F68*D68 -> 0 | I68: =IF(H68-G68<0,0,H68-G68) -> 0 | J68: =IFERROR(I68/G68,0) -> 0
A69: BYMA | B69: Abril | C69: Compra | D69: 2 | E69: 417 | G69: =E69*D69 -> 834 | H69: =F69*D69 -> 0 | I69: =IF(H69-G69<0,0,H69-G69) -> 0 | J69: =IFERROR(I69/G69,0) -> 0
A70: COME | B70: Abril | C70: Compra | D70: 1 | E70: 141.5 | G70: =E70*D70 -> 141.5 | H70: =F70*D70 -> 0 | I70: =IF(H70-G70<0,0,H70-G70) -> 0 | J70: =IFERROR(I70/G70,0) -> 0
A71: S28A5 | B71: Abril | C71: Venta | D71: 394448 | E71: 1.266 | F71: 1.3081 | G71: =E71*D71 -> 499371.17 | H71: =F71*D71 -> 515977.43 | I71: =IF(H71-G71<0,0,H71-G71) -> 16606.261 | J71: =IFERROR(I71/G71,0) -> 0.033254344
A72: S16Y5 | B72: Abril | C72: Compra | D72: 381253 | E72: 1.3508 | G72: =E72*D72 -> 514996.55 | H72: =F72*D72 -> 0 | I72: =IF(H72-G72<0,0,H72-G72) -> 0 | J72: =IFERROR(I72/G72,0) -> 0
A73: S16Y5 | B73: Mayo | C73: Venta | D73: 857590 | E73: 1.33 | F73: 1.37 | G73: =E73*D73 -> 1140594.7 | H73: =F73*D73 -> 1174898.3 | I73: =IF(H73-G73<0,0,H73-G73) -> 34303.6 | J73: =IFERROR(I73/G73,0) -> 0.030075188
A74: S29G5 | B74: Junio | C74: Compra | D74: 795920 | E74: 1.47261 | G74: =E74*D74 -> 1172079.8 | H74: =F74*D74 -> 0 | I74: =IF(H74-G74<0,0,H74-G74) -> 0 | J74: =IFERROR(I74/G74,0) -> 0
A75: S31L5 | B75: Julio | C75: Compra | D75: 732312 | E75: 1.363 | F75: 1.47 | G75: =E75*D75 -> 998141.26 | H75: =F75*D75 -> 1076498.6 | I75: =IF(H75-G75<0,0,H75-G75) -> 78357.384 | J75: =IFERROR(I75/G75,0) -> 0.078503302
A76: S30S5 | B76: Agosto | C76: Compra | D76: 697617 | E76: 1.51 | G76: =E76*D76 -> 1053401.7 | H76: =F76*D76 -> 0 | I76: =IF(H76-G76<0,0,H76-G76) -> 0 | J76: =IFERROR(I76/G76,0) -> 0
A77: MR39O | B77: Agosto | C77: Venta | D77: 12 | E77: 1169.9 | F77: 797 | G77: =E77*D77 -> 14038.8 | H77: =F77*D77 -> 9564 | I77: =IF(H77-G77<0,0,H77-G77) -> 0 | J77: =IFERROR(I77/G77,0) -> 0
A78: YMCJO | B78: Agosto | C78: Compra | D78: 7 | E78: 1343 | G78: =E78*D78 -> 9401 | H78: =F78*D78 -> 0 | I78: =IF(H78-G78<0,0,H78-G78) -> 0 | J78: =IFERROR(I78/G78,0) -> 0
A79: S29G5 | B79: Septiembre | C79: Venta | D79: 795920 | E79: 1.47261 | F79: 1.5769989 | G79: =E79*D79 -> 1172079.8 | H79: =F79*D79 -> 1255165 | I79: =IF(H79-G79<0,0,H79-G79) -> 83085.249 | J79: =IFERROR(I79/G79,0) -> 0.070887027
A80: D31O5 | B80: Septiembre | C80: Compra | D80: 490 | E80: 285.30612 | G80: =E80*D80 -> 139800 | H80: =F80*D80 -> 0 | I80: =IF(H80-G80<0,0,H80-G80) -> 0 | J80: =IFERROR(I80/G80,0) -> 0
A81: S12S5 | B81: Septiembre | C81: Compra | D81: 40262 | E81: 1.53 | G81: =E81*D81 -> 61600.86 | H81: =F81*D81 -> 0 | I81: =IF(H81-G81<0,0,H81-G81) -> 0 | J81: =IFERROR(I81/G81,0) -> 0
A82: S31O5 | B82: Septiembre | C82: Compra | D82: 462349 | E82: 1.249 | G82: =E82*D82 -> 577473.9 | H82: =F82*D82 -> 0 | I82: =IF(H82-G82<0,0,H82-G82) -> 0 | J82: =IFERROR(I82/G82,0) -> 0

Sheet Septiembre
A1: Portfolio De Inversiones | C1: P&L | D1: P&L % | E1: Valor Medio Total | F1: Valor Portolio | G1: Efectivo | H1: Medio+Efectivo | I1: Portfolio+Efectivo | M1: Opc/Futuros | N1: =SUMIF(B4:B1001,M1,G4:G1001) -> 0
C2: =SUM(I5:I1001) -> 705857.1 | D2: =(F2/E2)-1 -> 0.07387484 | E2: =SUM(G5:G1001) -> 9554769.9 | F2: =SUM(H5:H1001) -> 10260627 | G2: =N9+SUMIF(Transacciones!C2:C1001,"Venta",Transacciones!I2:I1001) -> 300653.56 | H2: =E2+G2 -> 9855423.5 | I2: =F2+G2 -> 10561281 | M2: Acciones | N2: =SUMIF($B$5:B1001,M2,$H$5:H1001) -> 449236.8
M3: Bonos | N3: =SUMIF($B$5:B1002,M3,$H$5:H1002) -> 51180
A4: Ticker | B4: Tipo | C4: Cantidad | D4: % Portfolio | E4: Costo medio | F4: Precio Actual | G4: Valor Medio | H4: Valor de Mercado | I4: P&L | J4: P&L % | K4: Broker | M4: Cedear | N4: =SUMIF($B$5:B1003,M4,$H$5:H1003) -> 835525 | P4: P&L Julio/Junio
A5: ALUA | B5: Acciones | C5: =SUMIFS(Transacciones!$D$2:$D1001,Transacciones!$A$2:$A1001,A5,Transacciones!$C$2:$C1001,"Compra")-SUMIFS(Transacciones!$D$2:$D1001,Transacciones!$A$2:$A1001,A5,Transacciones!$C$2:$C1001,"Venta") -> 15 | D5: =(H5/$F$2) -> 0.001476518 | E5: =IFERROR((SUMIFS(Transacciones!$G$2:$G1001,Transacciones!$A$2:$A1001,A5,Transacciones!$C$2:$C1001,"Compra")-SUMIFS(Transacciones!$G$2:$G1001,Transacciones!$A$2:$A1001,A5,Transacciones!$C$2:$C1001,"Venta"))/C5,0) -> 984 | F5: =IFERROR(__xludf.DUMMYFUNCTION("GOOGLEFINANCE(""BCBA:""&A5,""price"")"),1010.0) -> 1010 | G5: =C5*E5 -> 14760 | H5: =F5*C5 -> 15150 | I5: =H5-G5 -> 390 | J5: =IFERROR(I5/G5,0) -> 0.026422764 | K5: Eco | M5: ON | N5: =SUMIF($B$5:B1004,M5,$H$5:H1004) -> 340811.4 | P5: =SUM(I5-Junio!I5) -> 4410
A6: BYMA | B6: Acciones | C6: =SUMIFS(Transacciones!$D$2:$D1001,Transacciones!$A$2:$A1001,A6,Transacciones!$C$2:$C1001,"Compra")-SUMIFS(Transacciones!$D$2:$D1001,Transacciones!$A$2:$A1001,A6,Transacciones!$C$2:$C1001,"Venta") -> 30 | D6: =(H6/$F$2) -> 0.00085009425 | E6: =IFERROR((SUMIFS(Transacciones!$G$2:$G1001,Transacciones!$A$2:$A1001,A6,Transacciones!$C$2:$C1001,"Compra")-SUMIFS(Transacciones!$G$2:$G1001,Transacciones!$A$2:$A1001,A6,Transacciones!$C$2:$C1001,"Venta"))/C6,0) -> 371.26667 | F6: =IFERROR(__xludf.DUMMYFUNCTION("GOOGLEFINANCE(""BCBA:""&A6,""price"")"),290.75) -> 290.75 | G6: =C6*E6 -> 11138 | H6: =F6*C6 -> 8722.5 | I6: =H6-G6 -> -2415.5 | J6: =IFERROR(I6/G6,0) -> -0.21687017 | K6: Eco | M6: FCI | N6: =SUMIF($B$5:B1005,M6,$H$5:H1005) -> 6685655.9 | P6: =SUM(I6-Junio!I6) -> 2962.5
A7: CEPU | B7: Acciones | C7: =SUMIFS(Transacciones!$D$2:$D1001,Transacciones!$A$2:$A1001,A7,Transacciones!$C$2:$C1001,"Compra")-SUMIFS(Transacciones!$D$2:$D1001,Transacciones!$A$2:$A1001,A7,Transacciones!$C$2:$C1001,"Venta") -> 20 | D7: =(H7/$F$2) -> 0.0043662049 | E7: =IFERROR((SUMIFS(Transacciones!$G$2:$G1001,Transacciones!$A$2:$A1001,A7,Transacciones!$C$2:$C1001,"Compra")-SUMIFS(Transacciones!$G$2:$G1001,Transacciones!$A$2:$A1001,A7,Transacciones!$C$2:$C1001,"Venta"))/C7,0) -> 1740 | F7: =IFERROR(__xludf.DUMMYFUNCTION("GOOGLEFINANCE(""BCBA:""&A7,""price"")"),2240.0) -> 2240 | G7: =C7*E7 -> 34800 | H7: =F7*C7 -> 44800 | I7: =H7-G7 -> 10000 | J7: =IFERROR(I7/G7,0) -> 0.28735632 | K7: Eco | M7: Letras | N7: =SUMIF($B$5:B1006,M7,$H$5:H1006) -> 1866788 | P7: =SUM(I7-Junio!I7) -> 16400
A8: COME | B8: Acciones | C8: =SUMIFS(Transacciones!$D$2:$D1001,Transacciones!$A$2:$A1001,A8,Transacciones!$C$2:$C1001,"Compra")-SUMIFS(Transacciones!$D$2:$D1001,Transacciones!$A$2:$A1001,A8,Transacciones!$C$2:$C1001,"Venta") -> 46 | D8: =(H8/$F$2) -> 0.00033085697 | E8: =IFERROR((SUMIFS(Transacciones!$G$2:$G1001,Transacciones!$A$2:$A1001,A8,Transacciones!$C$2:$C1001,"Compra")-SUMIFS(Transacciones!$G$2:$G1001,Transacciones!$A$2:$A1001,A8,Transacciones!$C$2:$C1001,"Venta"))/C8,0) -> 232.2337 | F8: =IFERROR(__xludf.DUMMYFUNCTION("GOOGLEFINANCE(""BCBA:""&A8,""price"")"),73.8) -> 73.8 | G8: =C8*E8 -> 10682.75 | H8: =F8*C8 -> 3394.8 | I8: =H8-G8 -> -7287.95 | J8: =IFERROR(I8/G8,0) -> -0.68221666 | K8: Eco | M8: Cripto | N8: =SUMIF($B$5:B1007,M8,$H$5:H1007) -> 31430 | P8: =SUM(I8-Junio!I8) -> -2033.2
A9: EDN | B9: Acciones | C9: =SUMIFS(Transacciones!$D$2:$D1001,Transacciones!$A$2:$A1001,A9,Transacciones!$C$2:$C1001,"Compra")-SUMIFS(Transacciones!$D$2:$D1001,Transacciones!$A$2:$A1001,A9,Transacciones!$C$2:$C1001,"Venta") -> 25 | D9: =(H9/$F$2) -> 0.0038983972 | E9: =IFERROR((SUMIFS(Transacciones!$G$2:$G1001,Transacciones!$A$2:$A1001,A9,Transacciones!$C$2:$C1001,"Compra")-SUMIFS(Transacciones!$G$2:$G1001,Transacciones!$A$2:$A1001,A9,Transacciones!$C$2:$C1001,"Venta"))/C9,0) -> 1270.6 | F9: =IFERROR(__xludf.DUMMYFUNCTION("GOOGLEFINANCE(""BCBA:""&A9,""price"")"),1600.0) -> 1600 | G9: =C9*E9 -> 31765 | H9: =F9*C9 -> 40000 | I9: =H9-G9 -> 8235 | J9: =IFERROR(I9/G9,0) -> 0.2592476 | K9: Eco | M9: Efectivo | N9: 107420 | P9: =SUM(I9-Junio!I9) -> 1875
A10: MORI | B10: Acciones | C10: =SUMIFS(Transacciones!$D$2:$D1001,Transacciones!$A$2:$A1001,A10,Transacciones!$C$2:$C1001,"Compra")-SUMIFS(Transacciones!$D$2:$D1001,Transacciones!$A$2:$A1001,A10,Transacciones!$C$2:$C1001,"Venta") -> 100 | D10: =(H10/$F$2) -> 0.00047268067 | E10: =IFERROR((SUMIFS(Transacciones!$G$2:$G1001,Transacciones!$A$2:$A1001,A10,Transacciones!$C$2:$C1001,"Compra")-SUMIFS(Transacciones!$G$2:$G1001,Transacciones!$A$2:$A1001,A10,Transacciones!$C$2:$C1001,"Venta"))/C10,0) -> 394 | F10: =IFERROR(__xludf.DUMMYFUNCTION("GOOGLEFINANCE(""BCBA:""&A10,""price"")"),48.5) -> 48.5 | G10: =C10*E10 -> 39400 | H10: =F10*C10 -> 4850 | I10: =H10-G10 -> -34550 | J10: =IFERROR(I10/G10,0) -> -0.87690355 | K10: Eco | M10: Total | N10: =SUM(N1:N9) -> 10368047
A11: PAMP | B11: Acciones | C11: =SUMIFS(Transacciones!$D$2:$D1001,Transacciones!$A$2:$A1001,A11,Transacciones!$C$2:$C1001,"Compra")-SUMIFS(Transacciones!$D$2:$D1001,Transacciones!$A$2:$A1001,A11,Transacciones!$C$2:$C1001,"Venta") -> 20 | D11: =(H11/$F$2) -> 0.010515927 | E11: =IFERROR((SUMIFS(Transacciones!$G$2:$G1001,Transacciones!$A$2:$A1001,A11,Transacciones!$C$2:$C1001,"Compra")-SUMIFS(Transacciones!$G$2:$G1001,Transacciones!$A$2:$A1001,A11,Transacciones!$C$2:$C1001,"Venta"))/C11,0) -> 4200 | F11: =IFERROR(__xludf.DUMMYFUNCTION("GOOGLEFINANCE(""BCBA:""&A11,""price"")"),5395.0) -> 5395 | G11: =C11*E11 -> 84000 | H11: =F11*C11 -> 107900 | I11: =H11-G11 -> 23900 | J11: =IFERROR(I11/G11,0) -> 0.28452381 | K11: Eco
A12: SEMI | B12: Acciones | C12: =SUMIFS(Transacciones!$D$2:$D1001,Transacciones!$A$2:$A1001,A12,Transacciones!$C$2:$C1001,"Compra")-SUMIFS(Transacciones!$D$2:$D1001,Transacciones!$A$2:$A1001,A12,Transacciones!$C$2:$C1001,"Venta") -> 7660 | D12: =(H12/$F$2) -> 0.020082009 | E12: =IFERROR((SUMIFS(Transacciones!$G$2:$G1001,Transacciones!$A$2:$A1001,A12,Transacciones!$C$2:$C1001,"Compra")-SUMIFS(Transacciones!$G$2:$G1001,Transacciones!$A$2:$A1001,A12,Transacciones!$C$2:$C1001,"Venta"))/C12,0) -> 40 | F12: =IFERROR(__xludf.DUMMYFUNCTION("GOOGLEFINANCE(""BCBA:""&A12,""price"")"),26.9) -> 26.9 | G12: =C12*E12 -> 306400 | H12: =F12*C12 -> 206054 | I12: =H12-G12 -> -100346 | J12: =IFERROR(I12/G12,0) -> -0.3275 | K12: Eco | M12: Eco | N12: =SUMIF($K$5:$K1001,M12,$H$5:$H1001) -> 1365009.8
A13: TXAR | B13: Acciones | C13: =SUMIFS(Transacciones!$D$2:$D1001,Transacciones!$A$2:$A1001,A13,Transacciones!$C$2:$C1001,"Compra")-SUMIFS(Transacciones!$D$2:$D1001,Transacciones!$A$2:$A1001,A13,Transacciones!$C$2:$C1001,"Venta") -> 23 | D13: =(H13/$F$2) -> 0.0017899004 | E13: =IFERROR((SUMIFS(Transacciones!$G$2:$G1001,Transacciones!$A$2:$A1001,A13,Transacciones!$C$2:$C1001,"Compra")-SUMIFS(Transacciones!$G$2:$G1001,Transacciones!$A$2:$A1001,A13,Transacciones!$C$2:$C1001,"Venta"))/C13,0) -> 963 | F13: =IFERROR(__xludf.DUMMYFUNCTION("GOOGLEFINANCE(""BCBA:""&A13,""price"")"),798.5) -> 798.5 | G13: =C13*E13 -> 22149 | H13: =F13*C13 -> 18365.5 | I13: =H13-G13 -> -3783.5 | J13: =IFERROR(I13/G13,0) -> -0.17082035 | K13: Eco | M13: Ppi | N13: =SUMIF($K$5:$K1002,M13,$H$5:$H1002) -> 5729735.1
A14: AMZN | B14: Cedear | C14: =SUMIFS(Transacciones!$D$2:$D1001,Transacciones!$A$2:$A1001,A14,Transacciones!$C$2:$C1001,"Compra")-SUMIFS(Transacciones!$D$2:$D1001,Transacciones!$A$2:$A1001,A14,Transacciones!$C$2:$C1001,"Venta") -> 45 | D14: =(H14/$F$2) -> 0.010780043 | E14: =IFERROR((SUMIFS(Transacciones!$G$2:$G1001,Transacciones!$A$2:$A1001,A14,Transacciones!$C$2:$C1001,"Compra")-SUMIFS(Transacciones!$G$2:$G1001,Transacciones!$A$2:$A1001,A14,Transacciones!$C$2:$C1001,"Venta"))/C14,0) -> 1895 | F14: =IFERROR(__xludf.DUMMYFUNCTION("GOOGLEFINANCE(""BCBA:""&A14,""price"")"),2458.0) -> 2458 | G14: =C14*E14 -> 85275 | H14: =F14*C14 -> 110610 | I14: =H14-G14 -> 25335 | J14: =IFERROR(I14/G14,0) -> 0.29709763 | K14: Eco | M14: Binance | N14: =SUMIF($K$5:$K1003,M14,$H$5:$H1003) -> 31430
A15: BABA | B15: Cedear | C15: =SUMIFS(Transacciones!$D$2:$D1001,Transacciones!$A$2:$A1001,A15,Transacciones!$C$2:$C1001,"Compra")-SUMIFS(Transacciones!$D$2:$D1001,Transacciones!$A$2:$A1001,A15,Transacciones!$C$2:$C1001,"Venta") -> 1 | D15: =(H15/$F$2) -> 0.0026333673 | E15: =IFERROR((SUMIFS(Transacciones!$G$2:$G1001,Transacciones!$A$2:$A1001,A15,Transacciones!$C$2:$C1001,"Compra")-SUMIFS(Transacciones!$G$2:$G1001,Transacciones!$A$2:$A1001,A15,Transacciones!$C$2:$C1001,"Venta"))/C15,0) -> 11400 | F15: =IFERROR(__xludf.DUMMYFUNCTION("GOOGLEFINANCE(""BCBA:""&A15,""price"")"),27020.0) -> 27020 | G15: =C15*E15 -> 11400 | H15: =F15*C15 -> 27020 | I15: =H15-G15 -> 15620 | J15: =IFERROR(I15/G15,0) -> 1.3701754 | K15: Eco | M15: Galicia | N15: =SUMIF($K$5:$K1004,M15,$H$5:$H1004) -> 3134452.1
A16: CDE | B16: Cedear | C16: =SUMIFS(Transacciones!$D$2:$D1001,Transacciones!$A$2:$A1001,A16,Transacciones!$C$2:$C1001,"Compra")-SUMIFS(Transacciones!$D$2:$D1001,Transacciones!$A$2:$A1001,A16,Transacciones!$C$2:$C1001,"Venta") -> 5 | D16: =(H16/$F$2) -> 0.0100335 | E16: =IFERROR((SUMIFS(Transacciones!$G$2:$G1001,Transacciones!$A$2:$A1001,A16,Transacciones!$C$2:$C1001,"Compra")-SUMIFS(Transacciones!$G$2:$G1001,Transacciones!$A$2:$A1001,A16,Transacciones!$C$2:$C1001,"Venta"))/C16,0) -> 7400 | F16: 20590 | G16: =C16*E16 -> 37000 | H16: =F16*C16 -> 102950 | I16: =H16-G16 -> 65950 | J16: =IFERROR(I16/G16,0) -> 1.7824324 | K16: Eco | M16: Efectivo | N16: 107420
A17: ETHA | B17: Cedear | C17: 5 | D17: =(H17/$F$2) -> 0.0045367598 | E17: =IFERROR((SUMIFS(Transacciones!$G$2:$G1001,Transacciones!$A$2:$A1001,A17,Transacciones!$C$2:$C1001,"Compra")-SUMIFS(Transacciones!$G$2:$G1001,Transacciones!$A$2:$A1001,A17,Transacciones!$C$2:$C1001,"Venta"))/C17,0) -> 5970 | F17: 9310 | G17: =C17*E17 -> 29850 | H17: =F17*C17 -> 46550 | I17: =H17-G17 -> 16700 | J17: =IFERROR(I17/G17,0) -> 0.55946399 | K17: Eco | M17: Total | N17: =SUM(N12:N16) -> 10368047
A18: GOOGL | B18: Cedear | C18: =SUMIFS(Transacciones!$D$2:$D1001,Transacciones!$A$2:$A1001,A18,Transacciones!$C$2:$C1001,"Compra")-SUMIFS(Transacciones!$D$2:$D1001,Transacciones!$A$2:$A1001,A18,Transacciones!$C$2:$C1001,"Venta") -> 25 | D18: =(H18/$F$2) -> 0.020515315 | E18: =IFERROR((SUMIFS(Transacciones!$G$2:$G1001,Transacciones!$A$2:$A1001,A18,Transacciones!$C$2:$C1001,"Compra")-SUMIFS(Transacciones!$G$2:$G1001,Transacciones!$A$2:$A1001,A18,Transacciones!$C$2:$C1001,"Venta"))/C18,0) -> 3995 | F18: =IFERROR(__xludf.DUMMYFUNCTION("GOOGLEFINANCE(""BCBA:""&A18,""price"")"),8420.0) -> 8420 | G18: =C18*E18 -> 99875 | H18: =F18*C18 -> 210500 | I18: =H18-G18 -> 110625 | J18: =IFERROR(I18/G18,0) -> 1.1076345 | K18: Eco
A19: IBM | B19: Cedear | C19: =SUMIFS(Transacciones!$D$2:$D1001,Transacciones!$A$2:$A1001,A19,Transacciones!$C$2:$C1001,"Compra")-SUMIFS(Transacciones!$D$2:$D1001,Transacciones!$A$2:$A1001,A19,Transacciones!$C$2:$C1001,"Venta") -> 1 | D19: =(H19/$F$2) -> 0.0030232071 | E19: =IFERROR((SUMIFS(Transacciones!$G$2:$G1001,Transacciones!$A$2:$A1001,A19,Transacciones!$C$2:$C1001,"Compra")-SUMIFS(Transacciones!$G$2:$G1001,Transacciones!$A$2:$A1001,A19,Transacciones!$C$2:$C1001,"Venta"))/C19,0) -> 17850 | F19: =IFERROR(__xludf.DUMMYFUNCTION("GOOGLEFINANCE(""BCBA:""&A19,""price"")"),31020.0) -> 31020 | G19: =C19*E19 -> 17850 | H19: =F19*C19 -> 31020 | I19: =H19-G19 -> 13170 | J19: =IFERROR(I19/G19,0) -> 0.73781513 | K19: Eco
A20: KO | B20: Cedear | C20: =SUMIFS(Transacciones!$D$2:$D1001,Transacciones!$A$2:$A1001,A20,Transacciones!$C$2:$C1001,"Compra")-SUMIFS(Transacciones!$D$2:$D1001,Transacciones!$A$2:$A1001,A20,Transacciones!$C$2:$C1001,"Venta") -> 1 | D20: =(H20/$F$2) -> 0.0021675089 | E20: =IFERROR((SUMIFS(Transacciones!$G$2:$G1001,Transacciones!$A$2:$A1001,A20,Transacciones!$C$2:$C1001,"Compra")-SUMIFS(Transacciones!$G$2:$G1001,Transacciones!$A$2:$A1001,A20,Transacciones!$C$2:$C1001,"Venta"))/C20,0) -> 15000 | F20: =IFERROR(__xludf.DUMMYFUNCTION("GOOGLEFINANCE(""BCBA:""&A20,""price"")"),22240.0) -> 22240 | G20: =C20*E20 -> 15000 | H20: =F20*C20 -> 22240 | I20: =H20-G20 -> 7240 | J20: =IFERROR(I20/G20,0) -> 0.48266667 | K20: Eco
A21: LAC | B21: Cedear | C21: =SUMIFS(Transacciones!$D$2:$D1001,Transacciones!$A$2:$A1001,A21,Transacciones!$C$2:$C1001,"Compra")-SUMIFS(Transacciones!$D$2:$D1001,Transacciones!$A$2:$A1001,A21,Transacciones!$C$2:$C1001,"Venta") -> 9 | D21: =(H21/$F$2) -> 0.0069864152 | E21: =IFERROR((SUMIFS(Transacciones!$G$2:$G1001,Transacciones!$A$2:$A1001,A21,Transacciones!$C$2:$C1001,"Compra")-SUMIFS(Transacciones!$G$2:$G1001,Transacciones!$A$2:$A1001,A21,Transacciones!$C$2:$C1001,"Venta"))/C21,0) -> 3655 | F21: =IFERROR(__xludf.DUMMYFUNCTION("GOOGLEFINANCE(""BCBA:""&A21,""price"")"),7965.0) -> 7965 | G21: =C21*E21 -> 32895 | H21: =F21*C21 -> 71685 | I21: =H21-G21 -> 38790 | J21: =IFERROR(I21/G21,0) -> 1.1792066 | K21: Eco
A22: MSFT | B22: Cedear | C22: =SUMIFS(Transacciones!$D$2:$D1001,Transacciones!$A$2:$A1001,A22,Transacciones!$C$2:$C1001,"Compra")-SUMIFS(Transacciones!$D$2:$D1001,Transacciones!$A$2:$A1001,A22,Transacciones!$C$2:$C1001,"Venta") -> 1 | D22: =(H22/$F$2) -> 0.0024199301 | E22: =IFERROR((SUMIFS(Transacciones!$G$2:$G1001,Transacciones!$A$2:$A1001,A22,Transacciones!$C$2:$C1001,"Compra")-SUMIFS(Transacciones!$G$2:$G1001,Transacciones!$A$2:$A1001,A22,Transacciones!$C$2:$C1001,"Venta"))/C22,0) -> 17775 | F22: =IFERROR(__xludf.DUMMYFUNCTION("GOOGLEFINANCE(""BCBA:""&A22,""price"")"),24830.0) -> 24830 | G22: =C22*E22 -> 17775 | H22: =F22*C22 -> 24830 | I22: =H22-G22 -> 7055 | J22: =IFERROR(I22/G22,0) -> 0.39690577 | K22: Eco
A23: PFE | B23: Cedear | C23: =SUMIFS(Transacciones!$D$2:$D1001,Transacciones!$A$2:$A1001,A23,Transacciones!$C$2:$C1001,"Compra")-SUMIFS(Transacciones!$D$2:$D1001,Transacciones!$A$2:$A1001,A23,Transacciones!$C$2:$C1001,"Venta") -> 1 | D23: =(H23/$F$2) -> 0.00095803112 | E23: =IFERROR((SUMIFS(Transacciones!$G$2:$G1001,Transacciones!$A$2:$A1001,A23,Transacciones!$C$2:$C1001,"Compra")-SUMIFS(Transacciones!$G$2:$G1001,Transacciones!$A$2:$A1001,A23,Transacciones!$C$2:$C1001,"Venta"))/C23,0) -> 7790 | F23: =IFERROR(__xludf.DUMMYFUNCTION("GOOGLEFINANCE(""BCBA:""&A23,""price"")"),9830.0) -> 9830 | G23: =C23*E23 -> 7790 | H23: =F23*C23 -> 9830 | I23: =H23-G23 -> 2040 | J23: =IFERROR(I23/G23,0) -> 0.2618742 | K23: Eco
A24: SPY | B24: Cedear | C24: =SUMIFS(Transacciones!$D$2:$D1001,Transacciones!$A$2:$A1001,A24,Transacciones!$C$2:$C1001,"Compra")-SUMIFS(Transacciones!$D$2:$D1001,Transacciones!$A$2:$A1001,A24,Transacciones!$C$2:$C1001,"Venta") -> 2 | D24: =(H24/$F$2) -> 0.010145579 | E24: =IFERROR((SUMIFS(Transacciones!$G$2:$G1001,Transacciones!$A$2:$A1001,A24,Transacciones!$C$2:$C1001,"Compra")-SUMIFS(Transacciones!$G$2:$G1001,Transacciones!$A$2:$A1001,A24,Transacciones!$C$2:$C1001,"Venta"))/C24,0) -> 35825 | F24: =IFERROR(__xludf.DUMMYFUNCTION("GOOGLEFINANCE(""BCBA:""&A24,""price"")"),52050.0) -> 52050 | G24: =C24*E24 -> 71650 | H24: =F24*C24 -> 104100 | I24: =H24-G24 -> 32450 | J24: =IFERROR(I24/G24,0) -> 0.45289602 | K24: Eco
A25: VIST | B25: Cedear | C25: =SUMIFS(Transacciones!$D$2:$D1001,Transacciones!$A$2:$A1001,A25,Transacciones!$C$2:$C1001,"Compra")-SUMIFS(Transacciones!$D$2:$D1001,Transacciones!$A$2:$A1001,A25,Transacciones!$C$2:$C1001,"Venta") -> 3 | D25: =(H25/$F$2) -> 0.0072305523 | E25: =IFERROR((SUMIFS(Transacciones!$G$2:$G1001,Transacciones!$A$2:$A1001,A25,Transacciones!$C$2:$C1001,"Compra")-SUMIFS(Transacciones!$G$2:$G1001,Transacciones!$A$2:$A1001,A25,Transacciones!$C$2:$C1001,"Venta"))/C25,0) -> 21041.667 | F25: =IFERROR(__xludf.DUMMYFUNCTION("GOOGLEFINANCE(""BCBA:""&A25,""price"")"),24730.0) -> 24730 | G25: =C25*E25 -> 63125 | H25: =F25*C25 -> 74190 | I25: =H25-G25 -> 11065 | J25: =IFERROR(I25/G25,0) -> 0.17528713 | K25: Eco
A26: AE38 | B26: Bonos | C26: =SUMIFS(Transacciones!$D$2:$D1001,Transacciones!$A$2:$A1001,A26,Transacciones!$C$2:$C1001,"Compra")-SUMIFS(Transacciones!$D$2:$D1001,Transacciones!$A$2:$A1001,A26,Transacciones!$C$2:$C1001,"Venta") -> 60 | D26: =(H26/$F$2) -> 0.0049879993 | E26: =IFERROR((SUMIFS(Transacciones!$G$2:$G1001,Transacciones!$A$2:$A1001,A26,Transacciones!$C$2:$C1001,"Compra")-SUMIFS(Transacciones!$G$2:$G1001,Transacciones!$A$2:$A1001,A26,Transacciones!$C$2:$C1001,"Venta"))/C26,0) -> 740 | F26: 853 | G26: =C26*E26 -> 44400 | H26: =F26*C26 -> 51180 | I26: =H26-G26 -> 6780 | J26: =IFERROR(I26/G26,0) -> 0.1527027 | K26: Eco
A27: YMCJO | B27: ON | C27: =SUMIFS(Transacciones!$D$2:$D1001,Transacciones!$A$2:$A1001,A27,Transacciones!$C$2:$C1001,"Compra")-SUMIFS(Transacciones!$D$2:$D1001,Transacciones!$A$2:$A1001,A27,Transacciones!$C$2:$C1001,"Venta") -> 26 | D27: =(H27/$F$2) -> 0.0028329653 | E27: =IFERROR((SUMIFS(Transacciones!$G$2:$G1001,Transacciones!$A$2:$A1001,A27,Transacciones!$C$2:$C1001,"Compra")-SUMIFS(Transacciones!$G$2:$G1001,Transacciones!$A$2:$A1001,A27,Transacciones!$C$2:$C1001,"Venta"))/C27,0) -> 1220.9615 | F27: 1118 | G27: =C27*E27 -> 31745 | H27: =F27*C27 -> 29068 | I27: =H27-G27 -> -2677 | J27: =IFERROR(I27/G27,0) -> -0.084328241 | K27: Eco
A28: NDT5D | B28: ON | C28: 98 | D28: =(H28/$F$2) -> 0.0085988312 | E28: =IFERROR((SUMIFS(Transacciones!$G$2:$G1001,Transacciones!$A$2:$A1001,A28,Transacciones!$C$2:$C1001,"Compra")-SUMIFS(Transacciones!$G$2:$G1001,Transacciones!$A$2:$A1001,A28,Transacciones!$C$2:$C1001,"Venta"))/C28,0) -> 1135 | F28: 900.3 | G28: =C28*E28 -> 111230 | H28: =F28*C28 -> 88229.4 | I28: =H28-G28 -> -23000.6 | J28: =IFERROR(I28/G28,0) -> -0.20678414 | K28: Ppi
A29: RUCDD | B29: ON | C29: =SUMIFS(Transacciones!$D$2:$D1001,Transacciones!$A$2:$A1001,A29,Transacciones!$C$2:$C1001,"Compra")-SUMIFS(Transacciones!$D$2:$D1001,Transacciones!$A$2:$A1001,A29,Transacciones!$C$2:$C1001,"Venta") -> 99 | D29: =(H29/$F$2) -> 0.01111511 | E29: =IFERROR((SUMIFS(Transacciones!$G$2:$G1001,Transacciones!$A$2:$A1001,A29,Transacciones!$C$2:$C1001,"Compra")-SUMIFS(Transacciones!$G$2:$G1001,Transacciones!$A$2:$A1001,A29,Transacciones!$C$2:$C1001,"Venta"))/C29,0) -> 1315.0625 | F29: 1152 | G29: =C29*E29 -> 130191.19 | H29: =F29*C29 -> 114048 | I29: =H29-G29 -> -16143.188 | J29: =IFERROR(I29/G29,0) -> -0.12399601 | K29: Ppi
A30: YMCJD | B30: ON | C30: =SUMIFS(Transacciones!$D$2:$D1001,Transacciones!$A$2:$A1001,A30,Transacciones!$C$2:$C1001,"Compra")-SUMIFS(Transacciones!$D$2:$D1001,Transacciones!$A$2:$A1001,A30,Transacciones!$C$2:$C1001,"Venta") -> 98 | D30: =(H30/$F$2) -> 0.010668549 | E30: =IFERROR((SUMIFS(Transacciones!$G$2:$G1001,Transacciones!$A$2:$A1001,A30,Transacciones!$C$2:$C1001,"Compra")-SUMIFS(Transacciones!$G$2:$G1001,Transacciones!$A$2:$A1001,A30,Transacciones!$C$2:$C1001,"Venta"))/C30,0) -> 1197.8 | F30: 1117 | G30: =C30*E30 -> 117384.4 | H30: =F30*C30 -> 109466 | I30: =H30-G30 -> -7918.4 | J30: =IFERROR(I30/G30,0) -> -0.067457005 | K30: Ppi
A31: Adcap Ahorro Pesos Clase A | B31: FCI | C31: =SUMIFS(Transacciones!$D$2:$D1001,Transacciones!$A$2:$A1001,A31,Transacciones!$C$2:$C1001,"Compra")-SUMIFS(Transacciones!$D$2:$D1001,Transacciones!$A$2:$A1001,A31,Transacciones!$C$2:$C1001,"Venta") -> 38715.043 | D31: =(H31/$F$2) -> 0.051224117 | E31: =IFERROR((SUMIFS(Transacciones!$G$2:$G1001,Transacciones!$A$2:$A1001,A31,Transacciones!$C$2:$C1001,"Compra")-SUMIFS(Transacciones!$G$2:$G1001,Transacciones!$A$2:$A1001,A31,Transacciones!$C$2:$C1001,"Venta"))/C31,0) -> 12.9 | F31: 13.5759 | G31: =C31*E31 -> 499424.06 | H31: =F31*C31 -> 525591.56 | I31: =H31-G31 -> 26167.498 | J31: =IFERROR(I31/G31,0) -> 0.052395349 | K31: Ppi
A32: Allaria Diversificado Clase A | B32: FCI | C32: =SUMIFS(Transacciones!$D$2:$D1001,Transacciones!$A$2:$A1001,A32,Transacciones!$C$2:$C1001,"Compra")-SUMIFS(Transacciones!$D$2:$D1001,Transacciones!$A$2:$A1001,A32,Transacciones!$C$2:$C1001,"Venta") -> 10501.993 | D32: =(H32/$F$2) -> 0.12218281 | E32: =IFERROR((SUMIFS(Transacciones!$G$2:$G1001,Transacciones!$A$2:$A1001,A32,Transacciones!$C$2:$C1001,"Compra")-SUMIFS(Transacciones!$G$2:$G1001,Transacciones!$A$2:$A1001,A32,Transacciones!$C$2:$C1001,"Venta"))/C32,0) -> 104.14 | F32: 119.3747 | G32: =C32*E32 -> 1093677.6 | H32: =F32*C32 -> 1253672.3 | I32: =H32-G32 -> 159994.71 | J32: =IFERROR(I32/G32,0) -> 0.14629057 | K32: Ppi
A33: Delta Recursos Naturales Clase A | B33: FCI | C33: =SUMIFS(Transacciones!$D$2:$D1001,Transacciones!$A$2:$A1001,A33,Transacciones!$C$2:$C1001,"Compra")-SUMIFS(Transacciones!$D$2:$D1001,Transacciones!$A$2:$A1001,A33,Transacciones!$C$2:$C1001,"Venta") -> 120.775 | D33: =(H33/$F$2) -> 0.011384561 | E33: =IFERROR((SUMIFS(Transacciones!$G$2:$G1001,Transacciones!$A$2:$A1001,A33,Transacciones!$C$2:$C1001,"Compra")-SUMIFS(Transacciones!$G$2:$G1001,Transacciones!$A$2:$A1001,A33,Transacciones!$C$2:$C1001,"Venta"))/C33,0) -> 1067 | F33: 967.193 | G33: =C33*E33 -> 128866.93 | H33: =F33*C33 -> 116812.73 | I33: =H33-G33 -> -12054.19 | J33: =IFERROR(I33/G33,0) -> -0.093539831 | K33: Ppi
A34: Max Ahorro Pesos Clase A | B34: FCI | C34: =SUMIFS(Transacciones!$D$2:$D1001,Transacciones!$A$2:$A1001,A34,Transacciones!$C$2:$C1001,"Compra")-SUMIFS(Transacciones!$D$2:$D1001,Transacciones!$A$2:$A1001,A34,Transacciones!$C$2:$C1001,"Venta") -> 93074.373 | D34: =(H34/$F$2) -> 0.051915273 | E34: =IFERROR((SUMIFS(Transacciones!$G$2:$G1001,Transacciones!$A$2:$A1001,A34,Transacciones!$C$2:$C1001,"Compra")-SUMIFS(Transacciones!$G$2:$G1001,Transacciones!$A$2:$A1001,A34,Transacciones!$C$2:$C1001,"Venta"))/C34,0) -> 5.34195 | F34: 5.7232 | G34: =C34*E34 -> 497198.65 | H34: =F34*C34 -> 532683.25 | I34: =H34-G34 -> 35484.605 | J34: =IFERROR(I34/G34,0) -> 0.071369069 | K34: Ppi
A35: Schroder Renta Plus Clase A | B35: FCI | C35: =SUMIFS(Transacciones!$D$2:$D1001,Transacciones!$A$2:$A1001,A35,Transacciones!$C$2:$C1001,"Compra")-SUMIFS(Transacciones!$D$2:$D1001,Transacciones!$A$2:$A1001,A35,Transacciones!$C$2:$C1001,"Venta") -> 13039.771 | D35: =(H35/$F$2) -> 0.10939331 | E35: =IFERROR((SUMIFS(Transacciones!$G$2:$G1001,Transacciones!$A$2:$A1001,A35,Transacciones!$C$2:$C1001,"Compra")-SUMIFS(Transacciones!$G$2:$G1001,Transacciones!$A$2:$A1001,A35,Transacciones!$C$2:$C1001,"Venta"))/C35,0) -> 80.363892 | F35: 86.0785 | G35: =C35*E35 -> 1047926.8 | H35: =F35*C35 -> 1122443.9 | I35: =H35-G35 -> 74517.185 | J35: =IFERROR(I35/G35,0) -> 0.071109155 | K35: Ppi
A36: Fima Ahorro Peso | B36: FCI | C36: =SUMIFS(Transacciones!$D$2:$D1001,Transacciones!$A$2:$A1001,A36,Transacciones!$C$2:$C1001,"Compra")-SUMIFS(Transacciones!$D$2:$D1001,Transacciones!$A$2:$A1001,A36,Transacciones!$C$2:$C1001,"Venta") -> 2374.82 | D36: =(H36/$F$2) -> 0.10411592 | E36: =IFERROR((SUMIFS(Transacciones!$G$2:$G1001,Transacciones!$A$2:$A1001,A36,Transacciones!$C$2:$C1001,"Compra")-SUMIFS(Transacciones!$G$2:$G1001,Transacciones!$A$2:$A1001,A36,Transacciones!$C$2:$C1001,"Venta"))/C36,0) -> 421.08574 | F36: 449.84236 | G36: =C36*E36 -> 1000002.8 | H36: =F36*C36 -> 1068294.6 | I36: =H36-G36 -> 68291.806 | J36: =IFERROR(I36/G36,0) -> 0.068291612 | K36: Galicia
A37: Fima Ahorro Plus | B37: FCI | C37: =SUMIFS(Transacciones!$D$2:$D1001,Transacciones!$A$2:$A1001,A37,Transacciones!$C$2:$C1001,"Compra")-SUMIFS(Transacciones!$D$2:$D1001,Transacciones!$A$2:$A1001,A37,Transacciones!$C$2:$C1001,"Venta") -> 9615.98 | D37: =(H37/$F$2) -> 0.10427054 | E37: =IFERROR((SUMIFS(Transacciones!$G$2:$G1001,Transacciones!$A$2:$A1001,A37,Transacciones!$C$2:$C1001,"Compra")-SUMIFS(Transacciones!$G$2:$G1001,Transacciones!$A$2:$A1001,A37,Transacciones!$C$2:$C1001,"Venta"))/C37,0) -> 103.99364 | F37: 111.26074 | G37: =C37*E37 -> 1000000.7 | H37: =F37*C37 -> 1069881.1 | I37: =H37-G37 -> 69880.346 | J37: =IFERROR(I37/G37,0) -> 0.069880294 | K37: Galicia
A38: Fima Premium | B38: FCI | C38: =SUMIFS(Transacciones!$D$2:$D1001,Transacciones!$A$2:$A1001,A38,Transacciones!$C$2:$C1001,"Compra")-SUMIFS(Transacciones!$D$2:$D1001,Transacciones!$A$2:$A1001,A38,Transacciones!$C$2:$C1001,"Venta") -> 15844.09 | D38: =(H38/$F$2) -> 0.097097027 | E38: =IFERROR((SUMIFS(Transacciones!$G$2:$G1001,Transacciones!$A$2:$A1001,A38,Transacciones!$C$2:$C1001,"Compra")-SUMIFS(Transacciones!$G$2:$G1001,Transacciones!$A$2:$A1001,A38,Transacciones!$C$2:$C1001,"Venta"))/C38,0) -> 60.203245 | F38: 62.88 | G38: =C38*E38 -> 953865.62 | H38: =F38*C38 -> 996276.38 | I38: =H38-G38 -> 42410.755 | J38: =IFERROR(I38/G38,0) -> 0.04446198 | K38: Galicia
A39: S30S5 | B39: Letras | C39: =SUMIFS(Transacciones!$D$2:$D1001,Transacciones!$A$2:$A1001,A39,Transacciones!$C$2:$C1001,"Compra")-SUMIFS(Transacciones!$D$2:$D1001,Transacciones!$A$2:$A1001,A39,Transacciones!$C$2:$C1001,"Venta") -> 697617 | D39: =(H39/$F$2) -> 0.1058049 | E39: =IFERROR((SUMIFS(Transacciones!$G$2:$G1001,Transacciones!$A$2:$A1001,A39,Transacciones!$C$2:$C1001,"Compra")-SUMIFS(Transacciones!$G$2:$G1001,Transacciones!$A$2:$A1001,A39,Transacciones!$C$2:$C1001,"Venta"))/C39,0) -> 1.51 | F39: 1.55619 | G39: =C39*E39 -> 1053401.7 | H39: =F39*C39 -> 1085624.6 | I39: =H39-G39 -> 32222.929 | J39: =IFERROR(I39/G39,0) -> 0.030589404 | K39: Ppi
A40: S12S5 | B40: Letras | C40: =SUMIFS(Transacciones!$D$2:$D1001,Transacciones!$A$2:$A1001,A40,Transacciones!$C$2:$C1001,"Compra")-SUMIFS(Transacciones!$D$2:$D1001,Transacciones!$A$2:$A1001,A40,Transacciones!$C$2:$C1001,"Venta") -> 40262 | D40: =(H40/$F$2) -> 0.0062221786 | E40: =IFERROR((SUMIFS(Transacciones!$G$2:$G1001,Transacciones!$A$2:$A1001,A40,Transacciones!$C$2:$C1001,"Compra")-SUMIFS(Transacciones!$G$2:$G1001,Transacciones!$A$2:$A1001,A40,Transacciones!$C$2:$C1001,"Venta"))/C40,0) -> 1.53 | F40: 1.5857 | G40: =C40*E40 -> 61600.86 | H40: =F40*C40 -> 63843.453 | I40: =H40-G40 -> 2242.5934 | J40: =IFERROR(I40/G40,0) -> 0.036405229 | K40: Ppi
A41: D31O5 | B41: Letras | C41: =SUMIFS(Transacciones!$D$2:$D1001,Transacciones!$A$2:$A1001,A41,Transacciones!$C$2:$C1001,"Compra")-SUMIFS(Transacciones!$D$2:$D1001,Transacciones!$A$2:$A1001,A41,Transacciones!$C$2:$C1001,"Venta") -> 490 | D41: =(H41/$F$2) -> 0.013629381 | E41: =IFERROR((SUMIFS(Transacciones!$G$2:$G1001,Transacciones!$A$2:$A1001,A41,Transacciones!$C$2:$C1001,"Compra")-SUMIFS(Transacciones!$G$2:$G1001,Transacciones!$A$2:$A1001,A41,Transacciones!$C$2:$C1001,"Venta"))/C41,0) -> 285.30612 | F41: 285.4 | G41: =C41*E41 -> 139800 | H41: =F41*C41 -> 139846 | I41: =H41-G41 -> 46 | J41: =IFERROR(I41/G41,0) -> 0.00032904149 | K41: Ppi
A42: S31O5 | B42: Letras | C42: =SUMIFS(Transacciones!$D$2:$D1001,Transacciones!$A$2:$A1001,A42,Transacciones!$C$2:$C1001,"Compra")-SUMIFS(Transacciones!$D$2:$D1001,Transacciones!$A$2:$A1001,A42,Transacciones!$C$2:$C1001,"Venta") -> 462349 | D42: =(H42/$F$2) -> 0.056280567 | E42: =IFERROR((SUMIFS(Transacciones!$G$2:$G1001,Transacciones!$A$2:$A1001,A42,Transacciones!$C$2:$C1001,"Compra")-SUMIFS(Transacciones!$G$2:$G1001,Transacciones!$A$2:$A1001,A42,Transacciones!$C$2:$C1001,"Venta"))/C42,0) -> 1.249 | F42: 1.249 | G42: =C42*E42 -> 577473.9 | H42: =F42*C42 -> 577473.9 | I42: =H42-G42 -> 0 | J42: =IFERROR(I42/G42,0) -> 0 | K42: Ppi
A43: BTC | B43: Cripto | C43: =SUMIFS(Transacciones!$D$2:$D1001,Transacciones!$A$2:$A1001,A43,Transacciones!$C$2:$C1001,"Compra")-SUMIFS(Transacciones!$D$2:$D1001,Transacciones!$A$2:$A1001,A43,Transacciones!$C$2:$C1001,"Venta") -> 1 | D43: =(H43/$F$2) -> 0.0030631656 | E43: 22000 | F43: 31430 | G43: =C43*E43 -> 22000 | H43: =F43*C43 -> 31430 | I43: =H43-G43 -> 9430 | J43: =IFERROR(I43/G43,0) -> 0.42863636 | K43: Binance

Sheet Agosto
A1: Portfolio De Inversiones | C1: P&L | D1: P&L % | E1: Valor Medio Total | F1: Valor Portolio | G1: Efectivo | H1: Medio+Efectivo | I1: Portfolio+Efectivo | M1: Opc/Futuros | N1: =SUMIF(B4:B999,M1,G4:G999) -> 0
C2: 310357.07 | D2: 0.035332511 | E2: 8783895.1 | F2: 9094252.2 | G2: 300653.56 | H2: 9084548.7 | I2: 9394905.8 | M2: Acciones | N2: =SUMIF($B$5:B999,M2,$H$5:H999) -> 305751.82
M3: Bonos | N3: =SUMIF($B$5:B1000,M3,$H$5:H1000) -> 51180
A4: Ticker | B4: Tipo | C4: Cantidad | D4: % Portfolio | E4: Costo medio | F4: Precio Actual | G4: Valor Medio | H4: Valor de Mercado | I4: P&L | J4: P&L % | K4: Broker | M4: Cedear | N4: =SUMIF($B$5:B1001,M4,$H$5:H1001) -> 683313 | P4: P&L Julio/Junio
A5: ALUA | B5: Acciones | C5: 15 | D5: =(H5/$F$2) -> 0.0011603483 | E5: 984 | F5: 703.5 | G5: =C5*E5 -> 14760 | H5: =F5*C5 -> 10552.5 | I5: =H5-G5 -> -4207.5 | J5: =IFERROR(I5/G5,0) -> -0.28506098 | K5: Eco | M5: ON | N5: =SUMIF($B$5:B1002,M5,$H$5:H1002) -> 340811.4 | P5: =SUM(I5-Junio!I5) -> -187.5
A6: BYMA | B6: Acciones | C6: 30 | D6: =(H6/$F$2) -> 0.00053275408 | E6: 371.26667 | F6: 161.5 | G6: =C6*E6 -> 11138 | H6: =F6*C6 -> 4845 | I6: =H6-G6 -> -6293 | J6: =IFERROR(I6/G6,0) -> -0.56500269 | K6: Eco | M6: FCI | N6: =SUMIF($B$5:B1003,M6,$H$5:H1003) -> 6685655.9 | P6: =SUM(I6-Junio!I6) -> -915
A7: CEPU | B7: Acciones | C7: 20 | D7: =(H7/$F$2) -> 0.0027973713 | E7: 1740 | F7: 1272 | G7: =C7*E7 -> 34800 | H7: =F7*C7 -> 25440 | I7: =H7-G7 -> -9360 | J7: =IFERROR(I7/G7,0) -> -0.26896552 | K7: Eco | M7: Letras | N7: =SUMIF($B$5:B1004,M7,$H$5:H1004) -> 2344814 | P7: =SUM(I7-Junio!I7) -> -2960
A8: COME | B8: Acciones | C8: 46 | D8: =(H8/$F$2) -> 0.00017663025 | E8: 232.2337 | F8: 34.92 | G8: =C8*E8 -> 10682.75 | H8: =F8*C8 -> 1606.32 | I8: =H8-G8 -> -9076.43 | J8: =IFERROR(I8/G8,0) -> -0.84963422 | K8: Eco | M8: Cripto | N8: =SUMIF($B$5:B1005,M8,$H$5:H1005) -> 31430 | P8: =SUM(I8-Junio!I8) -> -3821.68
A9: EDN | B9: Acciones | C9: 25 | D9: =(H9/$F$2) -> 0.0043983825 | E9: 1270.6 | F9: 1600 | G9: =C9*E9 -> 31765 | H9: =F9*C9 -> 40000 | I9: =H9-G9 -> 8235 | J9: =IFERROR(I9/G9,0) -> 0.2592476 | K9: Eco | M9: Efectivo | N9: 107420 | P9: =SUM(I9-Junio!I9) -> 1875
A10: MORI | B10: Acciones | C10: 100 | D10: =(H10/$F$2) -> 0.00033317748 | E10: 394 | F10: 30.3 | G10: =C10*E10 -> 39400 | H10: =F10*C10 -> 3030 | I10: =H10-G10 -> -36370 | J10: =IFERROR(I10/G10,0) -> -0.92309645 | K10: Eco | M10: Total | N10: =SUM(N1:N9) -> 10550376
A11: PAMP | B11: Acciones | C11: 20 | D11: =(H11/$F$2) -> 0.0074387644 | E11: 4200 | F11: 3382.5 | G11: =C11*E11 -> 84000 | H11: =F11*C11 -> 67650 | I11: =H11-G11 -> -16350 | J11: =IFERROR(I11/G11,0) -> -0.19464286 | K11: Eco
A12: SEMI | B12: Acciones | C12: 7660 | D12: =(H12/$F$2) -> 0.015498141 | E12: 40 | F12: 18.4 | G12: =C12*E12 -> 306400 | H12: =F12*C12 -> 140944 | I12: =H12-G12 -> -165456 | J12: =IFERROR(I12/G12,0) -> -0.54 | K12: Eco | M12: Eco | N12: =SUMIF($K$5:$K999,M12,$H$5:$H999) -> 1069312.8
A13: TXAR | B13: Acciones | C13: 23 | D13: =(H13/$F$2) -> 0.0012847675 | E13: 963 | F13: 508 | G13: =C13*E13 -> 22149 | H13: =F13*C13 -> 11684 | I13: =H13-G13 -> -10465 | J13: =IFERROR(I13/G13,0) -> -0.47248183 | K13: Eco | M13: Ppi | N13: =SUMIF($K$5:$K1000,M13,$H$5:$H1000) -> 6207761.2
A14: AMZN | B14: Cedear | C14: 45 | D14: =(H14/$F$2) -> 0.011618327 | E14: 1895 | F14: 2348 | G14: =C14*E14 -> 85275 | H14: =F14*C14 -> 105660 | I14: =H14-G14 -> 20385 | J14: =IFERROR(I14/G14,0) -> 0.23905013 | K14: Eco | M14: Binance | N14: =SUMIF($K$5:$K1001,M14,$H$5:$H1001) -> 31430
A15: BABA | B15: Cedear | C15: 1 | D15: =(H15/$F$2) -> 0.0025818505 | E15: 11400 | F15: 23480 | G15: =C15*E15 -> 11400 | H15: =F15*C15 -> 23480 | I15: =H15-G15 -> 12080 | J15: =IFERROR(I15/G15,0) -> 1.0596491 | K15: Eco | M15: Galicia | N15: =SUMIF($K$5:$K1002,M15,$H$5:$H1002) -> 3134452.1
A16: CDE | B16: Cedear | C16: 5 | D16: =(H16/$F$2) -> 0.011320337 | E16: 7400 | F16: 20590 | G16: =C16*E16 -> 37000 | H16: =F16*C16 -> 102950 | I16: =H16-G16 -> 65950 | J16: =IFERROR(I16/G16,0) -> 1.7824324 | K16: Eco | M16: Efectivo | N16: 107420
A17: ETHA | B17: Cedear | C17: 5 | D17: =(H17/$F$2) -> 0.0051186177 | E17: 5970 | F17: 9310 | G17: =C17*E17 -> 29850 | H17: =F17*C17 -> 46550 | I17: =H17-G17 -> 16700 | J17: =IFERROR(I17/G17,0) -> 0.55946399 | K17: Eco | M17: Total | N17: =SUM(N12:N16) -> 10550376
A18: GOOGL | B18: Cedear | C18: 25 | D18: =(H18/$F$2) -> 0.016026606 | E18: 3995 | F18: 5830 | G18: =C18*E18 -> 99875 | H18: =F18*C18 -> 145750 | I18: =H18-G18 -> 45875 | J18: =IFERROR(I18/G18,0) -> 0.45932416 | K18: Eco
A19: IBM | B19: Cedear | C19: 1 | D19: =(H19/$F$2) -> 0.0027006069 | E19: 17850 | F19: 24560 | G19: =C19*E19 -> 17850 | H19: =F19*C19 -> 24560 | I19: =H19-G19 -> 6710 | J19: =IFERROR(I19/G19,0) -> 0.37591036 | K19: Eco
A20: KO | B20: Cedear | C20: 1 | D20: =(H20/$F$2) -> 0.0021420123 | E20: 15000 | F20: 19480 | G20: =C20*E20 -> 15000 | H20: =F20*C20 -> 19480 | I20: =H20-G20 -> 4480 | J20: =IFERROR(I20/G20,0) -> 0.29866667 | K20: Eco
A21: LAC | B21: Cedear | C21: 9 | D21: =(H21/$F$2) -> 0.0040248499 | E21: 3655 | F21: 4067 | G21: =C21*E21 -> 32895 | H21: =F21*C21 -> 36603 | I21: =H21-G21 -> 3708 | J21: =IFERROR(I21/G21,0) -> 0.1127223 | K21: Eco
A22: MSFT | B22: Cedear | C22: 1 | D22: =(H22/$F$2) -> 0.0026412287 | E22: 17775 | F22: 24020 | G22: =C22*E22 -> 17775 | H22: =F22*C22 -> 24020 | I22: =H22-G22 -> 6245 | J22: =IFERROR(I22/G22,0) -> 0.35133615 | K22: Eco
A23: PFE | B23: Cedear | C23: 1 | D23: =(H23/$F$2) -> 0.00097314213 | E23: 7790 | F23: 8850 | G23: =C23*E23 -> 7790 | H23: =F23*C23 -> 8850 | I23: =H23-G23 -> 1060 | J23: =IFERROR(I23/G23,0) -> 0.13607189 | K23: Eco
A24: SPY | B24: Cedear | C24: 2 | D24: =(H24/$F$2) -> 0.01025263 | E24: 35825 | F24: 46620 | G24: =C24*E24 -> 71650 | H24: =F24*C24 -> 93240 | I24: =H24-G24 -> 21590 | J24: =IFERROR(I24/G24,0) -> 0.30132589 | K24: Eco
A25: VIST | B25: Cedear | C25: 3 | D25: =(H25/$F$2) -> 0.0057365904 | E25: 21041.667 | F25: 17390 | G25: =C25*E25 -> 63125 | H25: =F25*C25 -> 52170 | I25: =H25-G25 -> -10955 | J25: =IFERROR(I25/G25,0) -> -0.17354455 | K25: Eco
A26: AE38 | B26: Bonos | C26: 60 | D26: =(H26/$F$2) -> 0.0056277304 | E26: 740 | F26: 853 | G26: =C26*E26 -> 44400 | H26: =F26*C26 -> 51180 | I26: =H26-G26 -> 6780 | J26: =IFERROR(I26/G26,0) -> 0.1527027 | K26: Eco
A27: YMCJO | B27: ON | C27: 26 | D27: =(H27/$F$2) -> 0.0031963046 | E27: 1220.9615 | F27: 1118 | G27: =C27*E27 -> 31745 | H27: =F27*C27 -> 29068 | I27: =H27-G27 -> -2677 | J27: =IFERROR(I27/G27,0) -> -0.084328241 | K27: Eco
A28: NDT5D | B28: ON | C28: 98 | D28: =(H28/$F$2) -> 0.0097016663 | E28: 1135 | F28: 900.3 | G28: =C28*E28 -> 111230 | H28: =F28*C28 -> 88229.4 | I28: =H28-G28 -> -23000.6 | J28: =IFERROR(I28/G28,0) -> -0.20678414 | K28: Ppi
A29: RUCDD | B29: ON | C29: 99 | D29: =(H29/$F$2) -> 0.012540668 | E29: 1315.0625 | F29: 1152 | G29: =C29*E29 -> 130191.19 | H29: =F29*C29 -> 114048 | I29: =H29-G29 -> -16143.188 | J29: =IFERROR(I29/G29,0) -> -0.12399601 | K29: Ppi
... A41: BTC | B41: Cripto | C41: 1 | D41: =(H41/$F$2) -> 0.0034560291 | E41: 22000 | F41: 31430 | G41: =C41*E41 -> 22000 | H41: =F41*C41 -> 31430 | I41: =H41-G41 -> 9430 | J41: =IFERROR(I41/G41,0) -> 0.42863636 | K41: Binance

Sheet Julio
A1: Portfolio De Inversiones | C1: P&L | D1: P&L % | E1: Valor Medio Total | F1: Valor Portolio | G1: Efectivo | H1: Medio+Efectivo | I1: Portfolio+Efectivo | M1: Opc/Futuros | N1: 0
C2: 853839.32 | D2: 0.078298801 | E2: 10904884 | F2: 11758723 | G2: 217000 | H2: 11121884 | I2: 11975723 | M2: Acciones | N2: 414838
M3: Bonos | N3: 54780
A4: Ticker | B4: Tipo | C4: Cantidad | D4: % Portfolio | E4: Costo medio | F4: Precio Actual | G4: Valor Medio | H4: Valor de Mercado | I4: P&L | J4: P&L % | K4: Broker | M4: Cedear | N4: 574225 | P4: P&L Junio/Mayo
A5: ALUA | B5: Acciones | C5: 15 | D5: 0.00095546089 | E5: 984 | F5: 749 | G5: 14760 | H5: 11235 | I5: -3525 | J5: -0.23882114 | K5: Eco | M5: ON | N5: 396699 | P5: -120
A6: BYMA | B6: Acciones | C6: 30 | D6: 0.00051536208 | E6: 371.26667 | F6: 202 | G6: 11138 | H6: 6060 | I6: -5078 | J6: -0.45591668 | K6: Eco | M6: FCI | N6: 6911392.9 | P6: -270
A7: CEPU | B7: Acciones | C7: 20 | D7: 0.0027979229 | E7: 1740 | F7: 1645 | G7: 34800 | H7: 32900 | I7: -1900 | J7: -0.054597701 | K7: Eco | M7: Letras | N7: 3375673.7 | P7: 2900
A8: COME | B8: Acciones | C8: 46 | D8: 0.00049682265 | E8: 232.2337 | F8: 127 | G8: 10682.75 | H8: 5842 | I8: -4840.75 | J8: -0.45313707 | K8: Eco | M8: Cripto | N8: 31114.52 | P8: -782
A9: EDN | B9: Acciones | C9: 25 | D9: 0.0042096408 | E9: 1270.6 | F9: 1980 | G9: 31765 | H9: 49500 | I9: 17735 | J9: 0.5583189 | K9: Eco | M9: Efectivo | N9: 107420 | P9: 9500
A10: MORI | B10: Acciones | C10: 100 | D10: 0.0018794558 | E10: 394 | F10: 221 | G10: 39400 | H10: 22100 | I10: -17300 | J10: -0.43908629 | K10: Eco | M10: Total | N10: 11866143
A11: PAMP | B11: Acciones | C11: 20 | D11: 0.006965042 | E11: 4200 | F11: 4095 | G11: 84000 | H11: 81900 | I11: -2100 | J11: -0.025 | K11: Eco
A12: SEMI | B12: Acciones | C12: 7660 | D12: 0.016188067 | E12: 40 | F12: 24.85 | G12: 306400 | H12: 190351 | I12: -116049 | J12: -0.37875 | K12: Eco | M12: Eco | N12: 1081875
A13: TXAR | B13: Acciones | C13: 23 | D13: 0.0012713966 | E13: 963 | F13: 650 | G13: 22149 | H13: 14950 | I13: -7199 | J13: -0.32502596 | K13: Eco | M13: Ppi | N13: 7379592.5
A14: AMZN | B14: Cedear | C14: 45 | D14: 0.0077112965 | E14: 1895 | F14: 2015 | G14: 85275 | H14: 90675 | I14: 5400 | J14: 0.063324538 | K14: Eco | M14: Binance | N14: 31114.52
A15: BABA | B15: Cedear | C15: 1 | D15: 0.0015095176 | E15: 11400 | F15: 17750 | G15: 11400 | H15: 17750 | I15: 6350 | J15: 0.55701754 | K15: Eco | M15: Galicia | N15: 3266141
A16: CDE | B16: Cedear | C16: 5 | D16: 0.005262051 | E16: 7400 | F16: 12375 | G16: 37000 | H16: 61875 | I16: 24875 | J16: 0.6722973 | K16: Eco | M16: Efectivo | N16: 107420
A17: ETHA | B17: Cedear | C17: 5 | D17: 0.0032273913 | E17: 5970 | F17: 7590 | G17: 29850 | H17: 37950 | I17: 8100 | J17: 0.27135678 | K17: Eco | M17: Total | N17: 11866143
A18: GOOGL | B18: Cedear | C18: 25 | D18: 0.0096842998 | E18: 3995 | F18: 4555 | G18: 99875 | H18: 113875 | I18: 14000 | J18: 0.14017522 | K18: Eco
A19: IBM | B19: Cedear | C19: 1 | D19: 0.0019411121 | E19: 17850 | F19: 22825 | G19: 17850 | H19: 22825 | I19: 4975 | J19: 0.27871148 | K19: Eco
A20: KO | B20: Cedear | C20: 1 | D20: 0.0015924348 | E20: 15000 | F20: 18725 | G20: 15000 | H20: 18725 | I20: 3725 | J20: 0.24833333 | K20: Eco
A21: LAC | B21: Cedear | C21: 9 | D21: 0.002770709 | E21: 3655 | F21: 3620 | G21: 32895 | H21: 32580 | I21: -315 | J21: -0.0095759234 | K21: Eco
A22: MSFT | B22: Cedear | C22: 1 | D22: 0.0020729292 | E22: 17775 | F22: 24375 | G22: 17775 | H22: 24375 | I22: 6600 | J22: 0.37130802 | K22: Eco
A23: PFE | B23: Cedear | C23: 1 | D23: 0.00068204685 | E23: 7790 | F23: 8020 | G23: 7790 | H23: 8020 | I23: 230 | J23: 0.029525032 | K23: Eco
A24: SPY | B24: Cedear | C24: 2 | D24: 0.0072967107 | E24: 35825 | F24: 42900 | G24: 71650 | H24: 85800 | I24: 14150 | J24: 0.19748779 | K24: Eco
A25: VIST | B25: Cedear | C25: 3 | D25: 0.0050834601 | E25: 21041.667 | F25: 19925 | G25: 63125 | H25: 59775 | I25: -3350 | J25: -0.053069307 | K25: Eco
A26: AE38 | B26: Bonos | C26: 60 | D26: 0.0046586691 | E26: 740 | F26: 913 | G26: 44400 | H26: 54780 | I26: 10380 | J26: 0.23378378 | K26: Eco
A27: MR39O | B27: ON | C27: 12 | D27: 0.00076232767 | E27: 1169 | F27: 747 | G27: 14028 | H27: 8964 | I27: -5064 | J27: -0.3609923 | K27: Eco
A28: YMCJO | B28: ON | C28: 26 | D28: 0.0024720371 | E28: 1220.9615 | F28: 1118 | G28: 31745 | H28: 29068 | I28: -2677 | J28: -0.084328241 | K28: Eco
A29: NDT5D | B29: ON | C29: 98 | D29: 0.0086676078 | E29: 1135 | F29: 1040 | G29: 111230 | H29: 101920 | I29: -9310 | J29: -0.083700441 | K29: Ppi
... A42: BTC | B42: Cripto | C42: 1 | D42: 0.0026460798 | E42: 22000 | F42: 31114.52 | G42: 22000 | H42: 31114.52 | I42: 9114.52 | J42: 0.41429636 | K42: Binance

Sheet Junio
A1: Portfolio De Inversiones | C1: P&L | D1: P&L % | E1: Valor Medio Total | F1: Valor Portolio | G1: Efectivo | H1: Medio+Efectivo | I1: Portfolio+Efectivo | M1: Opc/Futuros | N1: 0
C2: 384956.31 | D2: 0.035301276 | E2: 10904884 | F2: 11289840 | G2: 217000 | H2: 11121884 | I2: 11506840 | M2: Acciones | N2: 365441
M3: Bonos | N3: 52740
A4: Ticker | B4: Tipo | C4: Cantidad | D4: % Portfolio | E4: Costo medio | F4: Precio Actual | G4: Valor Medio | H4: Valor de Mercado | I4: P&L | J4: P&L % | K4: Broker | M4: Cedear | N4: 505953 | P4: P&L Junio/Mayo
A5: ALUA | B5: Acciones | C5: 15 | D5: 0.0009512978 | E5: 984 | F5: 716 | G5: 14760 | H5: 10740 | I5: -4020 | J5: -0.27235772 | K5: Eco | M5: ON | N5: 353492 | P5: -615
A6: BYMA | B6: Acciones | C6: 30 | D6: 0.00051019323 | E6: 371.26667 | F6: 192 | G6: 11138 | H6: 5760 | I6: -5378 | J6: -0.4828515 | K6: Eco | M6: FCI | N6: 6724481.9 | P6: -570
A7: CEPU | B7: Acciones | C7: 20 | D7: 0.0025155361 | E7: 1740 | F7: 1420 | G7: 34800 | H7: 28400 | I7: -6400 | J7: -0.18390805 | K7: Eco | M7: Letras | N7: 3259732.2 | P7: -1600
A8: COME | B8: Acciones | C8: 46 | D8: 0.00048078626 | E8: 232.2337 | F8: 118 | G8: 10682.75 | H8: 5428 | I8: -5254.75 | J8: -0.49189113 | K8: Eco | M8: Cripto | N8: 28000 | P8: -1196
A9: EDN | B9: Acciones | C9: 25 | D9: 0.00337693 | E9: 1270.6 | F9: 1525 | G9: 31765 | H9: 38125 | I9: 6360 | J9: 0.20022037 | K9: Eco | M9: Efectivo | N9: 107420 | P9: -1875
A10: MORI | B10: Acciones | C10: 100 | D10: 0.0018246494 | E10: 394 | F10: 206 | G10: 39400 | H10: 20600 | I10: -18800 | J10: -0.47715736 | K10: Eco | M10: Total | N10: 11397260
A11: PAMP | B11: Acciones | C11: 20 | D11: 0.0065279933 | E11: 4200 | F11: 3685 | G11: 84000 | H11: 73700 | I11: -10300 | J11: -0.12261905 | K11: Eco
A12: SEMI | B12: Acciones | C12: 7660 | D12: 0.014926695 | E12: 40 | F12: 22 | G12: 306400 | H12: 168520 | I12: -137880 | J12: -0.45 | K12: Eco | M12: Eco | N12: 963854
A13: TXAR | B13: Acciones | C13: 23 | D13: 0.0012549336 | E13: 963 | F13: 616 | G13: 22149 | H13: 14168 | I13: -7981 | J13: -0.36033229 | K13: Eco | M13: Ppi | N13: 7082321.5
A14: AMZN | B14: Cedear | C14: 45 | D14: 0.0075731808 | E14: 1895 | F14: 1900 | G14: 85275 | H14: 85500 | I14: 225 | J14: 0.0026385224 | K14: Eco | M14: Binance | N14: 28000
A15: BABA | B15: Cedear | C15: 1 | D15: 0.0013884165 | E15: 11400 | F15: 15675 | G15: 11400 | H15: 15675 | I15: 4275 | J15: 0.375 | K15: Eco | M15: Galicia | N15: 3215664.5
A16: CDE | B16: Cedear | C16: 5 | D16: 0.0048968807 | E16: 7400 | F16: 11057 | G16: 37000 | H16: 55285 | I16: 18285 | J16: 0.49418919 | K16: Eco | M16: Efectivo | N16: 107420
A17: ETHA | B17: Cedear | C17: 5 | D17: 0.0021501633 | E17: 5970 | F17: 4855 | G17: 29850 | H17: 24275 | I17: -5575 | J17: -0.18676717 | K17: Eco | M17: Total | N17: 11397260
A18: GOOGL | B18: Cedear | C18: 25 | D18: 0.0081932073 | E18: 3995 | F18: 3700 | G18: 99875 | H18: 92500 | I18: -7375 | J18: -0.073842303 | K18: Eco
A19: IBM | B19: Cedear | C19: 1 | D19: 0.0021080901 | E19: 17850 | F19: 23800 | G19: 17850 | H19: 23800 | I19: 5950 | J19: 0.33333333 | K19: Eco
A20: KO | B20: Cedear | C20: 1 | D20: 0.0015722101 | E20: 15000 | F20: 17750 | G20: 15000 | H20: 17750 | I20: 2750 | J20: 0.18333333 | K20: Eco
A21: LAC | B21: Cedear | C21: 9 | D21: 0.0025979996 | E21: 3655 | F21: 3259 | G21: 32895 | H21: 29331 | I21: -3564 | J21: -0.10834473 | K21: Eco
A22: MSFT | B22: Cedear | C22: 1 | D22: 0.0017944453 | E22: 17775 | F22: 20259 | G22: 17775 | H22: 20259 | I22: 2484 | J22: 0.13974684 | K22: Eco
A23: PFE | B23: Cedear | C23: 1 | D23: 0.00068202915 | E23: 7790 | F23: 7700 | G23: 7790 | H23: 7700 | I23: -90 | J23: -0.011553273 | K23: Eco
A24: SPY | B24: Cedear | C24: 2 | D24: 0.0066962862 | E24: 35825 | F24: 37800 | G24: 71650 | H24: 75600 | I24: 3950 | J24: 0.0551291 | K24: Eco
A25: VIST | B25: Cedear | C25: 3 | D25: 0.0051619863 | E25: 21041.667 | F25: 19426 | G25: 63125 | H25: 58278 | I25: -4847 | J25: -0.076784158 | K25: Eco
A26: AE38 | B26: Bonos | C26: 60 | D26: 0.0046714568 | E26: 740 | F26: 879 | G26: 44400 | H26: 52740 | I26: 8340 | J26: 0.18783784 | K26: Eco
A27: MR39O | B27: ON | C27: 12 | D27: 0.00075466082 | E27: 1169 | F27: 710 | G27: 14028 | H27: 8520 | I27: -5508 | J27: -0.39264328 | K27: Eco
A28: YMCJO | B28: ON | C28: 26 | D28: 0.0027635467 | E28: 1220.9615 | F28: 1200 | G28: 31745 | H28: 31200 | I28: -545 | J28: -0.017168058 | K28: Eco
A29: NDT5D | B29: ON | C29: 98 | D29: 0.0079946217 | E29: 1135 | F29: 921 | G29: 111230 | H29: 90258 | I29: -20972 | J29: -0.18854626 | K29: Ppi
... A42: BTC | B42: Cripto | C42: 1 | D42: 0.002480106 | E42: 22000 | F42: 28000 | G42: 22000 | H42: 28000 | I42: 6000 | J42: 0.27272727 | K42: Binance

Sheet Mayo
A1: Portfolio De Inversiones | C1: P&L | D1: P&L % | E1: Valor Medio Total | F1: Valor Portolio | G1: Efectivo | H1: Medio+Efectivo | I1: Portfolio+Efectivo | M1: Opc/Futuros | N1: 0
C2: 439491.15 | D2: 0.04517191 | E2: 9729302 | F2: 10168793 | G2: 139000 | H2: 9868302 | I2: 10307793 | M2: Acciones | N2: 397929
M3: Bonos | N3: 51180
A4: Ticker | B4: Tipo | C4: Cantidad | D4: % Portfolio | E4: Costo medio | F4: Precio Actual | G4: Valor Medio | H4: Valor de Mercado | I4: P&L | J4: P&L % | K4: Broker | M4: Cedear | N4: 461810
A5: ALUA | B5: Acciones | C5: 15 | D5: 0.0011166517 | E5: 984 | F5: 757 | G5: 14760 | H5: 11355 | I5: -3405 | J5: -0.23069106 | K5: Eco | M5: ON | N5: 341521.4
A6: BYMA | B6: Acciones | C6: 30 | D6: 0.00062249275 | E6: 371.26667 | F6: 211 | G6: 11138 | H6: 6330 | I6: -4808 | J6: -0.43167535 | K6: Eco | M6: FCI | N6: 6685655.9
A7: CEPU | B7: Acciones | C7: 20 | D7: 0.0029502026 | E7: 1740 | F7: 1500 | G7: 34800 | H7: 30000 | I7: -4800 | J7: -0.13793103 | K7: Eco | M7: Letras | N7: 2205766.2
A8: COME | B8: Acciones | C8: 46 | D8: 0.00065140474 | E8: 232.2337 | F8: 144 | G8: 10682.75 | H8: 6624 | I8: -4058.75 | J8: -0.37993494 | K8: Eco | M8: Cripto | N8: 24930.7
A9: EDN | B9: Acciones | C9: 25 | D9: 0.0039336035 | E9: 1270.6 | F9: 1600 | G9: 31765 | H9: 40000 | I9: 8235 | J9: 0.2592476 | K9: Eco | M9: Efectivo | N9: 29244.57
A10: MORI | B10: Acciones | C10: 100 | D10: 0.0025175062 | E10: 394 | F10: 256 | G10: 39400 | H10: 25600 | I10: -13800 | J10: -0.35025381 | K10: Eco | M10: Total | N10: 10198038
A11: PAMP | B11: Acciones | C11: 20 | D11: 0.0070509842 | E11: 4200 | F11: 3585 | G11: 84000 | H11: 71700 | I11: -12300 | J11: -0.14642857 | K11: Eco
A12: SEMI | B12: Acciones | C12: 7660 | D12: 0.018794462 | E12: 40 | F12: 24.95 | G12: 306400 | H12: 191117 | I12: -115283 | J12: -0.37625 | K12: Eco | M12: Eco | N12: 940697
A13: TXAR | B13: Acciones | C13: 23 | D13: 0.0014950643 | E13: 963 | F13: 661 | G13: 22149 | H13: 15203 | I13: -6946 | J13: -0.31360332 | K13: Eco | M13: Ppi | N13: 6068713.3
A14: AMZN | B14: Cedear | C14: 45 | D14: 0.0076115227 | E14: 1895 | F14: 1720 | G14: 85275 | H14: 77400 | I14: -7875 | J14: -0.092348285 | K14: Eco | M14: Binance | N14: 24930.7
A15: BABA | B15: Cedear | C15: 1 | D15: 0.0014996863 | E15: 11400 | F15: 15250 | G15: 11400 | H15: 15250 | I15: 3850 | J15: 0.3377193 | K15: Eco | M15: Galicia | N15: 3134452.1
A16: CDE | B16: Cedear | C16: 5 | D16: 0.0036336662 | E16: 7400 | F16: 7390 | G16: 37000 | H16: 36950 | I16: -50 | J16: -0.0013513514 | K16: Eco | M16: Efectivo | N16: 107420
A17: ETHA | B17: Cedear | C17: 5 | D17: 0.002261822 | E17: 5970 | F17: 4600 | G17: 29850 | H17: 23000 | I17: -6850 | J17: -0.22948074 | K17: Eco | M17: Total | N17: 10276213
A18: GOOGL | B18: Cedear | C18: 25 | D18: 0.0085801726 | E18: 3995 | F18: 3490 | G18: 99875 | H18: 87250 | I18: -12625 | J18: -0.12640801 | K18: Eco
A19: IBM | B19: Cedear | C19: 1 | D19: 0.0020602248 | E19: 17850 | F19: 20950 | G19: 17850 | H19: 20950 | I19: 3100 | J19: 0.17366947 | K19: Eco | M19: P&L Mayo/Abril
A20: KO | B20: Cedear | C20: 1 | D20: 0.001693908 | E20: 15000 | F20: 17225 | G20: 15000 | H20: 17225 | I20: 2225 | J20: 0.14833333 | K20: Eco | M20: Opc/Futuros | N20: 0
A21: LAC | B21: Cedear | C21: 9 | D21: 0.002810068 | E21: 3655 | F21: 3175 | G21: 32895 | H21: 28575 | I21: -4320 | J21: -0.13132695 | K21: Eco | M21: Acciones | N21: -40985
A22: MSFT | B22: Cedear | C22: 1 | D22: 0.0018094576 | E22: 17775 | F22: 18400 | G22: 17775 | H22: 18400 | I22: 625 | J22: 0.035161744 | K22: Eco | M22: Bonos | N22: -118520
A23: PFE | B23: Cedear | C23: 1 | D23: 0.00068936401 | E23: 7790 | F23: 7010 | G23: 7790 | H23: 7010 | I23: -780 | J23: -0.10012837 | K23: Eco | M23: Cedear | N23: 3155
A24: SPY | B24: Cedear | C24: 2 | D24: 0.0069673952 | E24: 35825 | F24: 35425 | G24: 71650 | H24: 70850 | I24: -800 | J24: -0.011165387 | K24: Eco | M24: ON | N24: 8641.4
A25: VIST | B25: Cedear | C25: 3 | D25: 0.0057971481 | E25: 21041.667 | F25: 19650 | G25: 63125 | H25: 58950 | I25: -4175 | J25: -0.066138614 | K25: Eco | M25: FCI | N25: 136044.05
A26: AE38 | B26: Bonos | C26: 60 | D26: 0.0050330457 | E26: 740 | F26: 853 | G26: 44400 | H26: 51180 | I26: 6780 | J26: 0.1527027 | K26: Eco | M26: Letras | N26: 20653.134
A27: MR39O | B27: ON | C27: 12 | D27: 0.00076469252 | E27: 1169 | F27: 648 | G27: 14028 | H27: 7776 | I27: -6252 | J27: -0.44568007 | K27: Eco | M27: Cripto | N27: 1063.7
A28: YMCJO | B28: ON | C28: 19 | D28: 0.0021636786 | E28: 1670.7895 | F28: 1158 | G28: 31745 | H28: 22002 | I28: -9743 | J28: -0.30691447 | K28: Eco
A29: NDT5D | B29: ON | C29: 98 | D29: 0.0086764869 | E29: 1135 | F29: 900.3 | G29: 111230 | H29: 88229.4 | I29: -23000.6 | J29: -0.20678414 | K29: Ppi
A30: RUCDD | B30: ON | C30: 99 | D30: 0.01121549 | E30: 1315.0625 | F30: 1152 | G30: 130191.19 | H30: 114048 | I30: -16143.188 | J30: -0.12399601 | K30: Ppi
A31: YMCJD | B31: ON | C31: 98 | D31: 0.010764896 | E31: 1197.8 | F31: 1117 | G31: 117384.4 | H31: 109466 | I31: -7918.4 | J31: -0.067457005 | K31: Ppi
A32: Adcap Ahorro Pesos Clase A | B32: FCI | C32: 38715.043 | D32: 0.05168672 | E32: 12.9 | F32: 13.5759 | G32: 499424.06 | H32: 525591.56 | I32: 26167.498 | J32: 0.052395349 | K32: Ppi
A33: Allaria Diversificado Clase A | B33: FCI | C33: 10501.993 | D33: 0.12328624 | E33: 104.14 | F33: 119.3747 | G33: 1093677.6 | H33: 1253672.3 | I33: 159994.71 | J33: 0.14629057 | K33: Ppi
A34: Delta Recursos Naturales Clase A | B34: FCI | C34: 120.775 | D34: 0.011487374 | E34: 1067 | F34: 967.193 | G34: 128866.93 | H34: 116812.73 | I34: -12054.19 | J34: -0.093539831 | K34: Ppi
A35: Max Ahorro Pesos Clase A | B35: FCI | C35: 93074.373 | D35: 0.052384117 | E35: 5.34195 | F35: 5.7232 | G35: 497198.65 | H35: 532683.25 | I35: 35484.605 | J35: 0.071369069 | K35: Ppi
A36: Schroder Renta Plus Clase A | B36: FCI | C36: 13039.771 | D36: 0.11038123 | E36: 80.363892 | F36: 86.0785 | G36: 1047926.7 | H36: 1122443.9 | I36: 74517.185 | J36: 0.071109155 | K36: Ppi
A37: Fima Ahorro Peso | B37: FCI | C37: 2374.82 | D37: 0.10505619 | E37: 421.08574 | F37: 449.84236 | G37: 1000002.8 | H37: 1068294.6 | I37: 68291.806 | J37: 0.068291612 | K37: Galicia
A38: Fima Ahorro Plus | B38: FCI | C38: 9615.98 | D38: 0.1052122 | E38: 103.99364 | F38: 111.26074 | G38: 1000000.7 | H38: 1069881.1 | I38: 69880.346 | J38: 0.069880294 | K38: Galicia
A39: Fima Premium | B39: FCI | C39: 15844.09 | D39: 0.097973906 | E39: 60.203245 | F39: 62.88 | G39: 953865.62 | H39: 996276.38 | I39: 42410.755 | J39: 0.04446198 | K39: Galicia
... A42: BTC | B42: Cripto | C42: 1 | D42: 0.0024516872 | E42: 22000 | F42: 24930.7 | G42: 22000 | H42: 24930.7 | I42: 2930.7 | J42: 0.13321364 | K42: Binance

Sheet Abril
A1: Portfolio De Inversiones | C1: P&L | D1: P&L % | E1: Valor Medio Total | F1: Valor Portolio | G1: Efectivo | H1: Medio+Efectivo | I1: Portfolio+Efectivo | M1: Opc/Futuros | N1: 0
C2: 305281.87 | D2: 0.030982204 | E2: 9853459 | F2: 10158741 | G2: 161000 | H2: 10014459 | I2: 10319741 | M2: Acciones | N2: 438914
M3: Bonos | N3: 169700
A4: Ticker | B4: Tipo | C4: Cantidad | D4: % Portfolio | E4: Costo medio | F4: Precio Actual | G4: Valor Medio | H4: Valor de Mercado | I4: P&L | J4: P&L % | K4: Broker | M4: Cedear | N4: 458655
A5: ALUA | B5: Acciones | C5: 15 | D5: 0.00097895991 | E5: 984 | F5: 663 | G5: 14760 | H5: 9945 | I5: -4815 | J5: -0.32621951 | K5: Eco | M5: ON | N5: 332880
A6: BYMA | B6: Acciones | C6: 30 | D6: 0.0011605769 | E6: 371.26667 | F6: 393 | G6: 11138 | H6: 11790 | I6: 652 | J6: 0.058538337 | K6: Eco | M6: FCI | N6: 6549611.8
A7: CEPU | B7: Acciones | C7: 20 | D7: 0.0028940595 | E7: 1740 | F7: 1470 | G7: 34800 | H7: 29400 | I7: -5400 | J7: -0.15517241 | K7: Eco | M7: Letras | N7: 2185113
A8: COME | B8: Acciones | C8: 46 | D8: 0.00064978525 | E8: 232.2337 | F8: 143.5 | G8: 10682.75 | H8: 6601 | I8: -4081.75 | J8: -0.38208795 | K8: Eco | M8: Cripto | N8: 23867
A9: EDN | B9: Acciones | C9: 25 | D9: 0.0051187446 | E9: 1270.6 | F9: 2080 | G9: 31765 | H9: 52000 | I9: 20235 | J9: 0.63702188 | K9: Eco | M9: Efectivo | N9: 107420
A10: MORI | B10: Acciones | C10: 100 | D10: 0.002608591 | E10: 394 | F10: 265 | G10: 39400 | H10: 26500 | I10: -12900 | J10: -0.32741117 | K10: Eco | M10: Total | N10: 10266161
A11: PAMP | B11: Acciones | C11: 20 | D11: 0.0076288982 | E11: 4200 | F11: 3875 | G11: 84000 | H11: 77500 | I11: -6500 | J11: -0.077380952 | K11: Eco
A12: SEMI | B12: Acciones | C12: 7660 | D12: 0.020773539 | E12: 40 | F12: 27.55 | G12: 306400 | H12: 211033 | I12: -95367 | J12: -0.31125 | K12: Eco | M12: Eco | N12: 1096911
A13: TXAR | B13: Acciones | C13: 23 | D13: 0.001392397 | E13: 963 | F13: 615 | G13: 22149 | H13: 14145 | I13: -8004 | J13: -0.36137072 | K13: Eco | M13: Ppi | N13: 5956122.6
A14: AMZN | B14: Cedear | C14: 45 | D14: 0.0075304608 | E14: 1895 | F14: 1700 | G14: 85275 | H14: 76500 | I14: -8775 | J14: -0.10290237 | K14: Eco | M14: Binance | N14: 23867
A15: BABA | B15: Cedear | C15: 1 | D15: 0.0016857404 | E15: 11400 | F15: 17125 | G15: 11400 | H15: 17125 | I15: 5725 | J15: 0.50219298 | K15: Eco | M15: Galicia | N15: 3081840.3
A16: CDE | B16: Cedear | C16: 5 | D16: 0.0043361673 | E16: 7400 | F16: 8810 | G16: 37000 | H16: 44050 | I16: 7050 | J16: 0.19054054 | K16: Eco | M16: Efectivo | N16: 107420
A17: ETHA | B17: Cedear | C17: 5 | D17: 0.0023305054 | E17: 5970 | F17: 4735 | G17: 29850 | H17: 23675 | I17: -6175 | J17: -0.20686767 | K17: Eco | M17: Total | N17: 10266161
A18: GOOGL | B18: Cedear | C18: 25 | D18: 0.0078134683 | E18: 3995 | F18: 3175 | G18: 99875 | H18: 79375 | I18: -20500 | J18: -0.20525657 | K18: Eco
A19: IBM | B19: Cedear | C19: 1 | D19: 0.0019195292 | E19: 17850 | F19: 19500 | G19: 17850 | H19: 19500 | I19: 1650 | J19: 0.092436975 | K19: Eco | M19: P&L Abril/Marzo
A20: KO | B20: Cedear | C20: 1 | D20: 0.0015799202 | E20: 15000 | F20: 16050 | G20: 15000 | H20: 16050 | I20: 1050 | J20: 0.07 | K20: Eco | M20: Opc/Futuros | N20: 0
A21: LAC | B21: Cedear | C21: 9 | D21: 0.0032336685 | E21: 3655 | F21: 3650 | G21: 32895 | H21: 32850 | I21: -45 | J21: -0.0013679891 | K21: Eco | M21: Acciones | N21: 28236
A22: MSFT | B22: Cedear | C22: 1 | D22: 0.001700506 | E22: 17775 | F22: 17275 | G22: 17775 | H22: 17275 | I22: -500 | J22: -0.028129395 | K22: Eco | M22: Bonos | N22: -480345.56 | O22: Se vendieron AL29 y AL30
A23: PFE | B23: Cedear | C23: 1 | D23: 0.00065756181 | E23: 7790 | F23: 6680 | G23: 7790 | H23: 6680 | I23: -1110 | J23: -0.14249037 | K23: Eco | M23: Cedear | N23: 18484
A24: SPY | B24: Cedear | C24: 2 | D24: 0.0066396024 | E24: 35825 | F24: 33725 | G24: 71650 | H24: 67450 | I24: -4200 | J24: -0.058618283 | K24: Eco | M24: ON | N24: 293738
A25: VIST | B25: Cedear | C25: 3 | D25: 0.0057216737 | E25: 21041.667 | F25: 19375 | G25: 63125 | H25: 58125 | I25: -5000 | J25: -0.079207921 | K25: Eco | M25: FCI | N25: 212765.55
A26: AE38 | B26: Bonos | C26: 60 | D26: 0.0048313074 | E26: 740 | F26: 818 | G26: 44400 | H26: 49080 | I26: 4680 | J26: 0.10540541 | K26: Eco | M26: Letras | N26: 1050521.5
A27: AL30 | B27: Bonos | C27: 163 | D27: 0.011873519 | E27: 770 | F27: 740 | G27: 125510 | H27: 120620 | I27: -4890 | J27: -0.038961039 | K27: Eco | M27: Cripto | N27: 2459
A28: MR39O | B28: ON | C28: 12 | D28: 0.00082687413 | E28: 1169 | F28: 700 | G28: 14028 | H28: 8400 | I28: -5628 | J28: -0.4011976 | K28: Eco
A29: YMCJO | B29: ON | C29: 19 | D29: 0.0020910072 | E29: 1670.7895 | F29: 1118 | G29: 31745 | H29: 21242 | I29: -10503 | J29: -0.33085525 | K29: Eco
A30: NDT5D | B30: ON | C30: 98 | D30: 0.0082191289 | E30: 1135 | F30: 852 | G30: 111230 | H30: 83496 | I30: -27734 | J30: -0.24933921 | K30: Ppi
A31: RUCDD | B31: ON | C31: 99 | D31: 0.010758814 | E31: 1315.0625 | F31: 1104 | G31: 130191.19 | H31: 109296 | I31: -20895.188 | J31: -0.16049617 | K31: Ppi
A32: YMCJD | B32: ON | C32: 98 | D32: 0.010872017 | E32: 1197.8 | F32: 1127 | G32: 117384.4 | H32: 110446 | I32: -6938.4 | J32: -0.059108365 | K32: Ppi
A33: Adcap Ahorro Pesos Clase A | B33: FCI | C33: 38715.043 | D33: 0.050984428 | E33: 12.9 | F33: 13.3782 | G33: 499424.06 | H33: 517937.59 | I33: 18513.534 | J33: 0.037069767 | K33: Ppi
A34: Allaria Diversificado Clase A | B34: FCI | C34: 10501.993 | D34: 0.11994339 | E34: 104.14 | F34: 116.0231 | G34: 1093677.6 | H34: 1218473.8 | I34: 124796.23 | J34: 0.11410697 | K34: Ppi
A35: Delta Recursos Naturales Clase A | B35: FCI | C35: 120.775 | D35: 0.011776673 | E35: 1067 | F35: 990.5706 | G35: 128866.93 | H35: 119636.16 | I35: -9230.7608 | J35: -0.071630178 | K35: Ppi
A36: Max Ahorro Pesos Clase A | B36: FCI | C36: 93074.373 | D36: 0.050871083 | E36: 5.34195 | F36: 5.5524 | G36: 497198.65 | H36: 516786.15 | I36: 19587.502 | J36: 0.039395726 | K36: Ppi
A37: Schroder Renta Plus Clase A | B37: FCI | C37: 13039.771 | D37: 0.10778283 | E37: 80.363892 | F37: 83.9691 | G37: 1047926.7 | H37: 1094937.8 | I37: 47011.092 | J37: 0.044861048 | K37: Ppi
A38: Fima Ahorro Peso | B38: FCI | C38: 2374.82 | D38: 0.10335139 | E38: 421.08574 | F38: 442.10507 | G38: 1000002.8 | H38: 1049920 | I38: 49917.125 | J38: 0.049916984 | K38: Galicia
A39: Fima Ahorro Plus | B39: FCI | C39: 9615.98 | D39: 0.10321032 | E39: 103.99364 | F39: 109.03588 | G39: 1000000.7 | H39: 1048486.9 | I39: 48486.108 | J39: 0.048486072 | K39: Galicia
... A43: BTC | B43: Cripto | C43: 1 | D43: 0.0023494053 | E43: 20647 | F43: 23867 | G43: 20647 | H43: 23867 | I43: 3220 | J43: 0.15595486 | K43: Binance

Sheet Marzo
A1: Portfolio De Inversiones | C1: P&L | D1: P&L % | E1: Valor Medio Total | F1: Valor Portolio | G1: Efectivo | H1: Medio+Efectivo | I1: Portfolio+Efectivo | M1: Opc/Futuros | N1: 0
C2: 1038747.7 | D2: 0.12993873 | E2: 7994134.7 | F2: 9032882.4 | G2: 161000 | H2: 8155134.7 | I2: 9193882.4 | M2: Acciones | N2: 410678
M3: Bonos | N3: 650045.56
A4: Ticker | B4: Tipo | C4: Cantidad | D4: % Portfolio | E4: Costo medio | F4: Precio Actual | G4: Valor Medio | H4: Valor de Mercado | I4: P&L | J4: P&L % | K4: Broker | M4: Cedear | N4: 440171
A5: ALUA | B5: Acciones | C5: 15 | D5: 0.0013085524 | E5: 984 | F5: 788 | G5: 14760 | H5: 11820 | I5: -2940 | J5: -0.19918699 | K5: Eco | M5: ON | N5: 39142
A6: BYMA | B6: Acciones | C6: 30 | D6: 0.0014281156 | E6: 371.26667 | F6: 430 | G6: 11138 | H6: 12900 | I6: 1762 | J6: 0.15819716 | K6: Eco | M6: FCI | N6: 6336846.3
A7: CEPU | B7: Acciones | C7: 20 | D7: 0.0029226551 | E7: 1740 | F7: 1320 | G7: 34800 | H7: 26400 | I7: -8400 | J7: -0.24137931 | K7: Eco | M7: Letras | N7: 1134591.6
A8: COME | B8: Acciones | C8: 46 | D8: 0.00075114451 | E8: 232.2337 | F8: 147.5 | G8: 10682.75 | H8: 6785 | I8: -3897.75 | J8: -0.36486392 | K8: Eco | M8: Cripto | N8: 21408
A9: EDN | B9: Acciones | C9: 25 | D9: 0.0047050319 | E9: 1270.6 | F9: 1700 | G9: 31765 | H9: 42500 | I9: 10735 | J9: 0.33795057 | K9: Eco | M9: Efectivo | N9: 107420
A10: MORI | B10: Acciones | C10: 100 | D10: 0.0026569592 | E10: 394 | F10: 240 | G10: 39400 | H10: 24000 | I10: -15400 | J10: -0.39086294 | K10: Eco | M10: Total | N10: 9140302.4
A11: PAMP | B11: Acciones | C11: 20 | D11: 0.0079819483 | E11: 4200 | F11: 3605 | G11: 84000 | H11: 72100 | I11: -11900 | J11: -0.14166667 | K11: Eco
A12: SEMI | B12: Acciones | C12: 7660 | D12: 0.02183633 | E12: 40 | F12: 25.75 | G12: 306400 | H12: 197245 | I12: -109155 | J12: -0.35625 | K12: Eco | M12: Eco | N12: 1074421
A13: TXAR | B13: Acciones | C13: 23 | D13: 0.0018740419 | E13: 963 | F13: 736 | G13: 22149 | H13: 16928 | I13: -5221 | J13: -0.2357217 | K13: Eco | M13: Ppi | N13: 4954014.6
A14: AMZN | B14: Cedear | C14: 45 | D14: 0.0082199675 | E14: 1895 | F14: 1650 | G14: 85275 | H14: 74250 | I14: -11025 | J14: -0.1292876 | K14: Eco | M14: Binance | N14: 21408
A15: BABA | B15: Cedear | C15: 1 | D15: 0.0017851445 | E15: 11400 | F15: 16125 | G15: 11400 | H15: 16125 | I15: 4725 | J15: 0.41447368 | K15: Eco | M15: Galicia | N15: 2983038.7
A16: CDE | B16: Cedear | C16: 5 | D16: 0.0038193789 | E16: 7400 | F16: 6900 | G16: 37000 | H16: 34500 | I16: -2500 | J16: -0.067567568 | K16: Eco | M16: Efectivo | N16: 107420
A17: ETHA | B17: Cedear | C17: 5 | D17: 0.0017685385 | E17: 5970 | F17: 3195 | G17: 29850 | H17: 15975 | I17: -13875 | J17: -0.46482412 | K17: Eco | M17: Total | N17: 9140302.4
A18: GOOGL | B18: Cedear | C18: 25 | D18: 0.0095207705 | E18: 3995 | F18: 3440 | G18: 99875 | H18: 86000 | I18: -13875 | J18: -0.13892365 | K18: Eco
A19: IBM | B19: Cedear | C19: 1 | D19: 0.0022335063 | E19: 17850 | F19: 20175 | G19: 17850 | H19: 20175 | I19: 2325 | J19: 0.1302521 | K19: Eco | M19: P&L Marzo/Febrero
A20: KO | B20: Cedear | C20: 1 | D20: 0.0020480727 | E20: 15000 | F20: 18500 | G20: 15000 | H20: 18500 | I20: 3500 | J20: 0.23333333 | K20: Eco | M20: Opc/Futuros | N20: 0
A21: LAC | B21: Cedear | C21: 9 | D21: 0.0035022044 | E21: 3655 | F21: 3515 | G21: 32895 | H21: 31635 | I21: -1260 | J21: -0.038303694 | K21: Eco | M21: Acciones | N21: -19123.5
A22: MSFT | B22: Cedear | C22: 1 | D22: 0.0017962151 | E22: 17775 | F22: 16225 | G22: 17775 | H22: 16225 | I22: -1550 | J22: -0.087201125 | K22: Eco | M22: Bonos | N22: -78395.231
A23: PFE | B23: Cedear | C23: 1 | D23: 0.00085642652 | E23: 7790 | F23: 7736 | G23: 7790 | H23: 7736 | I23: -54 | J23: -0.0069319641 | K23: Eco | M23: Cedear | N23: -38669
A24: SPY | B24: Cedear | C24: 2 | D24: 0.0075834044 | E24: 35825 | F24: 34250 | G24: 71650 | H24: 68500 | I24: -3150 | J24: -0.043963712 | K24: Eco | M24: ON | N24: 1543
A25: VIST | B25: Cedear | C25: 3 | D25: 0.0055962203 | E25: 21041.667 | F25: 16850 | G25: 63125 | H25: 50550 | I25: -12575 | J25: -0.19920792 | K25: Eco | M25: FCI | N25: 5029146.5
A26: AE38 | B26: Bonos | C26: 60 | D26: 0.005440124 | E26: 740 | F26: 819 | G26: 44400 | H26: 49140 | I26: 4740 | J26: 0.10675676 | K26: Eco | M26: Letras | N26: 8015.03
A27: AL30 | B27: Bonos | C27: 163 | D27: 0.0149775 | E27: 770 | F27: 830 | G27: 125510 | H27: 135290 | I27: 9780 | J27: 0.077922078 | K27: Eco | M27: Cripto | N27: -752
A28: T13F6 | B28: Bonos | C28: 444714 | D28: 0.051546731 | E28: 1.11175 | F28: 1.047 | G28: 494410.79 | H28: 465615.56 | I28: -28795.232 | J28: -0.058241511 | K28: Ppi
A29: MR39O | B29: ON | C29: 12 | D29: 0.0016871691 | E29: 1169 | F29: 1270 | G29: 14028 | H29: 15240 | I29: 1212 | J29: 0.086398631 | K29: Eco
A30: YMCJO | B30: ON | C30: 19 | D30: 0.00264611 | E30: 1670.7895 | F30: 1258 | G30: 31745 | H30: 23902 | I30: -7843 | J30: -0.24706253 | K30: Eco
A31: Allaria Diversificado Clase A | B31: FCI | C31: 10501.993 | D31: 0.13219953 | E31: 104.14 | F31: 113.7063 | G31: 1093677.6 | H31: 1194142.8 | I31: 100465.22 | J31: 0.091859996 | K31: Ppi
A32: Delta Recursos Naturales Clase A | B32: FCI | C32: 120.775 | D32: 0.012302271 | E32: 1067 | F32: 920.0991 | G32: 128866.93 | H32: 111124.97 | I32: -17741.956 | J32: -0.13767657 | K32: Ppi
A33: Max Ahorro Pesos Clase A | B33: FCI | C33: 93074.373 | D33: 0.054892235 | E33: 5.34195 | F33: 5.3273 | G33: 497198.65 | H33: 495835.11 | I33: -1363.5396 | J33: -0.0027424442 | K33: Ppi
A34: Schroder Renta Plus Clase A | B34: FCI | C34: 13039.771 | D34: 0.11607583 | E34: 80.363892 | F34: 80.4078 | G34: 1047926.7 | H34: 1048499.3 | I34: 572.55555 | J34: 0.00054636982 | K34: Ppi
A35: Adcap Ahorro Pesos Clase A | B35: FCI | C35: 38715.043 | D35: 0.055818879 | E35: 12.9 | F35: 13.0235 | G35: 499424.06 | H35: 504205.37 | I35: 4781.3079 | J35: 0.0095736434 | K35: Ppi
A36: Fima Premium | B36: FCI | C36: 15844.09 | D36: 0.10614622 | E36: 60.203245 | F36: 60.515077 | G36: 953865.62 | H36: 958806.33 | I36: 4940.7018 | J36: 0.0051796623 | K36: Galicia
A37: Fima Ahorro Plus | B37: FCI | C37: 9615.98 | D37: 0.11154688 | E37: 103.99364 | F37: 104.78286 | G37: 1000000.7 | H37: 1007589.9 | I37: 7589.143 | J37: 0.0075891373 | K37: Galicia
A38: Fima Ahorro Peso | B38: FCI | C38: 2374.82 | D38: 0.11254907 | E38: 421.08574 | F38: 428.09246 | G38: 1000002.8 | H38: 1016642.5 | I38: 16639.692 | J38: 0.016639644 | K38: Galicia
A39: S16Y5 | B39: Letras | C39: 857590 | D39: 0.12560681 | E39: -0.0040835663 | F39: 1.323 | G39: -3502.0256 | H39: 1134591.6 | I39: 1138093.6 | J39: -324.98152 | K39: Ppi
A40: BTC | B40: Cripto | C40: 1 | D40: 0.0023700076 | E40: 22000 | F40: 21408 | G40: 22000 | H40: 21408 | I40: -592 | J40: -0.026909091 | K40: Binance

Sheet Febrero
A1: Portfolio De Inversiones | C1: P&L | D1: P&L % | E1: Valor Medio Total | F1: Valor Portolio | G1: Efectivo | H1: Medio+Efectivo | I1: Portfolio+Efectivo | M1: Opc/Futuros | N1: 0
C2: -26609.188 | D2: -0.0063999368 | E2: 4157726.7 | F2: 4131117.5 | G2: 161005.18 | H2: 4318731.9 | I2: 4292122.7 | M2: Acciones | N2: 429801.5
M3: Bonos | N3: 728440.79
A4: Ticker | B4: Tipo | C4: Cantidad | D4: % Portfolio | E4: Costo medio | F4: Precio Actual | G4: Valor Medio | H4: Valor de Mercado | I4: P&L | J4: P&L % | K4: Broker | M4: Cedear | N4: 478840
A5: ALUA | B5: Acciones | C5: 15 | D5: 0.0028503183 | E5: 984 | F5: 785 | G5: 14760 | H5: 11775 | I5: -2985 | J5: -0.20223577 | K5: Eco | M5: ON | N5: 37599
A6: BYMA | B6: Acciones | C6: 30 | D6: 0.0034893706 | E6: 371.26667 | F6: 480.5 | G6: 11138 | H6: 14415 | I6: 3277 | J6: 0.29421799 | K6: Eco | M6: FCI | N6: 1307699.7
A7: CEPU | B7: Acciones | C7: 20 | D7: 0.007286164 | E7: 1740 | F7: 1505 | G7: 34800 | H7: 30100 | I7: -4700 | J7: -0.13505747 | K7: Eco | M7: Letras | N7: 1126576.5
A8: COME | B8: Acciones | C8: 46 | D8: 0.0019458415 | E8: 232.2337 | F8: 174.75 | G8: 10682.75 | H8: 8038.5 | I8: -2644.25 | J8: -0.24752522 | K8: Eco | M8: Cripto | N8: 22160
A9: EDN | B9: Acciones | C9: 25 | D9: 0.00968261 | E9: 1270.6 | F9: 1600 | G9: 31765 | H9: 40000 | I9: 8235 | J9: 0.2592476 | K9: Eco | M9: Efectivo | N9: 50856.87
A10: MORI | B10: Acciones | C10: 100 | D10: 0.0066810009 | E10: 394 | F10: 276 | G10: 39400 | H10: 27600 | I10: -11800 | J10: -0.29949239 | K10: Eco
A11: PAMP | B11: Acciones | C11: 20 | D11: 0.018493785 | E11: 4200 | F11: 3820 | G11: 84000 | H11: 76400 | I11: -7600 | J11: -0.09047619 | K11: Eco | M11: Total | N11: 4181974.4
A12: SEMI | B12: Acciones | C12: 7660 | D12: 0.049507669 | E12: 40 | F12: 26.7 | G12: 306400 | H12: 204522 | I12: -101878 | J12: -0.3325 | K12: Eco
A13: TXAR | B13: Acciones | C13: 23 | D13: 0.004103248 | E13: 963 | F13: 737 | G13: 22149 | H13: 16951 | I13: -5198 | J13: -0.23468328 | K13: Eco | M13: Ppi | N13: 2928687
A14: AMZN | B14: Cedear | C14: 45 | D14: 0.019117103 | E14: 1895 | F14: 1755 | G14: 85275 | H14: 78975 | I14: -6300 | J14: -0.073878628 | K14: Eco | M14: Binance | N14: 22160
A15: BABA | B15: Cedear | C15: 1 | D15: 0.0047565822 | E15: 11400 | F15: 19650 | G15: 11400 | H15: 19650 | I15: 8250 | J15: 0.72368421 | K15: Eco | M15: Efectivo | N15: 50856.87
A16: CDE | B16: Cedear | C16: 5 | D16: 0.0081333924 | E16: 7400 | F16: 6720 | G16: 37000 | H16: 33600 | I16: -3400 | J16: -0.091891892 | K16: Eco | M16: Total | N16: 4181974.4
A17: ETHA | B17: Cedear | C17: 5 | D17: 0.0050228539 | E17: 5970 | F17: 4150 | G17: 29850 | H17: 20750 | I17: -9100 | J17: -0.30485762 | K17: Eco
A18: GOOGL | B18: Cedear | C18: 25 | D18: 0.022027938 | E18: 3995 | F18: 3640 | G18: 99875 | H18: 91000 | I18: -8875 | J18: -0.088861076 | K18: Eco | M18: P&L Febrero/Enero
A19: IBM | B19: Cedear | C19: 1 | D19: 0.0049381311 | E19: 17850 | F19: 20400 | G19: 17850 | H19: 20400 | I19: 2550 | J19: 0.14285714 | K19: Eco | M19: Opc/Futuros | N19: 0
A20: KO | B20: Cedear | C20: 1 | D20: 0.0041695739 | E20: 15000 | F20: 17225 | G20: 15000 | H20: 17225 | I20: 2225 | J20: 0.14833333 | K20: Eco | M20: Acciones | N20: -48487
A21: LAC | B21: Cedear | C21: 9 | D21: 0.0083548821 | E21: 3655 | F21: 3835 | G21: 32895 | H21: 34515 | I21: 1620 | J21: 0.049247606 | K21: Eco | M21: Bonos | N21: 502832.79
A22: MSFT | B22: Cedear | C22: 1 | D22: 0.0039456636 | E22: 17775 | F22: 16300 | G22: 17775 | H22: 16300 | I22: -1475 | J22: -0.082981716 | K22: Eco | M22: Cedear | N22: -15150
A23: PFE | B23: Cedear | C23: 1 | D23: 0.0019486253 | E23: 7790 | F23: 8050 | G23: 7790 | H23: 8050 | I23: 260 | J23: 0.033376123 | K23: Eco | M23: ON | N23: 6451
A24: SPY | B24: Cedear | C24: 2 | D24: 0.017247149 | E24: 35825 | F24: 35625 | G24: 71650 | H24: 71250 | I24: -400 | J24: -0.0055826936 | K24: Eco | M24: FCI | N24: -31070.352
A25: TEFO | B25: Cedear | C25: 15 | D25: 0.0024509107 | E25: 605 | F25: 675 | G25: 9075 | H25: 10125 | I25: 1050 | J25: 0.11570248 | K25: Eco | M25: Letras | N25: 1097832.3
A26: VIST | B26: Cedear | C26: 3 | D26: 0.013797719 | E26: 21041.667 | F26: 19000 | G26: 63125 | H26: 57000 | I26: -6125 | J26: -0.097029703 | K26: Eco | M26: Cripto | N26: 160
A27: AE38 | B27: Bonos | C27: 60 | D27: 0.012141993 | E27: 740 | F27: 836 | G27: 44400 | H27: 50160 | I27: 5760 | J27: 0.12972973 | K27: Eco
A28: AL29 | B28: Bonos | C28: 60 | D28: 0.012548663 | E28: 826 | F28: 864 | G28: 49560 | H28: 51840 | I28: 2280 | J28: 0.046004843 | K28: Eco
A29: AL30 | B29: Bonos | C29: 163 | D29: 0.031959875 | E29: 770 | F29: 810 | G29: 125510 | H29: 132030 | I29: 6520 | J29: 0.051948052 | K29: Eco
A30: T13F6 | B30: Bonos | C30: 444714 | D30: 0.11967967 | E30: 1.11175 | F30: 1.11175 | G30: 494410.79 | H30: 494410.79 | I30: 0 | J30: 0 | K30: Ppi
A31: MR39O | B31: ON | C31: 12 | D31: 0.0033753578 | E31: 1169 | F31: 1162 | G31: 494410.79 | H31: 494410.79 | I31: 13944 | J31: 0 | K31: Eco
A32: YMCJO | B32: ON | C32: 19 | D32: 0.0057260535 | E32: 1670.7895 | F32: 1245 | G32: 31745 | H32: 23655 | I32: -8090 | J32: -0.25484328 | K32: Eco
A33: Allaria Diversificado Clase A | B33: FCI | C33: 10501.993 | D33: 0.28772252 | E33: 104.14 | F33: 113.18 | G33: 1093677.6 | H33: 1188615.6 | I33: 94938.017 | J33: 0.086806222 | K33: Ppi
A34: Delta Recursos Naturales Clase A | B34: FCI | C34: 120.775 | D34: 0.028826134 | E34: 1067 | F34: 986 | G34: 128866.93 | H34: 119084.15 | I34: -9782.775 | J34: -0.075913777 | K34: Ppi
A35: S16A5 | B35: Letras | C35: 391711 | D35: 0.12171995 | E35: 1.27 | F35: 1.2837 | G35: 497472.97 | H35: 502839.41 | I35: 5366.4407 | J35: 0.010787402 | K35: Ppi
A36: S14M5 | B36: Letras | C36: 493143 | D36: 0.15098508 | E36: 1.25 | F36: 1.26482 | G36: 616428.75 | H36: 623737.13 | I36: 7308.3793 | J36: 0.011856 | K36: Ppi
A37: BTC | B37: Cripto | C37: 1 | D37: 0.0053641659 | E37: 22000 | F37: 22160 | G37: 22000 | H37: 22160 | I37: 160 | J37: 0.0072727273 | K37: Binance

Sheet Enero
A1: Portfolio De Inversiones | C1: P&L | D1: P&L % | E1: Valor Medio Total | F1: Valor Portolio | G1: Efectivo | H1: Medio+Efectivo | I1: Portfolio+Efectivo | M1: Opc/Futuros | N1: 0
C2: 41498.55 | D2: 0.01610312 | E2: 2577050.3 | F2: 2618548.8 | G2: 161005.18 | H2: 2738055.5 | I2: 2779554 | M2: Acciones | N2: 478288.5
M3: Bonos | N3: 225608
A4: Ticker | B4: Tipo | C4: Cantidad | D4: % Portfolio | E4: Costo medio | F4: Precio Actual | G4: Valor Medio | H4: Valor de Mercado | I4: P&L | J4: P&L % | K4: Broker | M4: Cedear | N4: 493990
A5: ALUA | B5: Acciones | C5: 15 | D5: 0.0046399746 | E5: 984 | F5: 810 | G5: 14760 | H5: 12150 | I5: -2610 | J5: -0.17682927 | K5: Eco | M5: ON | N5: 31148
A6: BYMA | B6: Acciones | C6: 30 | D6: 0.0052586379 | E6: 371.26667 | F6: 459 | G6: 11138 | H6: 13770 | I6: 2632 | J6: 0.23630813 | K6: Eco | M6: FCI | N6: 1338770.1
A7: CEPU | B7: Acciones | C7: 20 | D7: 0.0126024 | E7: 1740 | F7: 1650 | G7: 34800 | H7: 33000 | I7: -1800 | J7: -0.051724138 | K7: Eco | M7: Letras | N7: 28744.249
A8: COME | B8: Acciones | C8: 46 | D8: 0.0038427773 | E8: 232.2337 | F8: 218.75 | G8: 10682.75 | H8: 10062.5 | I8: -620.25 | J8: -0.058060893 | K8: Eco | M8: Cripto | N8: 22000
A9: EDN | B9: Acciones | C9: 25 | D9: 0.015275637 | E9: 1270.6 | F9: 1600 | G9: 31765 | H9: 40000 | I9: 8235 | J9: 0.2592476 | K9: Eco | M9: Efectivo | N9: 50856.87
A10: MORI | B10: Acciones | C10: 100 | D10: 0.011456727 | E10: 394 | F10: 300 | G10: 39400 | H10: 30000 | I10: -9400 | J10: -0.23857868 | K10: Eco | M10: Total | N10: 2669405.7
A11: PAMP | B11: Acciones | C11: 20 | D11: 0.029749302 | E11: 4200 | F11: 3895 | G11: 84000 | H11: 77900 | I11: -6100 | J11: -0.072619048 | K11: Eco
A12: SEMI | B12: Acciones | C12: 7660 | D12: 0.092731515 | E12: 40 | F12: 31.7 | G12: 306400 | H12: 242822 | I12: -63578 | J12: -0.2075 | K12: Eco | M12: Eco | N12: 1332505.8
A13: TXAR | B13: Acciones | C13: 23 | D13: 0.0070970607 | E13: 963 | F13: 808 | G13: 22149 | H13: 18584 | I13: -3565 | J13: -0.16095535 | K13: Eco | M13: Binance | N13: 22000
A14: AMZN | B14: Cedear | C14: 45 | D14: 0.032909449 | E14: 1895 | F14: 1915 | G14: 85275 | H14: 86175 | I14: 900 | J14: 0.01055409 | K14: Eco | M14: Efectivo | N14: 50856.87
A15: BABA | B15: Cedear | C15: 1 | D15: 0.0053082837 | E15: 11400 | F15: 13900 | G15: 11400 | H15: 13900 | I15: 2500 | J15: 0.21929825 | K15: Eco | M15: Total | N15: 2627907.1
A16: CDE | B16: Cedear | C16: 5 | D16: 0.014110869 | E16: 7400 | F16: 7390 | G16: 37000 | H16: 36950 | I16: -50 | J16: -0.0013513514 | K16: Eco
A17: ETHA | B17: Cedear | C17: 5 | D17: 0.0092990437 | E17: 5970 | F17: 4870 | G17: 29850 | H17: 24350 | I17: -5500 | J17: -0.18425461 | K17: Eco
A18: GOOGL | B18: Cedear | C18: 25 | D18: 0.036375109 | E18: 3995 | F18: 3810 | G18: 99875 | H18: 95250 | I18: -4625 | J18: -0.046307885 | K18: Eco
A19: IBM | B19: Cedear | C19: 1 | D19: 0.007733291 | E19: 17850 | F19: 20250 | G19: 17850 | H19: 20250 | I19: 2400 | J19: 0.13445378 | K19: Eco
A20: KO | B20: Cedear | C20: 1 | D20: 0.0058620255 | E20: 15000 | F20: 15350 | G20: 15000 | H20: 15350 | I20: 350 | J20: 0.023333333 | K20: Eco
A21: LAC | B21: Cedear | C21: 9 | D21: 0.012527931 | E21: 3655 | F21: 3645 | G21: 32895 | H21: 32805 | I21: -90 | J21: -0.0027359781 | K21: Eco
A22: MSFT | B22: Cedear | C22: 1 | D22: 0.0062725583 | E22: 17775 | F22: 16425 | G22: 17775 | H22: 16425 | I22: -1350 | J22: -0.075949367 | K22: Eco
A23: PFE | B23: Cedear | C23: 1 | D23: 0.0029443789 | E23: 7790 | F23: 7710 | G23: 7790 | H23: 7710 | I23: -80 | J23: -0.010269576 | K23: Eco
A24: SPY | B24: Cedear | C24: 2 | D24: 0.027610713 | E24: 35825 | F24: 36150 | G24: 71650 | H24: 72300 | I24: 650 | J24: 0.0090718772 | K24: Eco
A25: TEFO | B25: Cedear | C25: 15 | D25: 0.0035802273 | E25: 605 | F25: 625 | G25: 9075 | H25: 9375 | I25: 300 | J25: 0.033057851 | K25: Eco
A26: VIST | B26: Cedear | C26: 3 | D26: 0.024116411 | E26: 21041.667 | F26: 21050 | G26: 63125 | H26: 63150 | I26: 25 | J26: 0.0003960396 | K26: Eco
A27: AE38 | B27: Bonos | C27: 60 | D27: 0.01883486 | E27: 740 | F27: 822 | G27: 44400 | H27: 49320 | I27: 4920 | J27: 0.11081081 | K27: Eco
... A34: BTC | B34: Cripto | C34: 1 | D34: 0.0084016001 | E34: 22000 | F34: 22000 | G34: 22000 | H34: 22000 | I34: 0 | J34: 0 | K34: Binance

Sheet Acciones
A1: Mes | B1: ALUA | C1: BOLT | D1: CARC | E1: SEMI | F1: LOMA | G1: PAMP | H1: TGNO4 | I1: TRAN | J1: TXAR | K1: GGAL | L1: MORI | N1: Mes | O1: ALUA | P1: BOLT | Q1: CARC | R1: SEMI | S1: LOMA | T1: PAMP | U1: TGNO4 | V1: TRAN | W1: TXAR | X1: GGAL | Y1: MORI | Z1: INFLACION | AB1: Accion | AC1: 45261 | AD1: 3M | AE1: D3M | AF1: 6M | AG1: D6M | AH1: 9M | AI1: D9M | AJ1: 12M | AK1: D12M
A2: Enero | B2: =IFERROR(VLOOKUP($B$1,INDIRECT(A2&"!$A$2:$J$101"),8,FALSE),0) -> 12150 | C2: =IFERROR(VLOOKUP($C$1,INDIRECT(A2&"!$A$2:$J$101"),8,FALSE),0) -> 0 | D2: =IFERROR(VLOOKUP($D$1,INDIRECT(A2&"!$A$2:$J$101"),8,FALSE),0) -> 0 | E2: =IFERROR(VLOOKUP($E$1,INDIRECT(A2&"!$A$2:$J$101"),8,FALSE),0) -> 242822 | F2: =IFERROR(VLOOKUP($F$1,INDIRECT(A2&"!$A$2:$J$101"),8,FALSE),0) -> 0 | G2: =IFERROR(VLOOKUP($G$1,INDIRECT(A2&"!$A$2:$J$101"),8,FALSE),0) -> 77900 | H2: =IFERROR(VLOOKUP($H$1,INDIRECT(A2&"!$A$2:$J$101"),8,FALSE),0) -> 0 | I2: =IFERROR(VLOOKUP($I$1,INDIRECT(A2&"!$A$2:$J$101"),8,FALSE),0) -> 0 | J2: =IFERROR(VLOOKUP($J$1,INDIRECT(A2&"!$A$2:$J$101"),8,FALSE),0) -> 18584 | K2: =IFERROR(VLOOKUP($K$1,INDIRECT(A2&"!$A$2:$J$101"),8,FALSE),0) -> 0 | L2: =IFERROR(VLOOKUP($L$1,INDIRECT(A2&"!$A$2:$J$101"),8,FALSE),0) -> 30000 | N2: Enero | O2: =IFERROR(VLOOKUP($O$1,INDIRECT(A2&"!$A$2:$J$101"),9,FALSE),0) -> -2610 | P2: =IFERROR(VLOOKUP($P$1,INDIRECT(A2&"!$A$2:$J$101"),9,FALSE),0) -> 0 | Q2: =IFERROR(VLOOKUP($Q$1,INDIRECT(A2&"!$A$2:$J$101"),9,FALSE),0) -> 0 | R2: =IFERROR(VLOOKUP($R$1,INDIRECT(A2&"!$A$2:$J$101"),9,FALSE),0) -> -63578 | S2: =IFERROR(VLOOKUP($S$1,INDIRECT(A2&"!$A$2:$J$101"),9,FALSE),0) -> 0 | T2: =IFERROR(VLOOKUP($T$1,INDIRECT(A2&"!$A$2:$J$101"),9,FALSE),0) -> -6100 | U2: =IFERROR(VLOOKUP($U$1,INDIRECT(A2&"!$A$2:$J$101"),9,FALSE),0) -> 0 | V2: =IFERROR(VLOOKUP($V$1,INDIRECT(A2&"!$A$2:$J$101"),9,FALSE),0) -> 0 | W2: =IFERROR(VLOOKUP($W$1,INDIRECT(A2&"!$A$2:$J$101"),9,FALSE),0) -> -3565 | X2: =IFERROR(VLOOKUP($X$1,INDIRECT(A2&"!$A$2:$J$101"),9,FALSE),0) -> 0 | Y2: =IFERROR(VLOOKUP($Y$1,INDIRECT(A2&"!$A$2:$J$101"),9,FALSE),0) -> -9400 | Z2: =Global!M2 -> 0.022 | AB2: ALUA | AC2: ='Dic2023'!E2 -> #REF! | AD2: =B$4 -> 11820 | AE2: =IFERROR(((AD2-AC2)/AC2),0) -> 0 | AF2: =B$7 -> 10740 | AG2: =IFERROR(((AF2-AD2)/AD2),0) -> -0.091370558 | AH2: =B$10 -> 15150 | AI2: =IFERROR(((AH2-AG2)/AG2),0) -> -165809.33 | AJ2: =B$13 -> 0 | AK2: =IFERROR(((AJ2-AG2)/AG2),0) -> -1
A3: Febrero | B3: =IFERROR(VLOOKUP($B$1,INDIRECT(A3&"!$A$2:$J$101"),8,FALSE),0) -> 11775 | C3: =IFERROR(VLOOKUP($C$1,INDIRECT(A3&"!$A$2:$J$101"),8,FALSE),0) -> 0 | D3: =IFERROR(VLOOKUP($D$1,INDIRECT(A3&"!$A$2:$J$101"),8,FALSE),0) -> 0 | E3: =IFERROR(VLOOKUP($E$1,INDIRECT(A3&"!$A$2:$J$101"),8,FALSE),0) -> 204522 | F3: =IFERROR(VLOOKUP($F$1,INDIRECT(A3&"!$A$2:$J$101"),8,FALSE),0) -> 0 | G3: =IFERROR(VLOOKUP($G$1,INDIRECT(A3&"!$A$2:$J$101"),8,FALSE),0) -> 76400 | H3: =IFERROR(VLOOKUP($H$1,INDIRECT(A3&"!$A$2:$J$101"),8,FALSE),0) -> 0 | I3: =IFERROR(VLOOKUP($I$1,INDIRECT(A3&"!$A$2:$J$101"),8,FALSE),0) -> 0 | J3: =IFERROR(VLOOKUP($J$1,INDIRECT(A3&"!$A$2:$J$101"),8,FALSE),0) -> 16951 | K3: =IFERROR(VLOOKUP($K$1,INDIRECT(A3&"!$A$2:$J$101"),8,FALSE),0) -> 0 | L3: =IFERROR(VLOOKUP($L$1,INDIRECT(A3&"!$A$2:$J$101"),8,FALSE),0) -> 27600 | N3: Febrero | O3: =IFERROR(VLOOKUP($O$1,INDIRECT(A3&"!$A$2:$J$101"),9,FALSE),0) -> -2985 | P3: =IFERROR(VLOOKUP($P$1,INDIRECT(A3&"!$A$2:$J$101"),9,FALSE),0) -> 0 | Q3: =IFERROR(VLOOKUP($Q$1,INDIRECT(A3&"!$A$2:$J$101"),9,FALSE),0) -> 0 | R3: =IFERROR(VLOOKUP($R$1,INDIRECT(A3&"!$A$2:$J$101"),9,FALSE),0) -> -101878 | S3: =IFERROR(VLOOKUP($S$1,INDIRECT(A3&"!$A$2:$J$101"),9,FALSE),0) -> 0 | T3: =IFERROR(VLOOKUP($T$1,INDIRECT(A3&"!$A$2:$J$101"),9,FALSE),0) -> -7600 | U3: =IFERROR(VLOOKUP($U$1,INDIRECT(A3&"!$A$2:$J$101"),9,FALSE),0) -> 0 | V3: =IFERROR(VLOOKUP($V$1,INDIRECT(A3&"!$A$2:$J$101"),9,FALSE),0) -> 0 | W3: =IFERROR(VLOOKUP($W$1,INDIRECT(A3&"!$A$2:$J$101"),9,FALSE),0) -> -5198 | X3: =IFERROR(VLOOKUP($X$1,INDIRECT(A3&"!$A$2:$J$101"),9,FALSE),0) -> 0 | Y3: =IFERROR(VLOOKUP($Y$1,INDIRECT(A3&"!$A$2:$J$101"),9,FALSE),0) -> -11800 | Z3: =Global!M3 -> 0.024 | AB3: BOLT | AC3: ='Dic2023'!E3 -> #REF! | AD3: =C$4 -> 0 | AE3: =IFERROR(((AD3-AC3)/AC3),0) -> 0 | AF3: =C$7 -> 0 | AG3: 0 | AH3: =C$10 -> 0 | AI3: =IFERROR(((AH3-AG3)/AG3),0) -> 0 | AJ3: =C$13 -> 0 | AK3: =IFERROR(((AJ3-AG3)/AG3),0) -> 0
A4: Marzo | B4: =IFERROR(VLOOKUP($B$1,INDIRECT(A4&"!$A$2:$J$101"),8,FALSE),0) -> 11820 | C4: =IFERROR(VLOOKUP($C$1,INDIRECT(A4&"!$A$2:$J$101"),8,FALSE),0) -> 0 | D4: =IFERROR(VLOOKUP($D$1,INDIRECT(A4&"!$A$2:$J$101"),8,FALSE),0) -> 0 | E4: =IFERROR(VLOOKUP($E$1,INDIRECT(A4&"!$A$2:$J$101"),8,FALSE),0) -> 197245 | F4: =IFERROR(VLOOKUP($F$1,INDIRECT(A4&"!$A$2:$J$101"),8,FALSE),0) -> 0 | G4: =IFERROR(VLOOKUP($G$1,INDIRECT(A4&"!$A$2:$J$101"),8,FALSE),0) -> 72100 | H4: =IFERROR(VLOOKUP($H$1,INDIRECT(A4&"!$A$2:$J$101"),8,FALSE),0) -> 0 | I4: =IFERROR(VLOOKUP($I$1,INDIRECT(A4&"!$A$2:$J$101"),8,FALSE),0) -> 0 | J4: =IFERROR(VLOOKUP($J$1,INDIRECT(A4&"!$A$2:$J$101"),8,FALSE),0) -> 16928 | K4: =IFERROR(VLOOKUP($K$1,INDIRECT(A4&"!$A$2:$J$101"),8,FALSE),0) -> 0 | L4: =IFERROR(VLOOKUP($L$1,INDIRECT(A4&"!$A$2:$J$101"),8,FALSE),0) -> 24000 | N4: Marzo | O4: =IFERROR(VLOOKUP($O$1,INDIRECT(A4&"!$A$2:$J$101"),9,FALSE),0) -> -2940 | P4: =IFERROR(VLOOKUP($P$1,INDIRECT(A4&"!$A$2:$J$101"),9,FALSE),0) -> 0 | Q4: =IFERROR(VLOOKUP($Q$1,INDIRECT(A4&"!$A$2:$J$101"),9,FALSE),0) -> 0 | R4: =IFERROR(VLOOKUP($R$1,INDIRECT(A4&"!$A$2:$J$101"),9,FALSE),0) -> -109155 | S4: =IFERROR(VLOOKUP($S$1,INDIRECT(A4&"!$A$2:$J$101"),9,FALSE),0) -> 0 | T4: =IFERROR(VLOOKUP($T$1,INDIRECT(A4&"!$A$2:$J$101"),9,FALSE),0) -> -11900 | U4: =IFERROR(VLOOKUP($U$1,INDIRECT(A4&"!$A$2:$J$101"),9,FALSE),0) -> 0 | V4: =IFERROR(VLOOKUP($V$1,INDIRECT(A4&"!$A$2:$J$101"),9,FALSE),0) -> 0 | W4: =IFERROR(VLOOKUP($W$1,INDIRECT(A4&"!$A$2:$J$101"),9,FALSE),0) -> -5221 | X4: =IFERROR(VLOOKUP($X$1,INDIRECT(A4&"!$A$2:$J$101"),9,FALSE),0) -> 0 | Y4: =IFERROR(VLOOKUP($Y$1,INDIRECT(A4&"!$A$2:$J$101"),9,FALSE),0) -> -15400 | Z4: =Global!M4 -> 0.03 | AB4: CARC | AC4: ='Dic2023'!E4 -> #REF! | AD4: =D$4 -> 0 | AE4: =IFERROR(((AD4-AC4)/AC4),0) -> 0 | AF4: =D$7 -> 0 | AG4: =IFERROR(((AF4-AD4)/AD4),0) -> 0 | AH4: =D$10 -> 0 | AI4: =IFERROR(((AH4-AG4)/AG4),0) -> 0 | AJ4: =D$13 -> 0 | AK4: =IFERROR(((AJ4-AG4)/AG4),0) -> 0
A5: Abril | B5: =IFERROR(VLOOKUP($B$1,INDIRECT(A5&"!$A$2:$J$101"),8,FALSE),0) -> 9945 | C5: =IFERROR(VLOOKUP($C$1,INDIRECT(A5&"!$A$2:$J$101"),8,FALSE),0) -> 0 | D5: =IFERROR(VLOOKUP($D$1,INDIRECT(A5&"!$A$2:$J$101"),8,FALSE),0) -> 0 | E5: =IFERROR(VLOOKUP($E$1,INDIRECT(A5&"!$A$2:$J$101"),8,FALSE),0) -> 211033 | F5: =IFERROR(VLOOKUP($F$1,INDIRECT(A5&"!$A$2:$J$101"),8,FALSE),0) -> 0 | G5: =IFERROR(VLOOKUP($G$1,INDIRECT(A5&"!$A$2:$J$101"),8,FALSE),0) -> 77500 | H5: =IFERROR(VLOOKUP($H$1,INDIRECT(A5&"!$A$2:$J$101"),8,FALSE),0) -> 0 | I5: =IFERROR(VLOOKUP($I$1,INDIRECT(A5&"!$A$2:$J$101"),8,FALSE),0) -> 0 | J5: =IFERROR(VLOOKUP($J$1,INDIRECT(A5&"!$A$2:$J$101"),8,FALSE),0) -> 14145 | K5: =IFERROR(VLOOKUP($K$1,INDIRECT(A5&"!$A$2:$J$101"),8,FALSE),0) -> 0 | L5: =IFERROR(VLOOKUP($L$1,INDIRECT(A5&"!$A$2:$J$101"),8,FALSE),0) -> 26500 | N5: Abril | O5: =IFERROR(VLOOKUP($O$1,INDIRECT(A5&"!$A$2:$J$101"),9,FALSE),0) -> -4815 | P5: =IFERROR(VLOOKUP($P$1,INDIRECT(A5&"!$A$2:$J$101"),9,FALSE),0) -> 0 | Q5: =IFERROR(VLOOKUP($Q$1,INDIRECT(A5&"!$A$2:$J$101"),9,FALSE),0) -> 0 | R5: =IFERROR(VLOOKUP($R$1,INDIRECT(A5&"!$A$2:$J$101"),9,FALSE),0) -> -95367 | S5: =IFERROR(VLOOKUP($S$1,INDIRECT(A5&"!$A$2:$J$101"),9,FALSE),0) -> 0 | T5: =IFERROR(VLOOKUP($T$1,INDIRECT(A5&"!$A$2:$J$101"),9,FALSE),0) -> -6500 | U5: =IFERROR(VLOOKUP($U$1,INDIRECT(A5&"!$A$2:$J$101"),9,FALSE),0) -> 0 | V5: =IFERROR(VLOOKUP($V$1,INDIRECT(A5&"!$A$2:$J$101"),9,FALSE),0) -> 0 | W5: =IFERROR(VLOOKUP($W$1,INDIRECT(A5&"!$A$2:$J$101"),9,FALSE),0) -> -8004 | X5: =IFERROR(VLOOKUP($X$1,INDIRECT(A5&"!$A$2:$J$101"),9,FALSE),0) -> 0 | Y5: =IFERROR(VLOOKUP($Y$1,INDIRECT(A5&"!$A$2:$J$101"),9,FALSE),0) -> -12900 | Z5: =Global!M5 -> 0.028 | AB5: SEMI | AC5: ='Dic2023'!E5 -> #REF! | AD5: =E$4 -> 197245 | AE5: =IFERROR(((AD5-AC5)/AC5),0) -> 0 | AF5: =E$7 -> 168520 | AG5: =IFERROR(((AF5-AD5)/AD5),0) -> -0.14563107 | AH5: =E$10 -> 206054 | AI5: =IFERROR(((AH5-AG5)/AG5),0) -> -1414905.1 | AJ5: =E$13 -> 0 | AK5: =IFERROR(((AJ5-AG5)/AG5),0) -> -1
A6: Mayo | B6: =IFERROR(VLOOKUP($B$1,INDIRECT(A6&"!$A$2:$J$101"),8,FALSE),0) -> 11355 | C6: =IFERROR(VLOOKUP($C$1,INDIRECT(A6&"!$A$2:$J$101"),8,FALSE),0) -> 0 | D6: =IFERROR(VLOOKUP($D$1,INDIRECT(A6&"!$A$2:$J$101"),8,FALSE),0) -> 0 | E6: =IFERROR(VLOOKUP($E$1,INDIRECT(A6&"!$A$2:$J$101"),8,FALSE),0) -> 191117 | F6: =IFERROR(VLOOKUP($F$1,INDIRECT(A6&"!$A$2:$J$101"),8,FALSE),0) -> 0 | G6: =IFERROR(VLOOKUP($G$1,INDIRECT(A6&"!$A$2:$J$101"),8,FALSE),0) -> 71700 | H6: =IFERROR(VLOOKUP($H$1,INDIRECT(A6&"!$A$2:$J$101"),8,FALSE),0) -> 0 | I6: =IFERROR(VLOOKUP($I$1,INDIRECT(A6&"!$A$2:$J$101"),8,FALSE),0) -> 0 | J6: =IFERROR(VLOOKUP($J$1,INDIRECT(A6&"!$A$2:$J$101"),8,FALSE),0) -> 15203 | K6: =IFERROR(VLOOKUP($K$1,INDIRECT(A6&"!$A$2:$J$101"),8,FALSE),0) -> 0 | L6: =IFERROR(VLOOKUP($L$1,INDIRECT(A6&"!$A$2:$J$101"),8,FALSE),0) -> 25600 | N6: Mayo | O6: =IFERROR(VLOOKUP($O$1,INDIRECT(A6&"!$A$2:$J$101"),9,FALSE),0) -> -3405 | P6: =IFERROR(VLOOKUP($P$1,INDIRECT(A6&"!$A$2:$J$101"),9,FALSE),0) -> 0 | Q6: =IFERROR(VLOOKUP($Q$1,INDIRECT(A6&"!$A$2:$J$101"),9,FALSE),0) -> 0 | R6: =IFERROR(VLOOKUP($R$1,INDIRECT(A6&"!$A$2:$J$101"),9,FALSE),0) -> -115283 | S6: =IFERROR(VLOOKUP($S$1,INDIRECT(A6&"!$A$2:$J$101"),9,FALSE),0) -> 0 | T6: =IFERROR(VLOOKUP($T$1,INDIRECT(A6&"!$A$2:$J$101"),9,FALSE),0) -> -12300 | U6: =IFERROR(VLOOKUP($U$1,INDIRECT(A6&"!$A$2:$J$101"),9,FALSE),0) -> 0 | V6: =IFERROR(VLOOKUP($V$1,INDIRECT(A6&"!$A$2:$J$101"),9,FALSE),0) -> 0 | W6: =IFERROR(VLOOKUP($W$1,INDIRECT(A6&"!$A$2:$J$101"),9,FALSE),0) -> -6946 | X6: =IFERROR(VLOOKUP($X$1,INDIRECT(A6&"!$A$2:$J$101"),9,FALSE),0) -> 0 | Y6: =IFERROR(VLOOKUP($Y$1,INDIRECT(A6&"!$A$2:$J$101"),9,FALSE),0) -> -13800 | Z6: =Global!M6 -> 0.0172 | AB6: LOMA | AC6: ='Dic2023'!E6 -> #REF! | AD6: =F$4 -> 0 | AE6: =IFERROR(((AD6-AC6)/AC6),0) -> 0 | AF6: =F$7 -> 0 | AG6: =IFERROR(((AF6-AD6)/AD6),0) -> 0 | AH6: =F$10 -> 0 | AI6: =IFERROR(((AH6-AG6)/AG6),0) -> 0 | AJ6: =F$13 -> 0 | AK6: =IFERROR(((AJ6-AG6)/AG6),0) -> 0
A7: Junio | B7: =IFERROR(VLOOKUP($B$1,INDIRECT(A7&"!$A$2:$J$101"),8,FALSE),0) -> 10740 | C7: =IFERROR(VLOOKUP($C$1,INDIRECT(A7&"!$A$2:$J$101"),8,FALSE),0) -> 0 | D7: =IFERROR(VLOOKUP($D$1,INDIRECT(A7&"!$A$2:$J$101"),8,FALSE),0) -> 0 | E7: =IFERROR(VLOOKUP($E$1,INDIRECT(A7&"!$A$2:$J$101"),8,FALSE),0) -> 168520 | F7: =IFERROR(VLOOKUP($F$1,INDIRECT(A7&"!$A$2:$J$101"),8,FALSE),0) -> 0 | G7: =IFERROR(VLOOKUP($G$1,INDIRECT(A7&"!$A$2:$J$101"),8,FALSE),0) -> 73700 | H7: =IFERROR(VLOOKUP($H$1,INDIRECT(A7&"!$A$2:$J$101"),8,FALSE),0) -> 0 | I7: =IFERROR(VLOOKUP($I$1,INDIRECT(A7&"!$A$2:$J$101"),8,FALSE),0) -> 0 | J7: =IFERROR(VLOOKUP($J$1,INDIRECT(A7&"!$A$2:$J$101"),8,FALSE),0) -> 14168 | K7: =IFERROR(VLOOKUP($K$1,INDIRECT(A7&"!$A$2:$J$101"),8,FALSE),0) -> 0 | L7: =IFERROR(VLOOKUP($L$1,INDIRECT(A7&"!$A$2:$J$101"),8,FALSE),0) -> 20600 | N7: Junio | O7: =IFERROR(VLOOKUP($O$1,INDIRECT(A7&"!$A$2:$J$101"),9,FALSE),0) -> -4020 | P7: =IFERROR(VLOOKUP($P$1,INDIRECT(A7&"!$A$2:$J$101"),9,FALSE),0) -> 0 | Q7: =IFERROR(VLOOKUP($Q$1,INDIRECT(A7&"!$A$2:$J$101"),9,FALSE),0) -> 0 | R7: =IFERROR(VLOOKUP($R$1,INDIRECT(A7&"!$A$2:$J$101"),9,FALSE),0) -> -137880 | S7: =IFERROR(VLOOKUP($S$1,INDIRECT(A7&"!$A$2:$J$101"),9,FALSE),0) -> 0 | T7: =IFERROR(VLOOKUP($T$1,INDIRECT(A7&"!$A$2:$J$101"),9,FALSE),0) -> -10300 | U7: =IFERROR(VLOOKUP($U$1,INDIRECT(A7&"!$A$2:$J$101"),9,FALSE),0) -> 0 | V7: =IFERROR(VLOOKUP($V$1,INDIRECT(A7&"!$A$2:$J$101"),9,FALSE),0) -> 0 | W7: =IFERROR(VLOOKUP($W$1,INDIRECT(A7&"!$A$2:$J$101"),9,FALSE),0) -> -7981 | X7: =IFERROR(VLOOKUP($X$1,INDIRECT(A7&"!$A$2:$J$101"),9,FALSE),0) -> 0 | Y7: =IFERROR(VLOOKUP($Y$1,INDIRECT(A7&"!$A$2:$J$101"),9,FALSE),0) -> -18800 | Z7: =Global!M7 -> 0.016 | AB7: PAMP | AC7: ='Dic2023'!E7 -> #REF! | AD7: =G$4 -> 72100 | AE7: =IFERROR(((AD7-AC7)/AC7),0) -> 0 | AF7: =G$7 -> 73700 | AG7: =IFERROR(((AF7-AD7)/AD7),0) -> 0.022191401 | AH7: =G$10 -> 107900 | AI7: =IFERROR(((AH7-AG7)/AG7),0) -> 4862242.8 | AJ7: =G$13 -> 0 | AK7: =IFERROR(((AJ7-AG7)/AG7),0) -> -1
A8: Julio | B8: =IFERROR(VLOOKUP($B$1,INDIRECT(A8&"!$A$2:$J$101"),8,FALSE),0) -> 11235 | C8: =IFERROR(VLOOKUP($C$1,INDIRECT(A8&"!$A$2:$J$101"),8,FALSE),0) -> 0 | D8: =IFERROR(VLOOKUP($D$1,INDIRECT(A8&"!$A$2:$J$101"),8,FALSE),0) -> 0 | E8: =IFERROR(VLOOKUP($E$1,INDIRECT(A8&"!$A$2:$J$101"),8,FALSE),0) -> 190351 | F8: =IFERROR(VLOOKUP($F$1,INDIRECT(A8&"!$A$2:$J$101"),8,FALSE),0) -> 0 | G8: =IFERROR(VLOOKUP($G$1,INDIRECT(A8&"!$A$2:$J$101"),8,FALSE),0) -> 81900 | H8: =IFERROR(VLOOKUP($H$1,INDIRECT(A8&"!$A$2:$J$101"),8,FALSE),0) -> 0 | I8: =IFERROR(VLOOKUP($I$1,INDIRECT(A8&"!$A$2:$J$101"),8,FALSE),0) -> 0 | J8: =IFERROR(VLOOKUP($J$1,INDIRECT(A8&"!$A$2:$J$101"),8,FALSE),0) -> 14950 | K8: =IFERROR(VLOOKUP($K$1,INDIRECT(A8&"!$A$2:$J$101"),8,FALSE),0) -> 0 | L8: =IFERROR(VLOOKUP($L$1,INDIRECT(A8&"!$A$2:$J$101"),8,FALSE),0) -> 22100 | N8: Julio | O8: =IFERROR(VLOOKUP($O$1,INDIRECT(A8&"!$A$2:$J$101"),9,FALSE),0) -> -3525 | P8: =IFERROR(VLOOKUP($P$1,INDIRECT(A8&"!$A$2:$J$101"),9,FALSE),0) -> 0 | Q8: =IFERROR(VLOOKUP($Q$1,INDIRECT(A8&"!$A$2:$J$101"),9,FALSE),0) -> 0 | R8: =IFERROR(VLOOKUP($R$1,INDIRECT(A8&"!$A$2:$J$101"),9,FALSE),0) -> -116049 | S8: =IFERROR(VLOOKUP($S$1,INDIRECT(A8&"!$A$2:$J$101"),9,FALSE),0) -> 0 | T8: =IFERROR(VLOOKUP($T$1,INDIRECT(A8&"!$A$2:$J$101"),9,FALSE),0) -> -2100 | U8: =IFERROR(VLOOKUP($U$1,INDIRECT(A8&"!$A$2:$J$101"),9,FALSE),0) -> 0 | V8: =IFERROR(VLOOKUP($V$1,INDIRECT(A8&"!$A$2:$J$101"),9,FALSE),0) -> 0 | W8: =IFERROR(VLOOKUP($W$1,INDIRECT(A8&"!$A$2:$J$101"),9,FALSE),0) -> -7199 | X8: =IFERROR(VLOOKUP($X$1,INDIRECT(A8&"!$A$2:$J$101"),9,FALSE),0) -> 0 | Y8: =IFERROR(VLOOKUP($Y$1,INDIRECT(A8&"!$A$2:$J$101"),9,FALSE),0) -> -17300 | Z8: =Global!M8 -> 0.02 | AB8: TGNO4 | AC8: ='Dic2023'!E8 -> #REF! | AD8: =H$4 -> 0 | AE8: =IFERROR(((AD8-AC8)/AC8),0) -> 0 | AF8: =H$7 -> 0 | AG8: =IFERROR(((AF8-AD8)/AD8),0) -> 0 | AH8: =H$10 -> 0 | AI8: =IFERROR(((AH8-AG8)/AG8),0) -> 0 | AJ8: =H$13 -> 0 | AK8: =IFERROR(((AJ8-AG8)/AG8),0) -> 0
A9: Agosto | B9: =IFERROR(VLOOKUP($B$1,INDIRECT(A9&"!$A$2:$J$101"),8,FALSE),0) -> 10552.5 | C9: =IFERROR(VLOOKUP($C$1,INDIRECT(A9&"!$A$2:$J$101"),8,FALSE),0) -> 0 | D9: =IFERROR(VLOOKUP($D$1,INDIRECT(A9&"!$A$2:$J$101"),8,FALSE),0) -> 0 | E9: =IFERROR(VLOOKUP($E$1,INDIRECT(A9&"!$A$2:$J$101"),8,FALSE),0) -> 140944 | F9: =IFERROR(VLOOKUP($F$1,INDIRECT(A9&"!$A$2:$J$101"),8,FALSE),0) -> 0 | G9: =IFERROR(VLOOKUP($G$1,INDIRECT(A9&"!$A$2:$J$101"),8,FALSE),0) -> 67650 | H9: =IFERROR(VLOOKUP($H$1,INDIRECT(A9&"!$A$2:$J$101"),8,FALSE),0) -> 0 | I9: =IFERROR(VLOOKUP($I$1,INDIRECT(A9&"!$A$2:$J$101"),8,FALSE),0) -> 0 | J9: =IFERROR(VLOOKUP($J$1,INDIRECT(A9&"!$A$2:$J$101"),8,FALSE),0) -> 11684 | K9: =IFERROR(VLOOKUP($K$1,INDIRECT(A9&"!$A$2:$J$101"),8,FALSE),0) -> 0 | L9: =IFERROR(VLOOKUP($L$1,INDIRECT(A9&"!$A$2:$J$101"),8,FALSE),0) -> 3030 | N9: Agosto | O9: =IFERROR(VLOOKUP($O$1,INDIRECT(A9&"!$A$2:$J$101"),9,FALSE),0) -> -4207.5 | P9: =IFERROR(VLOOKUP($P$1,INDIRECT(A9&"!$A$2:$J$101"),9,FALSE),0) -> 0 | Q9: =IFERROR(VLOOKUP($Q$1,INDIRECT(A9&"!$A$2:$J$101"),9,FALSE),0) -> 0 | R9: =IFERROR(VLOOKUP($R$1,INDIRECT(A9&"!$A$2:$J$101"),9,FALSE),0) -> -165456 | S9: =IFERROR(VLOOKUP($S$1,INDIRECT(A9&"!$A$2:$J$101"),9,FALSE),0) -> 0 | T9: =IFERROR(VLOOKUP($T$1,INDIRECT(A9&"!$A$2:$J$101"),9,FALSE),0) -> -16350 | U9: =IFERROR(VLOOKUP($U$1,INDIRECT(A9&"!$A$2:$J$101"),9,FALSE),0) -> 0 | V9: =IFERROR(VLOOKUP($V$1,INDIRECT(A9&"!$A$2:$J$101"),9,FALSE),0) -> 0 | W9: =IFERROR(VLOOKUP($W$1,INDIRECT(A9&"!$A$2:$J$101"),9,FALSE),0) -> -10465 | X9: =IFERROR(VLOOKUP($X$1,INDIRECT(A9&"!$A$2:$J$101"),9,FALSE),0) -> 0 | Y9: =IFERROR(VLOOKUP($Y$1,INDIRECT(A9&"!$A$2:$J$101"),9,FALSE),0) -> -36370 | Z9: =Global!M9 | AB9: TRAN | AC9: ='Dic2023'!E9 -> #REF! | AD9: =I$4 -> 0 | AE9: =IFERROR(((AD9-AC9)/AC9),0) -> 0 | AF9: =I$7 -> 0 | AG9: =IFERROR(((AF9-AD9)/AD9),0) -> 0 | AH9: =I$10 -> 0 | AI9: =IFERROR(((AH9-AG9)/AG9),0) -> 0 | AJ9: =I$13 -> 0 | AK9: =IFERROR(((AJ9-AG9)/AG9),0) -> 0
A10: Septiembre | B10: =IFERROR(VLOOKUP($B$1,INDIRECT(A10&"!$A$2:$J$101"),8,FALSE),0) -> 15150 | C10: =IFERROR(VLOOKUP($C$1,INDIRECT(A10&"!$A$2:$J$101"),8,FALSE),0) -> 0 | D10: =IFERROR(VLOOKUP($D$1,INDIRECT(A10&"!$A$2:$J$101"),8,FALSE),0) -> 0 | E10: =IFERROR(VLOOKUP($E$1,INDIRECT(A10&"!$A$2:$J$101"),8,FALSE),0) -> 206054 | F10: =IFERROR(VLOOKUP($F$1,INDIRECT(A10&"!$A$2:$J$101"),8,FALSE),0) -> 0 | G10: =IFERROR(VLOOKUP($G$1,INDIRECT(A10&"!$A$2:$J$101"),8,FALSE),0) -> 107900 | H10: =IFERROR(VLOOKUP($H$1,INDIRECT(A10&"!$A$2:$J$101"),8,FALSE),0) -> 0 | I10: =IFERROR(VLOOKUP($I$1,INDIRECT(A10&"!$A$2:$J$101"),8,FALSE),0) -> 0 | J10: =IFERROR(VLOOKUP($J$1,INDIRECT(A10&"!$A$2:$J$101"),8,FALSE),0) -> 18365.5 | K10: =IFERROR(VLOOKUP($K$1,INDIRECT(A10&"!$A$2:$J$101"),8,FALSE),0) -> 0 | L10: =IFERROR(VLOOKUP($L$1,INDIRECT(A10&"!$A$2:$J$101"),8,FALSE),0) -> 4850 | N10: Septiembre | O10: =IFERROR(VLOOKUP($O$1,INDIRECT(A10&"!$A$2:$J$101"),9,FALSE),0) -> 390 | P10: =IFERROR(VLOOKUP($P$1,INDIRECT(A10&"!$A$2:$J$101"),9,FALSE),0) -> 0 | Q10: =IFERROR(VLOOKUP($Q$1,INDIRECT(A10&"!$A$2:$J$101"),9,FALSE),0) -> 0 | R10: =IFERROR(VLOOKUP($R$1,INDIRECT(A10&"!$A$2:$J$101"),9,FALSE),0) -> -100346 | S10: =IFERROR(VLOOKUP($S$1,INDIRECT(A10&"!$A$2:$J$101"),9,FALSE),0) -> 0 | T10: =IFERROR(VLOOKUP($T$1,INDIRECT(A10&"!$A$2:$J$101"),9,FALSE),0) -> 23900 | U10: =IFERROR(VLOOKUP($U$1,INDIRECT(A10&"!$A$2:$J$101"),9,FALSE),0) -> 0 | V10: =IFERROR(VLOOKUP($V$1,INDIRECT(A10&"!$A$2:$J$101"),9,FALSE),0) -> 0 | W10: =IFERROR(VLOOKUP($W$1,INDIRECT(A10&"!$A$2:$J$101"),9,FALSE),0) -> -3783.5 | X10: =IFERROR(VLOOKUP($X$1,INDIRECT(A10&"!$A$2:$J$101"),9,FALSE),0) -> 0 | Y10: =IFERROR(VLOOKUP($Y$1,INDIRECT(A10&"!$A$2:$J$101"),9,FALSE),0) -> -34550 | Z10: =Global!M10 | AB10: TXAR | AC10: ='Dic2023'!E10 -> #REF! | AD10: =J$4 -> 16928 | AE10: =IFERROR(((AD10-AC10)/AC10),0) -> 0 | AF10: =J$7 -> 14168 | AG10: =IFERROR(((AF10-AD10)/AD10),0) -> -0.16304348 | AH10: =J$10 -> 18365.5 | AI10: =IFERROR(((AH10-AG10)/AG10),0) -> -112642.73 | AJ10: =J$13 -> 0 | AK10: =IFERROR(((AJ10-AG10)/AG10),0) -> -1
A11: Octubre | B11: =IFERROR(VLOOKUP($B$1,INDIRECT(A11&"!$A$2:$J$101"),8,FALSE),0) -> 0 | C11: =IFERROR(VLOOKUP($C$1,INDIRECT(A11&"!$A$2:$J$101"),8,FALSE),0) -> 0 | D11: =IFERROR(VLOOKUP($D$1,INDIRECT(A11&"!$A$2:$J$101"),8,FALSE),0) -> 0 | E11: =IFERROR(VLOOKUP($E$1,INDIRECT(A11&"!$A$2:$J$101"),8,FALSE),0) -> 0 | F11: =IFERROR(VLOOKUP($F$1,INDIRECT(A11&"!$A$2:$J$101"),8,FALSE),0) -> 0 | G11: =IFERROR(VLOOKUP($G$1,INDIRECT(A11&"!$A$2:$J$101"),8,FALSE),0) -> 0 | H11: =IFERROR(VLOOKUP($H$1,INDIRECT(A11&"!$A$2:$J$101"),8,FALSE),0) -> 0 | I11: =IFERROR(VLOOKUP($I$1,INDIRECT(A11&"!$A$2:$J$101"),8,FALSE),0) -> 0 | J11: =IFERROR(VLOOKUP($J$1,INDIRECT(A11&"!$A$2:$J$101"),8,FALSE),0) -> 0 | K11: =IFERROR(VLOOKUP($K$1,INDIRECT(A11&"!$A$2:$J$101"),8,FALSE),0) -> 0 | L11: =IFERROR(VLOOKUP($L$1,INDIRECT(A11&"!$A$2:$J$101"),8,FALSE),0) -> 0 | N11: Octubre | O11: =IFERROR(VLOOKUP($O$1,INDIRECT(A11&"!$A$2:$J$101"),9,FALSE),0) -> 0 | P11: =IFERROR(VLOOKUP($P$1,INDIRECT(A11&"!$A$2:$J$101"),9,FALSE),0) -> 0 | Q11: =IFERROR(VLOOKUP($Q$1,INDIRECT(A11&"!$A$2:$J$101"),9,FALSE),0) -> 0 | R11: =IFERROR(VLOOKUP($R$1,INDIRECT(A11&"!$A$2:$J$101"),9,FALSE),0) -> 0 | S11: =IFERROR(VLOOKUP($S$1,INDIRECT(A11&"!$A$2:$J$101"),9,FALSE),0) -> 0 | T11: =IFERROR(VLOOKUP($T$1,INDIRECT(A11&"!$A$2:$J$101"),9,FALSE),0) -> 0 | U11: =IFERROR(VLOOKUP($U$1,INDIRECT(A11&"!$A$2:$J$101"),9,FALSE),0) -> 0 | V11: =IFERROR(VLOOKUP($V$1,INDIRECT(A11&"!$A$2:$J$101"),9,FALSE),0) -> 0 | W11: =IFERROR(VLOOKUP($W$1,INDIRECT(A11&"!$A$2:$J$101"),9,FALSE),0) -> 0 | X11: =IFERROR(VLOOKUP($X$1,INDIRECT(A11&"!$A$2:$J$101"),9,FALSE),0) -> 0 | Y11: =IFERROR(VLOOKUP($Y$1,INDIRECT(A11&"!$A$2:$J$101"),9,FALSE),0) -> 0 | Z11: =Global!M11 | AB11: GGAL | AC11: 0 | AD11: =K$4 -> 0 | AE11: 0 | AF11: =K$7 -> 0 | AG11: =IFERROR(((AF11-AD11)/AD11),0) -> 0 | AH11: =K$10 -> 0 | AI11: =IFERROR(((AH11-AG11)/AG11),0) -> 0 | AJ11: =K$13 -> 0 | AK11: =IFERROR(((AJ11-AG11)/AG11),0) -> 0
A12: Noviembre | B12: =IFERROR(VLOOKUP($B$1,INDIRECT(A12&"!$A$2:$J$101"),8,FALSE),0) -> 0 | C12: =IFERROR(VLOOKUP($C$1,INDIRECT(A12&"!$A$2:$J$101"),8,FALSE),0) -> 0 | D12: =IFERROR(VLOOKUP($D$1,INDIRECT(A12&"!$A$2:$J$101"),8,FALSE),0) -> 0 | E12: =IFERROR(VLOOKUP($E$1,INDIRECT(A12&"!$A$2:$J$101"),8,FALSE),0) -> 0 | F12: =IFERROR(VLOOKUP($F$1,INDIRECT(A12&"!$A$2:$J$101"),8,FALSE),0) -> 0 | G12: =IFERROR(VLOOKUP($G$1,INDIRECT(A12&"!$A$2:$J$101"),8,FALSE),0) -> 0 | H12: =IFERROR(VLOOKUP($H$1,INDIRECT(A12&"!$A$2:$J$101"),8,FALSE),0) -> 0 | I12: =IFERROR(VLOOKUP($I$1,INDIRECT(A12&"!$A$2:$J$101"),8,FALSE),0) -> 0 | J12: =IFERROR(VLOOKUP($J$1,INDIRECT(A12&"!$A$2:$J$101"),8,FALSE),0) -> 0 | K12: =IFERROR(VLOOKUP($K$1,INDIRECT(A12&"!$A$2:$J$101"),8,FALSE),0) -> 0 | L12: =IFERROR(VLOOKUP($L$1,INDIRECT(A12&"!$A$2:$J$101"),8,FALSE),0) -> 0 | N12: Noviembre | O12: =IFERROR(VLOOKUP($O$1,INDIRECT(A12&"!$A$2:$J$101"),9,FALSE),0) -> 0 | P12: =IFERROR(VLOOKUP($P$1,INDIRECT(A12&"!$A$2:$J$101"),9,FALSE),0) -> 0 | Q12: =IFERROR(VLOOKUP($Q$1,INDIRECT(A12&"!$A$2:$J$101"),9,FALSE),0) -> 0 | R12: =IFERROR(VLOOKUP($R$1,INDIRECT(A12&"!$A$2:$J$101"),9,FALSE),0) -> 0 | S12: =IFERROR(VLOOKUP($S$1,INDIRECT(A12&"!$A$2:$J$101"),9,FALSE),0) -> 0 | T12: =IFERROR(VLOOKUP($T$1,INDIRECT(A12&"!$A$2:$J$101"),9,FALSE),0) -> 0 | U12: =IFERROR(VLOOKUP($U$1,INDIRECT(A12&"!$A$2:$J$101"),9,FALSE),0) -> 0 | V12: =IFERROR(VLOOKUP($V$1,INDIRECT(A12&"!$A$2:$J$101"),9,FALSE),0) -> 0 | W12: =IFERROR(VLOOKUP($W$1,INDIRECT(A12&"!$A$2:$J$101"),9,FALSE),0) -> 0 | X12: =IFERROR(VLOOKUP($X$1,INDIRECT(A12&"!$A$2:$J$101"),9,FALSE),0) -> 0 | Y12: =IFERROR(VLOOKUP($Y$1,INDIRECT(A12&"!$A$2:$J$101"),9,FALSE),0) -> 0 | Z12: =Global!M12 | AB12: MORI | AC12: 0 | AD12: =L$4 -> 24000 | AE12: 0 | AF12: =L$7 -> 20600 | AG12: =IFERROR(((AF12-AD12)/AD12),0) -> -0.14166667 | AH12: =L$10 -> 4850 | AI12: =IFERROR(((AH12-AG12)/AG12),0) -> -34236.294 | AJ12: =L$13 -> 0 | AK12: =IFERROR(((AJ12-AG12)/AG12),0) -> -1
A13: Diciembre | B13: =IFERROR(VLOOKUP($B$1,INDIRECT(A13&"!$A$2:$J$101"),8,FALSE),0) -> 0 | C13: =IFERROR(VLOOKUP($C$1,INDIRECT(A13&"!$A$2:$J$101"),8,FALSE),0) -> 0 | D13: =IFERROR(VLOOKUP($D$1,INDIRECT(A13&"!$A$2:$J$101"),8,FALSE),0) -> 0 | E13: =IFERROR(VLOOKUP($E$1,INDIRECT(A13&"!$A$2:$J$101"),8,FALSE),0) -> 0 | F13: =IFERROR(VLOOKUP($F$1,INDIRECT(A13&"!$A$2:$J$101"),8,FALSE),0) -> 0 | G13: {=IFERROR(VLOOKUP(#REF!,INDIRECT(#REF!&"!$A$2:$J$101"),8,FALSE),0)} -> 0 | H13: =IFERROR(VLOOKUP($H$1,INDIRECT(A13&"!$A$2:$J$101"),8,FALSE),0) -> 0 | I13: =IFERROR(VLOOKUP($I$1,INDIRECT(A13&"!$A$2:$J$101"),8,FALSE),0) -> 0 | J13: =IFERROR(VLOOKUP($J$1,INDIRECT(A13&"!$A$2:$J$101"),8,FALSE),0) -> 0 | K13: =IFERROR(VLOOKUP($K$1,INDIRECT(A13&"!$A$2:$J$101"),8,FALSE),0) -> 0 | L13: =IFERROR(VLOOKUP($L$1,INDIRECT(A13&"!$A$2:$J$101"),8,FALSE),0) -> 0 | N13: Diciembre | O13: =IFERROR(VLOOKUP($O$1,INDIRECT(A13&"!$A$2:$J$101"),9,FALSE),0) -> 0 | P13: =IFERROR(VLOOKUP($P$1,INDIRECT(A13&"!$A$2:$J$101"),9,FALSE),0) -> 0 | Q13: =IFERROR(VLOOKUP($Q$1,INDIRECT(A13&"!$A$2:$J$101"),9,FALSE),0) -> 0 | R13: =IFERROR(VLOOKUP($R$1,INDIRECT(A13&"!$A$2:$J$101"),9,FALSE),0) -> 0 | S13: =IFERROR(VLOOKUP($S$1,INDIRECT(A13&"!$A$2:$J$101"),9,FALSE),0) -> 0 | T13: =IFERROR(VLOOKUP($T$1,INDIRECT(A13&"!$A$2:$J$101"),9,FALSE),0) -> 0 | U13: =IFERROR(VLOOKUP($U$1,INDIRECT(A13&"!$A$2:$J$101"),9,FALSE),0) -> 0 | V13: =IFERROR(VLOOKUP($V$1,INDIRECT(A13&"!$A$2:$J$101"),9,FALSE),0) -> 0 | W13: =IFERROR(VLOOKUP($W$1,INDIRECT(A13&"!$A$2:$J$101"),9,FALSE),0) -> 0 | X13: =IFERROR(VLOOKUP($X$1,INDIRECT(A13&"!$A$2:$J$101"),9,FALSE),0) -> 0 | Y13: =IFERROR(VLOOKUP($Y$1,INDIRECT(A13&"!$A$2:$J$101"),9,FALSE),0) -> 0 | Z13: =Global!M13
A14: Total | B14: =SUM(B2:B13) -> 104722.5 | C14: =SUM(C2:C13) -> 0 | D14: =SUM(D2:D13) -> 0 | E14: =SUM(E2:E13) -> 1752608 | F14: =SUM(F2:F13) -> 0 | G14: =SUM(G2:G13) -> 706750 | H14: =SUM(H2:H13) -> 0 | I14: =SUM(I2:I13) -> 0 | ... L14: =SUM(L2:L13) -> 184280 | N14: Promedio | O14: =AVERAGE(O2:O13) -> -2343.125 | P14: =AVERAGE(P2:P13) -> 0 | Q14: =AVERAGE(Q2:Q13) -> 0 | R14: =AVERAGE(R2:R13) -> -83749.333 | S14: =AVERAGE(S2:S13) -> 0 | T14: =AVERAGE(T2:T13) -> -4104.1667 | U14: =AVERAGE(U2:U13) -> 0 | V14: =AVERAGE(V2:V13) -> 0 | ... Z14: =AVERAGE(Z2:Z13) -> 0.022457143
N15: Acumulado | O15: =SUM(O2:O13) -> -28117.5 | P15: =SUM(P2:P13) -> 0 | Q15: =SUM(Q2:Q13) -> 0 | R15: =SUM(R2:R13) -> -1004992 | S15: =SUM(S2:S13) -> 0 | T15: =SUM(T2:T13) -> -49250 | U15: =SUM(U2:U13) -> 0 | V15: =SUM(V2:V13) -> 0 | ... Z15: =SUM(Z2:Z13) -> 0.1572 | AB15: Watchlist | AD15: Tiempo Real | AE15: Ultimo Cierre | AF15: Ult. Precio Bajo 52w | AG15: Ult. Precio Alto 52w | AH15: Variación del precio % | AI15: Variación del precio | AJ15: Variacion l52-h52) | AK15: Meta
AB16: Accion | AC16: Empresa | AD16: Ticket | AE16: price | AF16: closeyest | AG16: low52 | AH16: high52 | AI16: changepct | AJ16: change | AK16: % | AL16: Meta
A17: P&L | N17: P&L | P17: Variacion % | Q17: Check | AB17: Morixe | AC17: MORI | AD17: =IFERROR(__xludf.DUMMYFUNCTION("GOOGLEFINANCE(""BCBA:""&$AC$17,AE$16)"),48.5) -> 48.5 | AE17: =IFERROR(__xludf.DUMMYFUNCTION("GOOGLEFINANCE(""BCBA:""&$AC$17,AF$16)"),47.9) -> 47.9 | AF17: =IFERROR(__xludf.DUMMYFUNCTION("GOOGLEFINANCE(""BCBA:""&$AC$17,AG$16)"),24.05) -> 24.05 | AG17: =IFERROR(__xludf.DUMMYFUNCTION("GOOGLEFINANCE(""BCBA:""&$AC$17,AH$16)"),59.2) -> 59.2 | AH17: =IFERROR(__xludf.DUMMYFUNCTION("(GOOGLEFINANCE(""BCBA:""&$AC$17,AI$16))/100"),0.0125) -> 0.0125 | AI17: =IFERROR(__xludf.DUMMYFUNCTION("GOOGLEFINANCE(""BCBA:""&$AC$17,AJ$16)"),0.6) -> 0.6 | AJ17: =(AG17/AF17)-1 -> 1.4615385 | AK17: 90
A18: Mes | B18: ALUA | C18: BOLT | D18: CARC | E18: SEMI | F18: LOMA | G18: PAMP | H18: TGNO4 | I18: TRAN | J18: TXAR | K18: GGAL | L18: MORI | N18: ALUA | O18: =B$31 -> #REF! | P18: =((B$31-B$32)/B$32)+100% -> #REF! | Q18: =(B$32+(B$32*P18))-B$32 -> #REF!
A19: Enero | B19: =B2-B32 -> #REF! | C19: =C2-C32 -> #REF! | D19: =D2-D32 -> #REF! | E19: =E2-E32 -> #REF! | F19: =F2-F32 -> #REF! | G19: =G2-G32 -> #REF! | H19: =H2-H32 -> #REF! | I19: =I2-I32 -> #REF! | J19: =J2-J32 -> #REF! | K19: =L2 -> 30000 | L19: 0 | N19: BOLT | O19: =C$31 -> #REF! | P19: =((C$31-C$32)/C$32)+100% -> #REF! | Q19: =(C$32+(C$32*P19))-C$32 -> #REF!
A20: Febrero | B20: =B3-B2 -> -375 | C20: =C3-C2 -> 0 | D20: =D3-D2 -> 0 | E20: =E3-E2 -> -38300 | F20: =F3-F2 -> 0 | G20: =G3-G2 -> -1500 | H20: =H3-H2 -> 0 | I20: =I3-I2 -> 0 | J20: =J3-J2 -> -1633 | K20: =L3 -> 27600 | L20: 0 | N20: CARC | O20: =D$31 -> #REF! | P20: =((D$31-D$32)/D$32)+100% -> #REF! | Q20: =(C$32+(C$32*P20))-C$32 -> #REF! | AB20: changepct | AC20: el cambio porcentual en el precio desde el cierre del día de negociación anterior
A21: Marzo | B21: =B4-B3 -> 45 | C21: =C4-C3 -> 0 | D21: =D4-D3 -> 0 | E21: =E4-E3 -> -7277 | F21: =F4-F3 -> 0 | G21: =G4-G3 -> -4300 | H21: =H4-H3 -> 0 | I21: =I4-I3 -> 0 | J21: =J4-J3 -> -23 | K21: =L4 -> 24000 | L21: 0 | N21: SEMI | O21: =E$31 -> #REF! | P21: =((E$31-E$32)/E$32)+100% -> #REF! | Q21: =(E$32+(E$32*P21))-E$32 -> #REF! | AB21: change | AC21: The price change since the previous trading day's close.
A22: Abril | B22: =B5-B4 -> -1875 | C22: =C5-C4 -> 0 | D22: =D5-D4 -> 0 | E22: =E5-E4 -> 13788 | F22: =F5-F4 -> 0 | G22: =G5-G4 -> 5400 | H22: =H5-H4 -> 0 | I22: =I5-I4 -> 0 | J22: =J5-J4 -> -2783 | K22: =L5 -> 26500 | L22: 0 | N22: LOMA | O22: =F$31 -> #REF! | P22: =((F$31-F$32)/F$32)+100% -> #REF! | Q22: =(F$32+(F$32*P22))-F$32 -> #REF!
A23: Mayo | B23: =B6-B5 -> 1410 | C23: 0 | D23: =D6-D5 -> 0 | E23: =E6-E5 -> -19916 | F23: =F6-F5 -> 0 | G23: =G6-G5 -> -5800 | H23: =H6-H5 -> 0 | I23: =I6-I5 -> 0 | J23: =J6-J5 -> 1058 | K23: 0 | L23: 0 | N23: PAMP | O23: =G$31 -> #REF! | P23: =((G$31-G$32)/G$32)+100% -> #REF! | Q23: =(G$32+(G$32*P23))-G$32 -> #REF!
A24: Junio | B24: =B7-B6 -> -615 | C24: 0 | D24: =D7-D6 -> 0 | E24: =E7-E6 -> -22597 | F24: =F7-F6 -> 0 | G24: =G7-G6 -> 2000 | H24: =H7-H6 -> 0 | I24: =I7-I6 -> 0 | J24: =J7-J6 -> -1035 | K24: =K7-K6 -> 0 | L24: =L7-L6 -> -5000 | N24: TGNO4 | O24: =H$31 -> #REF! | P24: =((H$31-H$32)/H$32)+100% -> #REF! | Q24: =(H$32+(H$32*P24))-H$32 -> #REF!
A25: Julio | B25: 0 | C25: =C8-C7 -> 0 | D25: 0 | E25: 0 | F25: 0 | G25: 0 | H25: 0 | I25: 0 | J25: =K8 -> 0 | K25: =K7-K6 -> 0 | L25: 0 | N25: TRAN | O25: =I$31 -> #REF! | P25: =((I$31-I$32)/I$32)+100% -> #REF! | Q25: =(I$32+(I$32*P25))-I$32 -> #REF!
A26: Agosto | B26: =B9-B8 -> -682.5 | C26: =C9-C8 -> 0 | D26: =D9-D8 -> 0 | E26: =F9-F8 -> 0 | F26: =G9-G8 -> -14250 | G26: =H9-H8 -> 0 | H26: =I9-I8 -> 0 | I26: =J9-J8 -> -3266 | J26: =K9 -> 0 | K26: =L9 -> 3030 | L26: 0 | N26: TXAR | O26: =J$31 -> #REF! | P26: =((J$31-J$32)/J$32)+100% -> #REF! | Q26: =(J$32+(J$32*P26))-J$32 -> #REF!
A27: Septiembre | B27: =B10-B9 -> 4597.5 | C27: =C10-C9 -> 0 | D27: =D10-D9 -> 0 | E27: =F10-F9 -> 0 | F27: =G10-G9 -> 40250 | G27: =H10-H9 -> 0 | H27: =I10-I9 -> 0 | I27: =J10-J9 -> 6681.5 | J27: =K10 -> 0 | K27: =L10 -> 4850 | L27: 0 | N27: GGAL | O27: =K$31 -> 115980 | P27: =SI.ERROR(((K$31-K$32)/K$32)+100%,0) -> #ERROR! | Q27: =(K$32+(K$32*P27))-K$32 -> #ERROR!
A28: Octubre | B28: =B11-B10 -> -15150 | C28: =C11-C10 -> 0 | D28: =D11-D10 -> 0 | E28: =F11-F10 -> 0 | F28: =G11-G10 -> -107900 | G28: =H11-H10 -> 0 | H28: =I11-I10 -> 0 | I28: =J11-J10 -> -18365.5 | J28: =K11 -> 0 | K28: =L11 -> 0 | L28: 0 | N28: MORI | O28: =L$31 -> -5000 | P28: =IFERROR(((L$31-L$32)/L$32)+100%,0) -> 0 | Q28: =(L$32+(L$32*P28))-L$32 -> 0
A29: Noviembre | B29: =B12-B11 -> 0 | C29: =C12-C11 -> 0 | D29: =D12-D11 -> 0 | E29: =F12-F11 -> 0 | F29: =G12-G11 -> 0 | G29: =H12-H11 -> 0 | H29: =I12-I11 -> 0 | I29: =J12-J11 -> 0 | J29: =K12 -> 0 | K29: =L12 -> 0 | L29: 0 | N29: INFLACION | P29: =Global!P2 -> 0.1572
A30: Diciembre | B30: =B13-B12 -> 0 | C30: =C13-C12 -> 0 | D30: =D13-D12 -> 0 | E30: =F13-F12 -> 0 | F30: =G13-G12 -> 0 | G30: =H13-H12 -> 0 | H30: =I13-I12 -> 0 | I30: =J13-J12 -> 0 | J30: =K13 -> 0 | K30: =L13 -> 0 | L30: 0
A31: Total | B31: =SUM(B19:B30) -> #REF! | C31: =SUM(C19:C30) -> #REF! | D31: =SUM(D19:D30) -> #REF! | E31: =SUM(E19:E30) -> #REF! | F31: =SUM(F19:F30) -> #REF! | G31: =SUM(G19:G30) -> #REF! | H31: =SUM(H19:H30) -> #REF! | I31: =SUM(I19:I30) -> #REF! | ... L31: =SUM(L19:L30) -> -5000
A32: Capital | B32: ='Dic2023'!$E2 -> #REF! | C32: ='Dic2023'!$E4 -> #REF! | D32: ='Dic2023'!$E4 -> #REF! | E32: ='Dic2023'!$E5 -> #REF! | F32: ='Dic2023'!$E6 -> #REF! | G32: ='Dic2023'!$E7 -> #REF! | H32: ='Dic2023'!$E8 -> #REF! | I32: ='Dic2023'!$E9 -> #REF! | J32: ='Dic2023'!$E10 -> #REF! | K32: 0 | L32: 0

Sheet Cedear
A1: Mes | B1: AMZN | C1: GOOGL | D1: KO | E1: MSFT | F1: SPY | G1: TEFO | H1: ARKK | I1: IBM | K1: Mes | L1: AMZN | M1: GOOGL | N1: KO | O1: MSFT | P1: SPY | Q1: TEFO | R1: ARKK | S1: INFLACION | U1: Acumulado | W1: 45261 | X1: 3M | Y1: D3M | Z1: 6M | AA1: D6M | AB1: 9M | AC1: D9M | AD1: 12M | AE1: D12M
A2: Enero | B2: =IFERROR(VLOOKUP($B$1,INDIRECT(A2&"!$A$2:$J$101"),8,FALSE),0) -> 86175 | C2: =IFERROR(VLOOKUP($C$1,INDIRECT(A2&"!$A$2:$J$101"),8,FALSE),0) -> 95250 | D2: =IFERROR(VLOOKUP($G$1,INDIRECT(A2&"!$A$2:$J$101"),8,FALSE),0) -> 9375 | E2: =IFERROR(VLOOKUP($E$1,INDIRECT(A2&"!$A$2:$J$101"),8,FALSE),0) -> 16425 | F2: =IFERROR(VLOOKUP($F$1,INDIRECT(A2&"!$A$2:$J$101"),8,FALSE),0) -> 72300 | G2: =IFERROR(VLOOKUP($G$1,INDIRECT(A2&"!$A$2:$J$101"),8,FALSE),0) -> 9375 | H2: =IFERROR(VLOOKUP($H$1,INDIRECT(A2&"!$A$2:$J$101"),8,FALSE),0) -> 0 | I2: =IFERROR(VLOOKUP($I$1,INDIRECT(A2&"!$A$2:$J$101"),8,FALSE),0) -> 20250 | K2: Enero | L2: =IFERROR(VLOOKUP($L$1,INDIRECT(A2&"!$A$2:$J$101"),9,FALSE),0) -> 900 | M2: =IFERROR(VLOOKUP($M$1,INDIRECT(A2&"!$A$2:$J$101"),9,FALSE),0) -> -4625 | N2: =IFERROR(VLOOKUP($N$1,INDIRECT(A2&"!$A$2:$J$101"),9,FALSE),0) -> 350 | O2: =IFERROR(VLOOKUP($O$1,INDIRECT(A2&"!$A$2:$J$101"),9,FALSE),0) -> -1350 | P2: =IFERROR(VLOOKUP($P$1,INDIRECT(A2&"!$A$2:$J$101"),9,FALSE),0) -> 650 | Q2: =IFERROR(VLOOKUP($Q$1,INDIRECT(A2&"!$A$2:$J$101"),9,FALSE),0) -> 300 | R2: =IFERROR(VLOOKUP($R$1,INDIRECT(A2&"!$A$2:$J$101"),9,FALSE),0) -> 0 | S2: =Global!M2 -> 0.022 | U2: AMZN | V2: =L15 -> 18270 | W2: ='Dic2023'!E16 -> #REF! | X2: =B$4 -> 74250 | Y2: =IFERROR(((X2-W2)/W2),0) -> 0 | Z2: =B$7 -> 85500 | AA2: =IFERROR(((Z2-X2)/X2),0) -> 0.15151515 | AB2: =B$10 -> 110610 | AC2: =IFERROR(((AB2-AA2)/AA2),0) -> 730025 | AD2: =B$13 -> 0 | AE2: =IFERROR(((AD2-AA2)/AA2),0) -> -1
A3: Febrero | B3: =IFERROR(VLOOKUP($B$1,INDIRECT(A3&"!$A$2:$J$101"),8,FALSE),0) -> 78975 | C3: =IFERROR(VLOOKUP($C$1,INDIRECT(A3&"!$A$2:$J$101"),8,FALSE),0) -> 91000 | D3: =IFERROR(VLOOKUP($G$1,INDIRECT(A3&"!$A$2:$J$101"),8,FALSE),0) -> 10125 | E3: =IFERROR(VLOOKUP($E$1,INDIRECT(A3&"!$A$2:$J$101"),8,FALSE),0) -> 16300 | F3: =IFERROR(VLOOKUP($F$1,INDIRECT(A3&"!$A$2:$J$101"),8,FALSE),0) -> 71250 | G3: =IFERROR(VLOOKUP($G$1,INDIRECT(A3&"!$A$2:$J$101"),8,FALSE),0) -> 10125 | H3: =IFERROR(VLOOKUP($H$1,INDIRECT(A3&"!$A$2:$J$101"),8,FALSE),0) -> 0 | I3: =IFERROR(VLOOKUP($I$1,INDIRECT(A3&"!$A$2:$J$101"),8,FALSE),0) -> 20400 | K3: Febrero | L3: =IFERROR(VLOOKUP($L$1,INDIRECT(A3&"!$A$2:$J$101"),9,FALSE),0) -> -6300 | M3: =IFERROR(VLOOKUP($M$1,INDIRECT(A3&"!$A$2:$J$101"),9,FALSE),0) -> -8875 | N3: =IFERROR(VLOOKUP($N$1,INDIRECT(A3&"!$A$2:$J$101"),9,FALSE),0) -> 2225 | O3: =IFERROR(VLOOKUP($O$1,INDIRECT(A3&"!$A$2:$J$101"),9,FALSE),0) -> -1475 | P3: =IFERROR(VLOOKUP($P$1,INDIRECT(A3&"!$A$2:$J$101"),9,FALSE),0) -> -400 | Q3: =IFERROR(VLOOKUP($Q$1,INDIRECT(A3&"!$A$2:$J$101"),9,FALSE),0) -> 1050 | R3: =IFERROR(VLOOKUP($R$1,INDIRECT(A3&"!$A$2:$J$101"),9,FALSE),0) -> 0 | S3: =Global!M3 -> 0.024 | U3: GOOGL | V3: =M15 -> 102625 | W3: ='Dic2023'!E17 -> #REF! | X3: =C$4 -> 86000 | Y3: =IFERROR(((X3-W3)/W3),0) -> 0 | Z3: =C$7 -> 92500 | AA3: =IFERROR(((Z3-X3)/X3),0) -> 0.075581395 | AB3: =C$10 -> 210500 | AC3: =IFERROR(((AB3-AA3)/AA3),0) -> 2785075.9 | AD3: =C$13 -> 0 | AE3: =IFERROR(((AD3-AA3)/AA3),0) -> -1
A4: Marzo | B4: =IFERROR(VLOOKUP($B$1,INDIRECT(A4&"!$A$2:$J$101"),8,FALSE),0) -> 74250 | C4: =IFERROR(VLOOKUP($C$1,INDIRECT(A4&"!$A$2:$J$101"),8,FALSE),0) -> 86000 | D4: =IFERROR(VLOOKUP($G$1,INDIRECT(A4&"!$A$2:$J$101"),8,FALSE),0) -> 0 | E4: =IFERROR(VLOOKUP($E$1,INDIRECT(A4&"!$A$2:$J$101"),8,FALSE),0) -> 16225 | F4: =IFERROR(VLOOKUP($F$1,INDIRECT(A4&"!$A$2:$J$101"),8,FALSE),0) -> 68500 | G4: =IFERROR(VLOOKUP($G$1,INDIRECT(A4&"!$A$2:$J$101"),8,FALSE),0) -> 0 | H4: =IFERROR(VLOOKUP($H$1,INDIRECT(A4&"!$A$2:$J$101"),8,FALSE),0) -> 0 | I4: =IFERROR(VLOOKUP($I$1,INDIRECT(A4&"!$A$2:$J$101"),8,FALSE),0) -> 20175 | K4: Marzo | L4: =IFERROR(VLOOKUP($L$1,INDIRECT(A4&"!$A$2:$J$101"),9,FALSE),0) -> -11025 | M4: =IFERROR(VLOOKUP($M$1,INDIRECT(A4&"!$A$2:$J$101"),9,FALSE),0) -> -13875 | N4: =IFERROR(VLOOKUP($N$1,INDIRECT(A4&"!$A$2:$J$101"),9,FALSE),0) -> 3500 | O4: =IFERROR(VLOOKUP($O$1,INDIRECT(A4&"!$A$2:$J$101"),9,FALSE),0) -> -1550 | P4: =IFERROR(VLOOKUP($P$1,INDIRECT(A4&"!$A$2:$J$101"),9,FALSE),0) -> -3150 | Q4: =IFERROR(VLOOKUP($Q$1,INDIRECT(A4&"!$A$2:$J$101"),9,FALSE),0) -> 0 | R4: =IFERROR(VLOOKUP($R$1,INDIRECT(A4&"!$A$2:$J$101"),9,FALSE),0) -> 0 | S4: =Global!M4 -> 0.03 | U4: KO | V4: =N15 -> 27545 | W4: ='Dic2023'!E18 -> #REF! | X4: =D$4 -> 0 | Y4: =IFERROR(((X4-W4)/W4),0) -> 0 | Z4: =D$7 -> 0 | AA4: =IFERROR(((Z4-X4)/X4),0) -> 0 | AB4: =D$10 -> 0 | AC4: =IFERROR(((AB4-AA4)/AA4),0) -> 0 | AD4: =D$13 -> 0 | AE4: =IFERROR(((AD4-AA4)/AA4),0) -> 0
A5: Abril | B5: =IFERROR(VLOOKUP($B$1,INDIRECT(A5&"!$A$2:$J$101"),8,FALSE),0) -> 76500 | C5: =IFERROR(VLOOKUP($C$1,INDIRECT(A5&"!$A$2:$J$101"),8,FALSE),0) -> 79375 | D5: =IFERROR(VLOOKUP($G$1,INDIRECT(A5&"!$A$2:$J$101"),8,FALSE),0) -> 0 | E5: =IFERROR(VLOOKUP($E$1,INDIRECT(A5&"!$A$2:$J$101"),8,FALSE),0) -> 17275 | F5: =IFERROR(VLOOKUP($F$1,INDIRECT(A5&"!$A$2:$J$101"),8,FALSE),0) -> 67450 | G5: =IFERROR(VLOOKUP($G$1,INDIRECT(A5&"!$A$2:$J$101"),8,FALSE),0) -> 0 | H5: =IFERROR(VLOOKUP($H$1,INDIRECT(A5&"!$A$2:$J$101"),8,FALSE),0) -> 0 | I5: =IFERROR(VLOOKUP($I$1,INDIRECT(A5&"!$A$2:$J$101"),8,FALSE),0) -> 19500 | K5: Abril | L5: =IFERROR(VLOOKUP($L$1,INDIRECT(A5&"!$A$2:$J$101"),9,FALSE),0) -> -8775 | M5: =IFERROR(VLOOKUP($M$1,INDIRECT(A5&"!$A$2:$J$101"),9,FALSE),0) -> -20500 | N5: =IFERROR(VLOOKUP($N$1,INDIRECT(A5&"!$A$2:$J$101"),9,FALSE),0) -> 1050 | O5: =IFERROR(VLOOKUP($O$1,INDIRECT(A5&"!$A$2:$J$101"),9,FALSE),0) -> -500 | P5: =IFERROR(VLOOKUP($P$1,INDIRECT(A5&"!$A$2:$J$101"),9,FALSE),0) -> -4200 | Q5: =IFERROR(VLOOKUP($Q$1,INDIRECT(A5&"!$A$2:$J$101"),9,FALSE),0) -> 0 | R5: =IFERROR(VLOOKUP($R$1,INDIRECT(A5&"!$A$2:$J$101"),9,FALSE),0) -> 0 | S5: =Global!M5 -> 0.028 | U5: MSFT | V5: =O15 -> 18134 | W5: ='Dic2023'!E19 -> #REF! | X5: =E$4 -> 16225 | Y5: =IFERROR(((X5-W5)/W5),0) -> 0 | Z5: =E$7 -> 20259 | AA5: =IFERROR(((Z5-X5)/X5),0) -> 0.24862866 | AB5: =E$10 -> 24830 | AC5: =IFERROR(((AB5-AA5)/AA5),0) -> 99866.811 | AD5: =E$13 -> 0 | AE5: =IFERROR(((AD5-AA5)/AA5),0) -> -1
A6: Mayo | B6: =IFERROR(VLOOKUP($B$1,INDIRECT(A6&"!$A$2:$J$101"),8,FALSE),0) -> 77400 | C6: =IFERROR(VLOOKUP($C$1,INDIRECT(A6&"!$A$2:$J$101"),8,FALSE),0) -> 87250 | D6: =IFERROR(VLOOKUP($G$1,INDIRECT(A6&"!$A$2:$J$101"),8,FALSE),0) -> 0 | E6: =IFERROR(VLOOKUP($E$1,INDIRECT(A6&"!$A$2:$J$101"),8,FALSE),0) -> 18400 | F6: =IFERROR(VLOOKUP($F$1,INDIRECT(A6&"!$A$2:$J$101"),8,FALSE),0) -> 70850 | G6: =IFERROR(VLOOKUP($G$1,INDIRECT(A6&"!$A$2:$J$101"),8,FALSE),0) -> 0 | H6: =IFERROR(VLOOKUP($H$1,INDIRECT(A6&"!$A$2:$J$101"),8,FALSE),0) -> 0 | I6: =IFERROR(VLOOKUP($I$1,INDIRECT(A6&"!$A$2:$J$101"),8,FALSE),0) -> 20950 | K6: Mayo | L6: =IFERROR(VLOOKUP($L$1,INDIRECT(A6&"!$A$2:$J$101"),9,FALSE),0) -> -7875 | M6: =IFERROR(VLOOKUP($M$1,INDIRECT(A6&"!$A$2:$J$101"),9,FALSE),0) -> -12625 | N6: =IFERROR(VLOOKUP($N$1,INDIRECT(A6&"!$A$2:$J$101"),9,FALSE),0) -> 2225 | O6: =IFERROR(VLOOKUP($O$1,INDIRECT(A6&"!$A$2:$J$101"),9,FALSE),0) -> 625 | P6: =IFERROR(VLOOKUP($P$1,INDIRECT(A6&"!$A$2:$J$101"),9,FALSE),0) -> -800 | Q6: =IFERROR(VLOOKUP($Q$1,INDIRECT(A6&"!$A$2:$J$101"),9,FALSE),0) -> 0 | R6: =IFERROR(VLOOKUP($R$1,INDIRECT(A6&"!$A$2:$J$101"),9,FALSE),0) -> 0 | S6: =Global!M6 -> 0.0172 | U6: SPY | V6: =P15 -> 64240 | W6: ='Dic2023'!E20 -> #REF! | X6: =F$4 -> 68500 | Y6: =IFERROR(((X6-W6)/W6),0) -> 0 | Z6: =F$7 -> 75600 | AA6: =IFERROR(((Z6-X6)/X6),0) -> 0.10364964 | AB6: =F$10 -> 104100 | AC6: =IFERROR(((AB6-AA6)/AA6),0) -> 1004344.1 | AD6: =F$13 -> 0 | AE6: =IFERROR(((AD6-AA6)/AA6),0) -> -1
A7: Junio | B7: =IFERROR(VLOOKUP($B$1,INDIRECT(A7&"!$A$2:$J$101"),8,FALSE),0) -> 85500 | C7: =IFERROR(VLOOKUP($C$1,INDIRECT(A7&"!$A$2:$J$101"),8,FALSE),0) -> 92500 | D7: =IFERROR(VLOOKUP($G$1,INDIRECT(A7&"!$A$2:$J$101"),8,FALSE),0) -> 0 | E7: =IFERROR(VLOOKUP($E$1,INDIRECT(A7&"!$A$2:$J$101"),8,FALSE),0) -> 20259 | F7: =IFERROR(VLOOKUP($F$1,INDIRECT(A7&"!$A$2:$J$101"),8,FALSE),0) -> 75600 | G7: =IFERROR(VLOOKUP($G$1,INDIRECT(A7&"!$A$2:$J$101"),8,FALSE),0) -> 0 | H7: =IFERROR(VLOOKUP($H$1,INDIRECT(A7&"!$A$2:$J$101"),8,FALSE),0) -> 0 | I7: =IFERROR(VLOOKUP($I$1,INDIRECT(A7&"!$A$2:$J$101"),8,FALSE),0) -> 23800 | K7: Junio | L7: =IFERROR(VLOOKUP($L$1,INDIRECT(A7&"!$A$2:$J$101"),9,FALSE),0) -> 225 | M7: =IFERROR(VLOOKUP($M$1,INDIRECT(A7&"!$A$2:$J$101"),9,FALSE),0) -> -7375 | N7: =IFERROR(VLOOKUP($N$1,INDIRECT(A7&"!$A$2:$J$101"),9,FALSE),0) -> 2750 | O7: =IFERROR(VLOOKUP($O$1,INDIRECT(A7&"!$A$2:$J$101"),9,FALSE),0) -> 2484 | P7: =IFERROR(VLOOKUP($P$1,INDIRECT(A7&"!$A$2:$J$101"),9,FALSE),0) -> 3950 | Q7: =IFERROR(VLOOKUP($Q$1,INDIRECT(A7&"!$A$2:$J$101"),9,FALSE),0) -> 0 | R7: =IFERROR(VLOOKUP($R$1,INDIRECT(A7&"!$A$2:$J$101"),9,FALSE),0) -> 0 | S7: =Global!M7 -> 0.016 | U7: TEFO | V7: =Q15 -> 1350 | W7: ='Dic2023'!E21 -> #REF! | X7: =G$4 -> 0 | Y7: =IFERROR(((X7-W7)/W7),0) -> 0 | Z7: =G$7 -> 0 | AA7: =IFERROR(((Z7-X7)/X7),0) -> 0 | AB7: =G$10 -> 0 | AC7: =IFERROR(((AB7-AA7)/AA7),0) -> 0 | AD7: =G$13 -> 0 | AE7: =IFERROR(((AD7-AA7)/AA7),0) -> 0
A8: Julio | B8: =IFERROR(VLOOKUP($B$1,INDIRECT(A8&"!$A$2:$J$101"),8,FALSE),0) -> 90675 | C8: =IFERROR(VLOOKUP($C$1,INDIRECT(A8&"!$A$2:$J$101"),8,FALSE),0) -> 113875 | D8: =IFERROR(VLOOKUP($G$1,INDIRECT(A8&"!$A$2:$J$101"),8,FALSE),0) -> 0 | E8: =IFERROR(VLOOKUP($E$1,INDIRECT(A8&"!$A$2:$J$101"),8,FALSE),0) -> 24375 | F8: =IFERROR(VLOOKUP($F$1,INDIRECT(A8&"!$A$2:$J$101"),8,FALSE),0) -> 85800 | G8: =IFERROR(VLOOKUP($G$1,INDIRECT(A8&"!$A$2:$J$101"),8,FALSE),0) -> 0 | H8: =IFERROR(VLOOKUP($H$1,INDIRECT(A8&"!$A$2:$J$101"),8,FALSE),0) -> 0 | I8: =IFERROR(VLOOKUP($I$1,INDIRECT(A8&"!$A$2:$J$101"),8,FALSE),0) -> 22825 | K8: Julio | L8: =IFERROR(VLOOKUP($L$1,INDIRECT(A8&"!$A$2:$J$101"),9,FALSE),0) -> 5400 | M8: =IFERROR(VLOOKUP($M$1,INDIRECT(A8&"!$A$2:$J$101"),9,FALSE),0) -> 14000 | N8: =IFERROR(VLOOKUP($N$1,INDIRECT(A8&"!$A$2:$J$101"),9,FALSE),0) -> 3725 | O8: =IFERROR(VLOOKUP($O$1,INDIRECT(A8&"!$A$2:$J$101"),9,FALSE),0) -> 6600 | P8: =IFERROR(VLOOKUP($P$1,INDIRECT(A8&"!$A$2:$J$101"),9,FALSE),0) -> 14150 | Q8: =IFERROR(VLOOKUP($Q$1,INDIRECT(A8&"!$A$2:$J$101"),9,FALSE),0) -> 0 | R8: =IFERROR(VLOOKUP($R$1,INDIRECT(A8&"!$A$2:$J$101"),9,FALSE),0) -> 0 | S8: =Global!M8 -> 0.02 | U8: INFLACION | V8: =S15 -> 0.1572
A9: Agosto | B9: =IFERROR(VLOOKUP($B$1,INDIRECT(A9&"!$A$2:$J$101"),8,FALSE),0) -> 105660 | C9: =IFERROR(VLOOKUP($C$1,INDIRECT(A9&"!$A$2:$J$101"),8,FALSE),0) -> 145750 | D9: =IFERROR(VLOOKUP($G$1,INDIRECT(A9&"!$A$2:$J$101"),8,FALSE),0) -> 0 | E9: =IFERROR(VLOOKUP($E$1,INDIRECT(A9&"!$A$2:$J$101"),8,FALSE),0) -> 24020 | F9: =IFERROR(VLOOKUP($F$1,INDIRECT(A9&"!$A$2:$J$101"),8,FALSE),0) -> 93240 | G9: =IFERROR(VLOOKUP($G$1,INDIRECT(A9&"!$A$2:$J$101"),8,FALSE),0) -> 0 | H9: =IFERROR(VLOOKUP($H$1,INDIRECT(A9&"!$A$2:$J$101"),8,FALSE),0) -> 0 | I9: =IFERROR(VLOOKUP($I$1,INDIRECT(A9&"!$A$2:$J$101"),8,FALSE),0) -> 24560 | K9: Agosto | L9: =IFERROR(VLOOKUP($L$1,INDIRECT(A9&"!$A$2:$J$101"),9,FALSE),0) -> 20385 | M9: =IFERROR(VLOOKUP($M$1,INDIRECT(A9&"!$A$2:$J$101"),9,FALSE),0) -> 45875 | N9: =IFERROR(VLOOKUP($N$1,INDIRECT(A9&"!$A$2:$J$101"),9,FALSE),0) -> 4480 | O9: =IFERROR(VLOOKUP($O$1,INDIRECT(A9&"!$A$2:$J$101"),9,FALSE),0) -> 6245 | P9: =IFERROR(VLOOKUP($P$1,INDIRECT(A9&"!$A$2:$J$101"),9,FALSE),0) -> 21590 | Q9: =IFERROR(VLOOKUP($Q$1,INDIRECT(A9&"!$A$2:$J$101"),9,FALSE),0) -> 0 | R9: =IFERROR(VLOOKUP($R$1,INDIRECT(A9&"!$A$2:$J$101"),9,FALSE),0) -> 0 | S9: =Global!M9
A10: Septiembre | B10: =IFERROR(VLOOKUP($B$1,INDIRECT(A10&"!$A$2:$J$101"),8,FALSE),0) -> 110610 | C10: =IFERROR(VLOOKUP($C$1,INDIRECT(A10&"!$A$2:$J$101"),8,FALSE),0) -> 210500 | D10: =IFERROR(VLOOKUP($G$1,INDIRECT(A10&"!$A$2:$J$101"),8,FALSE),0) -> 0 | E10: =IFERROR(VLOOKUP($E$1,INDIRECT(A10&"!$A$2:$J$101"),8,FALSE),0) -> 24830 | F10: =IFERROR(VLOOKUP($F$1,INDIRECT(A10&"!$A$2:$J$101"),8,FALSE),0) -> 104100 | G10: =IFERROR(VLOOKUP($G$1,INDIRECT(A10&"!$A$2:$J$101"),8,FALSE),0) -> 0 | H10: =IFERROR(VLOOKUP($H$1,INDIRECT(A10&"!$A$2:$J$101"),8,FALSE),0) -> 0 | I10: =IFERROR(VLOOKUP($I$1,INDIRECT(A10&"!$A$2:$J$101"),8,FALSE),0) -> 31020 | K10: Septiembre | L10: =IFERROR(VLOOKUP($L$1,INDIRECT(A10&"!$A$2:$J$101"),9,FALSE),0) -> 25335 | M10: =IFERROR(VLOOKUP($M$1,INDIRECT(A10&"!$A$2:$J$101"),9,FALSE),0) -> 110625 | N10: =IFERROR(VLOOKUP($N$1,INDIRECT(A10&"!$A$2:$J$101"),9,FALSE),0) -> 7240 | O10: =IFERROR(VLOOKUP($O$1,INDIRECT(A10&"!$A$2:$J$101"),9,FALSE),0) -> 7055 | P10: =IFERROR(VLOOKUP($P$1,INDIRECT(A10&"!$A$2:$J$101"),9,FALSE),0) -> 32450 | Q10: =IFERROR(VLOOKUP($Q$1,INDIRECT(A10&"!$A$2:$J$101"),9,FALSE),0) -> 0 | R10: =IFERROR(VLOOKUP($R$1,INDIRECT(A10&"!$A$2:$J$101"),9,FALSE),0) -> 0 | S10: =Global!M10 | U10: Watchlist | W10: Tiempo Real | X10: Ultimo Cierre | Y10: Ult. Precio Bajo 52w | Z10: Ult. Precio Alto 52w | AA10: Variación del precio % | AB10: Variación del precio | AC10: Variacion l52-h52)
A11: Octubre | B11: =IFERROR(VLOOKUP($B$1,INDIRECT(A11&"!$A$2:$J$101"),8,FALSE),0) -> 0 | C11: =IFERROR(VLOOKUP($C$1,INDIRECT(A11&"!$A$2:$J$101"),8,FALSE),0) -> 0 | D11: =IFERROR(VLOOKUP($G$1,INDIRECT(A11&"!$A$2:$J$101"),8,FALSE),0) -> 0 | E11: =IFERROR(VLOOKUP($E$1,INDIRECT(A11&"!$A$2:$J$101"),8,FALSE),0) -> 0 | F11: =IFERROR(VLOOKUP($F$1,INDIRECT(A11&"!$A$2:$J$101"),8,FALSE),0) -> 0 | G11: =IFERROR(VLOOKUP($G$1,INDIRECT(A11&"!$A$2:$J$101"),8,FALSE),0) -> 0 | H11: =IFERROR(VLOOKUP($H$1,INDIRECT(A11&"!$A$2:$J$101"),8,FALSE),0) -> 0 | I11: =IFERROR(VLOOKUP($I$1,INDIRECT(A11&"!$A$2:$J$101"),8,FALSE),0) -> 0 | K11: Octubre | L11: =IFERROR(VLOOKUP($L$1,INDIRECT(A11&"!$A$2:$J$101"),9,FALSE),0) -> 0 | M11: =IFERROR(VLOOKUP($M$1,INDIRECT(A11&"!$A$2:$J$101"),9,FALSE),0) -> 0 | N11: =IFERROR(VLOOKUP($N$1,INDIRECT(A11&"!$A$2:$J$101"),9,FALSE),0) -> 0 | O11: =IFERROR(VLOOKUP($O$1,INDIRECT(A11&"!$A$2:$J$101"),9,FALSE),0) -> 0 | P11: =IFERROR(VLOOKUP($P$1,INDIRECT(A11&"!$A$2:$J$101"),9,FALSE),0) -> 0 | Q11: =IFERROR(VLOOKUP($Q$1,INDIRECT(A11&"!$A$2:$J$101"),9,FALSE),0) -> 0 | R11: =IFERROR(VLOOKUP($R$1,INDIRECT(A11&"!$A$2:$J$101"),9,FALSE),0) -> 0 | S11: =Global!M11 | U11: Empresa | V11: Ticket | W11: price | X11: closeyest | Y11: low52 | Z11: high52 | AA11: changepct | AB11: change | AC11: %
A12: Noviembre | B12: =IFERROR(VLOOKUP($B$1,INDIRECT(A12&"!$A$2:$J$101"),8,FALSE),0) -> 0 | C12: =IFERROR(VLOOKUP($C$1,INDIRECT(A12&"!$A$2:$J$101"),8,FALSE),0) -> 0 | D12: =IFERROR(VLOOKUP($G$1,INDIRECT(#REF!&"!$A$2:$J$101"),8,FALSE),0) -> 0 | E12: =IFERROR(VLOOKUP($E$1,INDIRECT(A12&"!$A$2:$J$101"),8,FALSE),0) -> 0 | F12: =IFERROR(VLOOKUP($F$1,INDIRECT(A12&"!$A$2:$J$101"),8,FALSE),0) -> 0 | G12: =IFERROR(VLOOKUP($G$1,INDIRECT(A12&"!$A$2:$J$101"),8,FALSE),0) -> 0 | H12: =IFERROR(VLOOKUP($H$1,INDIRECT(A12&"!$A$2:$J$101"),8,FALSE),0) -> 0 | I12: =IFERROR(VLOOKUP($I$1,INDIRECT(B12&"!$A$2:$J$101"),8,FALSE),0) -> 0 | K12: Noviembre | L12: =IFERROR(VLOOKUP($L$1,INDIRECT(A12&"!$A$2:$J$101"),9,FALSE),0) -> 0 | M12: =IFERROR(VLOOKUP($M$1,INDIRECT(A12&"!$A$2:$J$101"),9,FALSE),0) -> 0 | N12: =IFERROR(VLOOKUP($N$1,INDIRECT(A12&"!$A$2:$J$101"),9,FALSE),0) -> 0 | O12: =IFERROR(VLOOKUP($O$1,INDIRECT(A12&"!$A$2:$J$101"),9,FALSE),0) -> 0 | P12: =IFERROR(VLOOKUP($P$1,INDIRECT(A12&"!$A$2:$J$101"),9,FALSE),0) -> 0 | Q12: =IFERROR(VLOOKUP($Q$1,INDIRECT(A12&"!$A$2:$J$101"),9,FALSE),0) -> 0 | R12: =IFERROR(VLOOKUP($R$1,INDIRECT(A12&"!$A$2:$J$101"),9,FALSE),0) -> 0 | S12: =Global!M12 | U12: Occ Petroleum Corp | V12: OXY | W12: =IFERROR(__xludf.DUMMYFUNCTION("GOOGLEFINANCE(""BCBA:""&$V$12,W$11)"),12780.0) -> 12780 | X12: =IFERROR(__xludf.DUMMYFUNCTION("GOOGLEFINANCE(""BCBA:""&$V$12,X$11)"),12610.0) -> 12610 | Y12: =IFERROR(__xludf.DUMMYFUNCTION("GOOGLEFINANCE(""BCBA:""&$V$12,Y$11)"),8470.0) -> 8470 | Z12: =IFERROR(__xludf.DUMMYFUNCTION("GOOGLEFINANCE(""BCBA:""&$V$12,Z$11)"),15250.0) -> 15250 | AA12: =IFERROR(__xludf.DUMMYFUNCTION("(GOOGLEFINANCE(""BCBA:""&$V$12,AA$11))/100"),0.013500000000000002) -> 0.0135 | AB12: =IFERROR(__xludf.DUMMYFUNCTION("GOOGLEFINANCE(""BCBA:""&$V$12,AB$11)"),170.0) -> 170 | AC12: =(Z12/Y12)-1 -> 0.80047225
A13: Diciembre | B13: =IFERROR(VLOOKUP($B$1,INDIRECT(A13&"!$A$2:$J$101"),8,FALSE),0) -> 0 | C13: =IFERROR(VLOOKUP($C$1,INDIRECT(A13&"!$A$2:$J$101"),8,FALSE),0) -> 0 | D13: =IFERROR(VLOOKUP($G$1,INDIRECT(#REF!&"!$A$2:$J$101"),8,FALSE),0) -> 0 | E13: =IFERROR(VLOOKUP($E$1,INDIRECT(A13&"!$A$2:$J$101"),8,FALSE),0) -> 0 | F13: =IFERROR(VLOOKUP($F$1,INDIRECT(A13&"!$A$2:$J$101"),8,FALSE),0) -> 0 | G13: =IFERROR(VLOOKUP($G$1,INDIRECT(A13&"!$A$2:$J$101"),8,FALSE),0) -> 0 | H13: =IFERROR(VLOOKUP($H$1,INDIRECT(A13&"!$A$2:$J$101"),8,FALSE),0) -> 0 | I13: =IFERROR(VLOOKUP($I$1,INDIRECT(B13&"!$A$2:$J$101"),8,FALSE),0) -> 0 | K13: Diciembre | L13: =IFERROR(VLOOKUP($L$1,INDIRECT(A13&"!$A$2:$J$101"),9,FALSE),0) -> 0 | M13: =IFERROR(VLOOKUP($M$1,INDIRECT(A13&"!$A$2:$J$101"),9,FALSE),0) -> 0 | N13: =IFERROR(VLOOKUP($N$1,INDIRECT(A13&"!$A$2:$J$101"),9,FALSE),0) -> 0 | O13: =IFERROR(VLOOKUP($O$1,INDIRECT(A13&"!$A$2:$J$101"),9,FALSE),0) -> 0 | P13: =IFERROR(VLOOKUP($P$1,INDIRECT(A13&"!$A$2:$J$101"),9,FALSE),0) -> 0 | Q13: =IFERROR(VLOOKUP($Q$1,INDIRECT(A13&"!$A$2:$J$101"),9,FALSE),0) -> 0 | R13: =IFERROR(VLOOKUP($R$1,INDIRECT(A13&"!$A$2:$J$101"),9,FALSE),0) -> 0 | S13: =Global!M13 | U13: Bco Bradesco | V13: BBD | W13: =IFERROR(__xludf.DUMMYFUNCTION("GOOGLEFINANCE(""BCBA:""&$V$13,W$11)"),5550.0) -> 5550 | X13: =IFERROR(__xludf.DUMMYFUNCTION("GOOGLEFINANCE(""BCBA:""&$V$13,X$11)"),5375.0) -> 5375 | Y13: =IFERROR(__xludf.DUMMYFUNCTION("GOOGLEFINANCE(""BCBA:""&$V$13,Y$11)"),2125.0) -> 2125 | Z13: =IFERROR(__xludf.DUMMYFUNCTION("GOOGLEFINANCE(""BCBA:""&$V$13,Z$11)"),5580.0) -> 5580 | AA13: =IFERROR(__xludf.DUMMYFUNCTION("GOOGLEFINANCE(""BCBA:""&$V$13,AA$11)/100"),0.0326) -> 0.0326 | AB13: =IFERROR(__xludf.DUMMYFUNCTION("GOOGLEFINANCE(""BCBA:""&$V$13,AB$11)"),175.0) -> 175 | AC13: =(Z13/Y13)-1 -> 1.6258824
A14: Total | B14: =SUM(B2:B13) -> 785745 | C14: =SUM(C2:C13) -> 1001500 | D14: =SUM(D2:D13) -> 19500 | E14: =SUM(E2:E13) -> 178109 | F14: =SUM(F2:F13) -> 709090 | G14: =SUM(G2:G13) -> 19500 | H14: =IFERROR(VLOOKUP($H$1,INDIRECT(B14&"!$A$2:$J$101"),8,FALSE),0) -> 0 | I14: =IFERROR(VLOOKUP($H$1,INDIRECT(C14&"!$A$2:$J$101"),8,FALSE),0) -> 0 | K14: Promedio | L14: =AVERAGE(L2:L13) -> 1522.5 | M14: =AVERAGE(M2:M13) -> 8552.0833 | N14: =AVERAGE(N2:N13) -> 2295.4167 | O14: =AVERAGE(O2:O13) -> 1511.1667 | P14: =AVERAGE(P2:P13) -> 5353.3333 | Q14: =AVERAGE(Q2:Q13) -> 112.5 | R14: =AVERAGE(R2:R13) -> 0 | S14: =AVERAGE(S2:S13) -> 0.022457143 | U14: Facebook | V14: META | W14: =IFERROR(__xludf.DUMMYFUNCTION("GOOGLEFINANCE(""BCBA:""&$V$14,W$11)"),40680.0) -> 40680 | X14: =IFERROR(__xludf.DUMMYFUNCTION("GOOGLEFINANCE(""BCBA:""&$V$14,X$11)"),40240.0) -> 40240 | Y14: =IFERROR(__xludf.DUMMYFUNCTION("GOOGLEFINANCE(""BCBA:""&$V$14,Y$11)"),21925.0) -> 21925 | Z14: =IFERROR(__xludf.DUMMYFUNCTION("GOOGLEFINANCE(""BCBA:""&$V$14,Z$11)"),51225.0) -> 51225 | AA14: =IFERROR(__xludf.DUMMYFUNCTION("GOOGLEFINANCE(""BCBA:""&$V$14,AA$11)/100"),0.0109) -> 0.0109 | AB14: =IFERROR(__xludf.DUMMYFUNCTION("GOOGLEFINANCE(""BCBA:""&$V$14,AB$11)"),440.0) -> 440 | AC14: =(Z14/Y14)-1 -> 1.336374
K15: Acumulado | L15: =SUM(L2:L13) -> 18270 | M15: =SUM(M2:M13) -> 102625 | N15: =SUM(N2:N13) -> 27545 | O15: =SUM(O2:O13) -> 18134 | P15: =SUM(P2:P13) -> 64240 | Q15: =SUM(Q2:Q13) -> 1350 | R15: =SUM(R2:R13) -> 0 | S15: =SUM(S2:S13) -> 0.1572 | U15: Netflix | V15: NFLX | W15: =IFERROR(__xludf.DUMMYFUNCTION("GOOGLEFINANCE(""BCBA:""&$V$15,W$11)"),3375.0) -> 3375 | X15: =IFERROR(__xludf.DUMMYFUNCTION("GOOGLEFINANCE(""BCBA:""&$V$15,X$11)"),3312.5) -> 3312.5 | Y15: =IFERROR(__xludf.DUMMYFUNCTION("GOOGLEFINANCE(""BCBA:""&$V$15,Y$11)"),1975.0) -> 1975 | Z15: =IFERROR(__xludf.DUMMYFUNCTION("GOOGLEFINANCE(""BCBA:""&$V$15,Z$11)"),4180.0) -> 4180 | AA15: =IFERROR(__xludf.DUMMYFUNCTION("GOOGLEFINANCE(""BCBA:""&$V$15,AA$11)/100"),0.0189) -> 0.0189 | AB15: =IFERROR(__xludf.DUMMYFUNCTION("GOOGLEFINANCE(""BCBA:""&$V$15,AB$11)"),62.5) -> 62.5 | AC15: =(Z15/Y15)-1 -> 1.1164557
A17: P&L
A18: Mes | B18: AMZN | C18: GOOGL | D18: KO | E18: MSFT | F18: SPY | G18: TEFO | H18: ARKK | I18: IBM | R18: changepct | S18: el cambio porcentual en el precio desde el cierre del día de negociación anterior
A19: Enero | B19: =B2-B32 -> 51175 | C19: =C2-C32 -> 38250 | D19: =D2-D32 -> #REF! | E19: =E2-E32 -> #REF! | F19: =F2-F32 -> #REF! | G19: =G2-G32 -> #REF! | H19: =H2-H32 -> #REF! | I19: =I2-I32 -> #REF! | R19: change | S19: The price change since the previous trading day's close.
A20: Febrero | B20: =B3-B2 -> -7200 | C20: =C3-C2 -> -4250 | D20: =D3-D2 -> 750 | E20: =E3-E2 -> -125 | F20: =F3-F2 -> -1050 | G20: =G3-G2 -> 750 | H20: =H3-H2 -> 0 | I20: =I3-I2 -> 150
A21: Marzo | B21: =B4-B3 -> -4725 | C21: =C4-C3 -> -5000 | D21: =D4-D3 -> -10125 | E21: =E4-E3 -> -75 | F21: =F4-F3 -> -2750 | G21: =G4-G3 -> -10125 | H21: =H4-H3 -> 0 | I21: =I4-I3 -> -225
A22: Abril | B22: =B5-B4 -> 2250 | C22: =C5-C4 -> -6625 | D22: =D5-D4 -> 0 | E22: =E5-E4 -> 1050 | F22: =F5-F4 -> -1050 | G22: =G5-G4 -> 0 | H22: =H5-H4 -> 0 | I22: =I5-I4 -> -675
A23: Mayo | B23: =B6-B5 -> 900 | C23: =C6-C5 -> 7875 | D23: =D6-D5 -> 0 | E23: =E6-E5 -> 1125 | F23: =F6-F5 -> 3400 | G23: =G6-G5 -> 0 | H23: =H6-H5 -> 0 | I23: =I6-I5 -> 1450
A24: Junio | B24: 0 | C24: 0 | D24: 0 | E24: 0 | F24: 0 | G24: 0 | H24: 0 | I24: 0
A25: Julio | B25: 0 | C25: =C8-C7 -> 21375 | D25: =D8-D7 -> 0 | E25: =F8-F7 -> 10200 | F25: =G8-G7 -> 0 | G25: =H8-H7 -> 0 | H25: =I8-I7 -> -975 | I25: =J8-J7 -> 0
A26: Agosto | B26: =B9-B8 -> 14985 | C26: =C9-C8 -> 31875 | D26: =D9-D8 -> 0 | E26: =F9-F8 -> 7440 | F26: =G9-G8 -> 0 | G26: =H9-H8 -> 0 | H26: =I9-I8 -> 1735 | I26: =J9-J8 -> 0
A27: Septiembre | B27: =B10-B9 -> 4950 | C27: =C10-C9 -> 64750 | D27: =D10-D9 -> 0 | E27: =F10-F9 -> 10860 | F27: =G10-G9 -> 0 | G27: =H10-H9 -> 0 | H27: =I10-I9 -> 6460 | I27: =J10-J9 -> 0
A28: Octubre | B28: =B11-B10 -> -110610 | C28: =C11-C10 -> -210500 | D28: =D11-D10 -> 0 | E28: =F11-F10 -> -104100 | F28: =G11-G10 -> 0 | G28: =H11-H10 -> 0 | H28: =I11-I10 -> -31020 | I28: =J11-J10 -> 0
A29: Noviembre | B29: =B12-B11 -> 0 | C29: =C12-C11 -> 0 | D29: =D12-D11 -> 0 | E29: =F12-F11 -> 0 | F29: =G12-G11 -> 0 | G29: =H12-H11 -> 0 | H29: =I12-I11 -> 0 | I29: =J12-J11 -> 0
A30: Diciembre | B30: =B13-B12 -> 0 | C30: =C13-C12 -> 0 | D30: =D13-D12 -> 0 | E30: =F13-F12 -> 0 | F30: =G13-G12 -> 0 | G30: =H13-H12 -> 0 | H30: =I13-I12 -> 0 | I30: =J13-J12 -> 0
A31: Total | B31: =SUM(B19:B30) -> -48275 | C31: =SUM(C19:C30) -> -62250 | D31: =SUM(D19:D30) -> #REF! | E31: =SUM(E19:E30) -> #REF! | F31: =SUM(F19:F30) -> #REF! | G31: =SUM(G19:G30) -> #REF! | H31: =SUM(H19:H30) -> #REF! | I31: =SUM(I19:I30) -> #REF!
A32: Capital | B32: 35000 | C32: 57000 | D32: ='Dic2023'!$E4 -> #REF! | E32: ='Dic2023'!$E5 -> #REF! | F32: ='Dic2023'!$E6 -> #REF! | G32: ='Dic2023'!$E7 -> #REF! | H32: ='Dic2023'!$E8 -> #REF! | I32: ='Dic2023'!$E9 -> #REF!

Sheet FCI
A1: Mes | B1: Adcap Cobertura Clase A | C1: Megainver Liquidez Pesos Clase A | D1: Delta Recursos Naturales Clase A | E1: Gainvest Balanceado Clase A | F1: Schroder Renta Plus Clase A | G1: Schroder Liquidez Clase A | H1: Allaria Diversificado Clase A | I1: Schroder Renta Performance Clase A | K1: Mes | L1: Adcap Cobertura Clase A | M1: Megainver Liquidez Pesos Clase A | N1: Delta Recursos Naturales Clase A | O1: Gainvest Balanceado Clase A | P1: Schroder Renta Plus Clase A | Q1: Schroder Liquidez Clase A | R1: Allaria Diversificado Clase A | S1: INFLACION | U1: FCI | V1: P&L | W1: Variacion % | X1: Check
A2: Enero | B2: =IFERROR(VLOOKUP($B$1,INDIRECT(A2&"!$A$2:$J$101"),8,FALSE),0) -> 0 | C2: =IFERROR(VLOOKUP($C$1,INDIRECT(A2&"!$A$2:$J$101"),8,FALSE),0) -> 0 | D2: =IFERROR(VLOOKUP($D$1,INDIRECT(A2&"!$A$2:$J$101"),8,FALSE),0) -> 131040.88 | E2: =IFERROR(VLOOKUP($E$1,INDIRECT(A2&"!$A$2:$J$101"),8,FALSE),0) -> 0 | F2: {=IFERROR(VLOOKUP($F$1,INDIRECT(A2&"!$A$2:$J$101"),8,FALSE),0)} -> 0 | G2: =IFERROR(VLOOKUP($G$1,INDIRECT(A2&"!$A$2:$J$101"),8,FALSE),0) -> 0 | H2: =IFERROR(VLOOKUP($H$1,INDIRECT(A2&"!$A$2:$J$101"),8,FALSE),0) -> 1207729.2 | I2: =IFERROR(VLOOKUP($I$1,INDIRECT(B2&"!$A$2:$J$101"),8,FALSE),0) -> 0 | K2: Enero | L2: =IFERROR(VLOOKUP($L$1,INDIRECT(A2&"!$A$2:$J$101"),9,FALSE),0) -> 0 | M2: =IFERROR(VLOOKUP($M$1,INDIRECT(A2&"!$A$2:$J$101"),9,FALSE),0) -> 0 | N2: =IFERROR(VLOOKUP($N$1,INDIRECT(A2&"!$A$2:$J$101"),9,FALSE),0) -> 2173.95 | O2: =IFERROR(VLOOKUP($O$1,INDIRECT(A2&"!$A$2:$J$101"),9,FALSE),0) -> 0 | P2: =IFERROR(VLOOKUP($P$1,INDIRECT(A2&"!$A$2:$J$101"),9,FALSE),0) -> 0 | Q2: =IFERROR(VLOOKUP($Q$1,INDIRECT(A2&"!$A$2:$J$101"),9,FALSE),0) -> 0 | R2: =IFERROR(VLOOKUP($R$1,INDIRECT(A2&"!$A$2:$J$101"),9,FALSE),0) -> 114051.64 | S2: =Global!M2 -> 0.022 | U2: Adcap Cobertura Clase A | V2: =B$31 -> -3865.58 | W2: =((B$31-B$32)/B$32)+100% -> -0.035455326 | X2: =(B$32+(B$32*W2))-B$32 -> -3865.58
A3: Febrero | B3: =IFERROR(VLOOKUP($B$1,INDIRECT(A3&"!$A$2:$J$101"),8,FALSE),0) -> 0 | C3: =IFERROR(VLOOKUP($C$1,INDIRECT(A3&"!$A$2:$J$101"),8,FALSE),0) -> 0 | D3: =IFERROR(VLOOKUP($D$1,INDIRECT(A3&"!$A$2:$J$101"),8,FALSE),0) -> 119084.15 | E3: =IFERROR(VLOOKUP($E$1,INDIRECT(A3&"!$A$2:$J$101"),8,FALSE),0) -> 0 | F3: {=IFERROR(VLOOKUP($E$1,INDIRECT(B3&"!$A$2:$J$101"),8,FALSE),0)} -> 0 | G3: =IFERROR(VLOOKUP($G$1,INDIRECT(A3&"!$A$2:$J$101"),8,FALSE),0) -> 0 | H3: =IFERROR(VLOOKUP($H$1,INDIRECT(A3&"!$A$2:$J$101"),8,FALSE),0) -> 1188615.6 | I3: =IFERROR(VLOOKUP($I$1,INDIRECT(B3&"!$A$2:$J$101"),8,FALSE),0) -> 0 | K3: Febrero | L3: =IFERROR(VLOOKUP($L$1,INDIRECT(A3&"!$A$2:$J$101"),9,FALSE),0) -> 0 | M3: =IFERROR(VLOOKUP($M$1,INDIRECT(A3&"!$A$2:$J$101"),9,FALSE),0) -> 0 | N3: =IFERROR(VLOOKUP($N$1,INDIRECT(A3&"!$A$2:$J$101"),9,FALSE),0) -> -9782.775 | O3: =IFERROR(VLOOKUP($O$1,INDIRECT(A3&"!$A$2:$J$101"),9,FALSE),0) -> 0 | P3: =IFERROR(VLOOKUP($P$1,INDIRECT(A3&"!$A$2:$J$101"),9,FALSE),0) -> 0 | Q3: =IFERROR(VLOOKUP($Q$1,INDIRECT(A3&"!$A$2:$J$101"),9,FALSE),0) -> 0 | R3: =IFERROR(VLOOKUP($R$1,INDIRECT(A3&"!$A$2:$J$101"),9,FALSE),0) -> 94938.017 | S3: =Global!M3 -> 0.024 | U3: Megainver Liquidez Pesos Clase A | V3: =C$31 -> 24833.554 | W3: =((C$31-C$32)/C$32)+100% -> 0.08559374 | X3: =(C$32+(C$32*W3))-C$32 -> 24833.554
A4: Marzo | B4: =IFERROR(VLOOKUP($B$1,INDIRECT(A4&"!$A$2:$J$101"),8,FALSE),0) -> 0 | C4: =IFERROR(VLOOKUP($C$1,INDIRECT(A4&"!$A$2:$J$101"),8,FALSE),0) -> 0 | D4: =IFERROR(VLOOKUP($D$1,INDIRECT(A4&"!$A$2:$J$101"),8,FALSE),0) -> 111124.97 | E4: =IFERROR(VLOOKUP($E$1,INDIRECT(A4&"!$A$2:$J$101"),8,FALSE),0) -> 0 | F4: =IFERROR(VLOOKUP($F$1,INDIRECT(A4&"!$A$2:$J$101"),8,FALSE),0) -> 1048499.3 | G4: =IFERROR(VLOOKUP($G$1,INDIRECT(A4&"!$A$2:$J$101"),8,FALSE),0) -> 0 | H4: =IFERROR(VLOOKUP($H$1,INDIRECT(A4&"!$A$2:$J$101"),8,FALSE),0) -> 1194142.8 | I4: =IFERROR(VLOOKUP($I$1,INDIRECT(B4&"!$A$2:$J$101"),8,FALSE),0) -> 0 | K4: Marzo | L4: =IFERROR(VLOOKUP($L$1,INDIRECT(A4&"!$A$2:$J$101"),9,FALSE),0) -> 0 | M4: =IFERROR(VLOOKUP($M$1,INDIRECT(A4&"!$A$2:$J$101"),9,FALSE),0) -> 0 | N4: =IFERROR(VLOOKUP($N$1,INDIRECT(A4&"!$A$2:$J$101"),9,FALSE),0) -> -17741.956 | O4: =IFERROR(VLOOKUP($O$1,INDIRECT(A4&"!$A$2:$J$101"),9,FALSE),0) -> 0 | P4: =IFERROR(VLOOKUP($P$1,INDIRECT(A4&"!$A$2:$J$101"),9,FALSE),0) -> 572.55555 | Q4: =IFERROR(VLOOKUP($Q$1,INDIRECT(A4&"!$A$2:$J$101"),9,FALSE),0) -> 0 | R4: =IFERROR(VLOOKUP($R$1,INDIRECT(A4&"!$A$2:$J$101"),9,FALSE),0) -> 100465.22 | S4: =Global!M4 -> 0.03 | U4: Delta Recursos Naturales Clase A | V4: =D$31 -> -53541.225 | W4: =((D$31-D$32)/D$32)+100% -> -1.216846 | X4: =(D$32+(D$32*W4))-D$32 -> -53541.225
A5: Abril | B5: =IFERROR(VLOOKUP($B$1,INDIRECT(A5&"!$A$2:$J$101"),8,FALSE),0) -> 0 | C5: =IFERROR(VLOOKUP($C$1,INDIRECT(A5&"!$A$2:$J$101"),8,FALSE),0) -> 0 | D5: =IFERROR(VLOOKUP($D$1,INDIRECT(A5&"!$A$2:$J$101"),8,FALSE),0) -> 119636.16 | E5: =IFERROR(VLOOKUP($E$1,INDIRECT(A5&"!$A$2:$J$101"),8,FALSE),0) -> 0 | F5: =IFERROR(VLOOKUP($F$1,INDIRECT(A5&"!$A$2:$J$101"),8,FALSE),0) -> 1094937.8 | G5: =IFERROR(VLOOKUP($G$1,INDIRECT(A5&"!$A$2:$J$101"),8,FALSE),0) -> 0 | H5: =IFERROR(VLOOKUP($H$1,INDIRECT(A5&"!$A$2:$J$101"),8,FALSE),0) -> 1218473.8 | I5: =IFERROR(VLOOKUP($I$1,INDIRECT(B5&"!$A$2:$J$101"),8,FALSE),0) -> 0 | K5: Abril | L5: =IFERROR(VLOOKUP($L$1,INDIRECT(A5&"!$A$2:$J$101"),9,FALSE),0) -> 0 | M5: =IFERROR(VLOOKUP($M$1,INDIRECT(A5&"!$A$2:$J$101"),9,FALSE),0) -> 0 | N5: =IFERROR(VLOOKUP($N$1,INDIRECT(A5&"!$A$2:$J$101"),9,FALSE),0) -> -9230.7608 | O5: =IFERROR(VLOOKUP($O$1,INDIRECT(A5&"!$A$2:$J$101"),9,FALSE),0) -> 0 | P5: =IFERROR(VLOOKUP($P$1,INDIRECT(A5&"!$A$2:$J$101"),9,FALSE),0) -> 47011.092 | Q5: =IFERROR(VLOOKUP($Q$1,INDIRECT(A5&"!$A$2:$J$101"),9,FALSE),0) -> 0 | R5: =IFERROR(VLOOKUP($R$1,INDIRECT(A5&"!$A$2:$J$101"),9,FALSE),0) -> 124796.23 | S5: =Global!M5 -> 0.028 | U5: Gainvest Balanceado Clase A | V5: =E$31 -> 69407.984 | W5: =((E$31-E$32)/E$32)+100% -> 0.11237933 | X5: =(E$32+(E$32*W5))-E$32 -> 69407.984
A6: Mayo | B6: =IFERROR(VLOOKUP($B$1,INDIRECT(A6&"!$A$2:$J$101"),8,FALSE),0) -> 0 | C6: =IFERROR(VLOOKUP($C$1,INDIRECT(A6&"!$A$2:$J$101"),8,FALSE),0) -> 0 | D6: =IFERROR(VLOOKUP($D$1,INDIRECT(A6&"!$A$2:$J$101"),8,FALSE),0) -> 116812.73 | E6: =IFERROR(VLOOKUP($E$1,INDIRECT(A6&"!$A$2:$J$101"),8,FALSE),0) -> 0 | F6: =IFERROR(VLOOKUP($F$1,INDIRECT(A6&"!$A$2:$J$101"),8,FALSE),0) -> 1122443.9 | G6: =IFERROR(VLOOKUP($G$1,INDIRECT(A6&"!$A$2:$J$101"),8,FALSE),0) -> 0 | H6: =IFERROR(VLOOKUP($H$1,INDIRECT(A6&"!$A$2:$J$101"),8,FALSE),0) -> 1253672.3 | I6: =IFERROR(VLOOKUP($I$1,INDIRECT(B6&"!$A$2:$J$101"),8,FALSE),0) -> 0 | K6: Mayo | L6: =IFERROR(VLOOKUP($L$1,INDIRECT(A6&"!$A$2:$J$101"),9,FALSE),0) -> 0 | M6: =IFERROR(VLOOKUP($M$1,INDIRECT(A6&"!$A$2:$J$101"),9,FALSE),0) -> 0 | N6: =IFERROR(VLOOKUP($N$1,INDIRECT(A6&"!$A$2:$J$101"),9,FALSE),0) -> -12054.19 | O6: =IFERROR(VLOOKUP($O$1,INDIRECT(A6&"!$A$2:$J$101"),9,FALSE),0) -> 0 | P6: =IFERROR(VLOOKUP($P$1,INDIRECT(A6&"!$A$2:$J$101"),9,FALSE),0) -> 74517.185 | Q6: =IFERROR(VLOOKUP($Q$1,INDIRECT(A6&"!$A$2:$J$101"),9,FALSE),0) -> 0 | R6: =IFERROR(VLOOKUP($R$1,INDIRECT(A6&"!$A$2:$J$101"),9,FALSE),0) -> 159994.71 | S6: =Global!M6 -> 0.0172 | U6: Schroder Renta Plus Clase A | V6: =F$31 -> -1116504.1 | W6: =((F$31-F$32)/F$32)+100% -> -4.6521005 | X6: =(F$32+(F$32*W6))-F$32 -> -1116504.1
A7: Junio | B7: =IFERROR(VLOOKUP($B$1,INDIRECT(A7&"!$A$2:$J$101"),8,FALSE),0) -> 0 | C7: =IFERROR(VLOOKUP($C$1,INDIRECT(A7&"!$A$2:$J$101"),8,FALSE),0) -> 0 | D7: =IFERROR(VLOOKUP($D$1,INDIRECT(A7&"!$A$2:$J$101"),8,FALSE),0) -> 108335.18 | E7: =IFERROR(VLOOKUP($E$1,INDIRECT(A7&"!$A$2:$J$101"),8,FALSE),0) -> 0 | F7: =IFERROR(VLOOKUP($F$1,INDIRECT(A7&"!$A$2:$J$101"),8,FALSE),0) -> 1117247.6 | G7: =IFERROR(VLOOKUP($G$1,INDIRECT(A7&"!$A$2:$J$101"),8,FALSE),0) -> 0 | H7: =IFERROR(VLOOKUP($H$1,INDIRECT(A7&"!$A$2:$J$101"),8,FALSE),0) -> 1218231.2 | I7: =IFERROR(VLOOKUP($I$1,INDIRECT(B7&"!$A$2:$J$101"),8,FALSE),0) -> 0 | K7: Junio | L7: =IFERROR(VLOOKUP($L$1,INDIRECT(A7&"!$A$2:$J$101"),9,FALSE),0) -> 0 | M7: =IFERROR(VLOOKUP($M$1,INDIRECT(A7&"!$A$2:$J$101"),9,FALSE),0) -> 0 | N7: =IFERROR(VLOOKUP($N$1,INDIRECT(A7&"!$A$2:$J$101"),9,FALSE),0) -> -20531.75 | O7: =IFERROR(VLOOKUP($O$1,INDIRECT(A7&"!$A$2:$J$101"),9,FALSE),0) -> 0 | P7: =IFERROR(VLOOKUP($P$1,INDIRECT(A7&"!$A$2:$J$101"),9,FALSE),0) -> 69320.837 | Q7: =IFERROR(VLOOKUP($Q$1,INDIRECT(A7&"!$A$2:$J$101"),9,FALSE),0) -> 0 | R7: =IFERROR(VLOOKUP($R$1,INDIRECT(A7&"!$A$2:$J$101"),9,FALSE),0) -> 124553.64 | S7: =Global!M7 -> 0.016 | U7: Schroder Liquidez Clase A | V7: =G$31 -> -4683.279 | W7: =((G$31-G$32)/G$32)+100% -> -0.041081395 | X7: =(G$32+(G$32*W7))-G$32 -> -4683.279
A8: Julio | B8: =IFERROR(VLOOKUP($B$1,INDIRECT(A8&"!$A$2:$J$101"),8,FALSE),0) -> 0 | C8: =IFERROR(VLOOKUP($C$1,INDIRECT(A8&"!$A$2:$J$101"),8,FALSE),0) -> 0 | D8: =IFERROR(VLOOKUP($D$1,INDIRECT(A8&"!$A$2:$J$101"),8,FALSE),0) -> 123984.11 | E8: 617425.8 | F8: =IFERROR(VLOOKUP($F$1,INDIRECT(A8&"!$A$2:$J$101"),8,FALSE),0) -> 1142390.9 | G8: =IFERROR(VLOOKUP($G$1,INDIRECT(A8&"!$A$2:$J$101"),8,FALSE),0) -> 0 | H8: =IFERROR(VLOOKUP($H$1,INDIRECT(A8&"!$A$2:$J$101"),8,FALSE),0) -> 1290584.7 | I8: =IFERROR(VLOOKUP($I$1,INDIRECT(B8&"!$A$2:$J$101"),8,FALSE),0) -> 0 | K8: Julio | L8: =IFERROR(VLOOKUP($L$1,INDIRECT(A8&"!$A$2:$J$101"),9,FALSE),0) -> 0 | M8: =IFERROR(VLOOKUP($M$1,INDIRECT(A8&"!$A$2:$J$101"),9,FALSE),0) -> 0 | N8: =IFERROR(VLOOKUP($N$1,INDIRECT(A8&"!$A$2:$J$101"),9,FALSE),0) -> -4882.8125 | O8: =IFERROR(VLOOKUP($O$1,INDIRECT(A8&"!$A$2:$J$101"),9,FALSE),0) -> 0 | P8: =IFERROR(VLOOKUP($P$1,INDIRECT(A8&"!$A$2:$J$101"),9,FALSE),0) -> 94464.123 | Q8: =IFERROR(VLOOKUP($Q$1,INDIRECT(A8&"!$A$2:$J$101"),9,FALSE),0) -> 0 | R8: =IFERROR(VLOOKUP($R$1,INDIRECT(A8&"!$A$2:$J$101"),9,FALSE),0) -> 196907.12 | S8: =Global!M8 -> 0.02 | U8: Allaria Diversificado Clase A | V8: =H$31 -> 134154.28 | W8: =((H$31-H$32)/H$32)+100% -> 0.12195844 | X8: =(H$32+(H$32*W8))-H$32 -> 134154.28
A9: Agosto | B9: =IFERROR(VLOOKUP($B$1,INDIRECT(A9&"!$A$2:$J$101"),8,FALSE),0) -> 0 | C9: =IFERROR(VLOOKUP($C$1,INDIRECT(A9&"!$A$2:$J$101"),8,FALSE),0) -> 0 | D9: =IFERROR(VLOOKUP($D$1,INDIRECT(A9&"!$A$2:$J$101"),8,FALSE),0) -> 116812.73 | E9: 0 | F9: =IFERROR(VLOOKUP($F$1,INDIRECT(A9&"!$A$2:$J$101"),8,FALSE),0) -> 1122443.9 | G9: =IFERROR(VLOOKUP($G$1,INDIRECT(A9&"!$A$2:$J$101"),8,FALSE),0) -> 0 | H9: =IFERROR(VLOOKUP($H$1,INDIRECT(A9&"!$A$2:$J$101"),8,FALSE),0) -> 1253672.3 | I9: =IFERROR(VLOOKUP($I$1,INDIRECT(B9&"!$A$2:$J$101"),8,FALSE),0) -> 0 | K9: Agosto | L9: =IFERROR(VLOOKUP($L$1,INDIRECT(A9&"!$A$2:$J$101"),9,FALSE),0) -> 0 | M9: =IFERROR(VLOOKUP($M$1,INDIRECT(A9&"!$A$2:$J$101"),9,FALSE),0) -> 0 | N9: =IFERROR(VLOOKUP($N$1,INDIRECT(A9&"!$A$2:$J$101"),9,FALSE),0) -> -12054.19 | O9: =IFERROR(VLOOKUP($O$1,INDIRECT(A9&"!$A$2:$J$101"),9,FALSE),0) -> 0 | P9: =IFERROR(VLOOKUP($P$1,INDIRECT(A9&"!$A$2:$J$101"),9,FALSE),0) -> 74517.185 | Q9: =IFERROR(VLOOKUP($Q$1,INDIRECT(A9&"!$A$2:$J$101"),9,FALSE),0) -> 0 | R9: =IFERROR(VLOOKUP($R$1,INDIRECT(A9&"!$A$2:$J$101"),9,FALSE),0) -> 159994.71 | S9: =Global!M9 | U9: INFLACION | V9: =Global!L2 -> 0.01610312
A10: Septiembre | B10: =IFERROR(VLOOKUP($B$1,INDIRECT(A10&"!$A$2:$J$101"),8,FALSE),0) -> 0 | C10: =IFERROR(VLOOKUP($C$1,INDIRECT(A10&"!$A$2:$J$101"),8,FALSE),0) -> 0 | D10: =IFERROR(VLOOKUP($D$1,INDIRECT(A10&"!$A$2:$J$101"),8,FALSE),0) -> 116812.73 | E10: 0 | F10: =IFERROR(VLOOKUP($F$1,INDIRECT(A10&"!$A$2:$J$101"),8,FALSE),0) -> 1122443.9 | G10: =IFERROR(VLOOKUP($G$1,INDIRECT(A10&"!$A$2:$J$101"),8,FALSE),0) -> 0 | H10: =IFERROR(VLOOKUP($H$1,INDIRECT(A10&"!$A$2:$J$101"),8,FALSE),0) -> 1253672.3 | I10: =IFERROR(VLOOKUP($I$1,INDIRECT(B10&"!$A$2:$J$101"),8,FALSE),0) -> 0 | K10: Septiembre | L10: =IFERROR(VLOOKUP($L$1,INDIRECT(A10&"!$A$2:$J$101"),9,FALSE),0) -> 0 | M10: =IFERROR(VLOOKUP($M$1,INDIRECT(A10&"!$A$2:$J$101"),9,FALSE),0) -> 0 | N10: =IFERROR(VLOOKUP($N$1,INDIRECT(A10&"!$A$2:$J$101"),9,FALSE),0) -> -12054.19 | O10: =IFERROR(VLOOKUP($O$1,INDIRECT(A10&"!$A$2:$J$101"),9,FALSE),0) -> 0 | P10: =IFERROR(VLOOKUP($P$1,INDIRECT(A10&"!$A$2:$J$101"),9,FALSE),0) -> 74517.185 | Q10: =IFERROR(VLOOKUP($Q$1,INDIRECT(A10&"!$A$2:$J$101"),9,FALSE),0) -> 0 | R10: =IFERROR(VLOOKUP($R$1,INDIRECT(A10&"!$A$2:$J$101"),9,FALSE),0) -> 159994.71 | S10: =Global!M10
A11: Octubre | B11: =IFERROR(VLOOKUP($B$1,INDIRECT(A11&"!$A$2:$J$101"),8,FALSE),0) -> 0 | C11: =IFERROR(VLOOKUP($C$1,INDIRECT(A11&"!$A$2:$J$101"),8,FALSE),0) -> 0 | D11: =IFERROR(VLOOKUP($D$1,INDIRECT(A11&"!$A$2:$J$101"),8,FALSE),0) -> 0 | E11: 0 | F11: =IFERROR(VLOOKUP($F$1,INDIRECT(A11&"!$A$2:$J$101"),8,FALSE),0) -> 0 | G11: =IFERROR(VLOOKUP($G$1,INDIRECT(A11&"!$A$2:$J$101"),8,FALSE),0) -> 0 | H11: 0 | I11: =IFERROR(VLOOKUP($I$1,INDIRECT(B11&"!$A$2:$J$101"),8,FALSE),0) -> 0 | K11: Octubre | L11: =IFERROR(VLOOKUP($L$1,INDIRECT(A11&"!$A$2:$J$101"),9,FALSE),0) -> 0 | M11: =IFERROR(VLOOKUP($M$1,INDIRECT(A11&"!$A$2:$J$101"),9,FALSE),0) -> 0 | N11: =IFERROR(VLOOKUP($N$1,INDIRECT(A11&"!$A$2:$J$101"),9,FALSE),0) -> 0 | O11: =IFERROR(VLOOKUP($O$1,INDIRECT(A11&"!$A$2:$J$101"),9,FALSE),0) -> 0 | P11: =IFERROR(VLOOKUP($P$1,INDIRECT(A11&"!$A$2:$J$101"),9,FALSE),0) -> 0 | Q11: =IFERROR(VLOOKUP($Q$1,INDIRECT(A11&"!$A$2:$J$101"),9,FALSE),0) -> 0 | R11: =IFERROR(VLOOKUP($R$1,INDIRECT(A11&"!$A$2:$J$101"),9,FALSE),0) -> 0 | S11: =Global!M11
A12: Noviembre | B12: =IFERROR(VLOOKUP($B$1,INDIRECT(A12&"!$A$2:$J$101"),8,FALSE),0) -> 0 | C12: =IFERROR(VLOOKUP($C$1,INDIRECT(A12&"!$A$2:$J$101"),8,FALSE),0) -> 0 | D12: =IFERROR(VLOOKUP($D$1,INDIRECT(A12&"!$A$2:$J$101"),8,FALSE),0) -> 0 | E12: 0 | F12: =IFERROR(VLOOKUP($F$1,INDIRECT(A12&"!$A$2:$J$101"),8,FALSE),0) -> 0 | G12: =IFERROR(VLOOKUP($G$1,INDIRECT(A12&"!$A$2:$J$101"),8,FALSE),0) -> 0 | H12: =IFERROR(VLOOKUP($H$1,INDIRECT(A12&"!$A$2:$J$101"),8,FALSE),0) -> 0 | I12: =IFERROR(VLOOKUP($I$1,INDIRECT(B12&"!$A$2:$J$101"),8,FALSE),0) -> 0 | K12: Noviembre | L12: =IFERROR(VLOOKUP($L$1,INDIRECT(A12&"!$A$2:$J$101"),9,FALSE),0) -> 0 | M12: =IFERROR(VLOOKUP($M$1,INDIRECT(A12&"!$A$2:$J$101"),9,FALSE),0) -> 0 | N12: =IFERROR(VLOOKUP($N$1,INDIRECT(A12&"!$A$2:$J$101"),9,FALSE),0) -> 0 | O12: =IFERROR(VLOOKUP($O$1,INDIRECT(A12&"!$A$2:$J$101"),9,FALSE),0) -> 0 | P12: =IFERROR(VLOOKUP($P$1,INDIRECT(A12&"!$A$2:$J$101"),9,FALSE),0) -> 0 | Q12: =IFERROR(VLOOKUP($Q$1,INDIRECT(A12&"!$A$2:$J$101"),9,FALSE),0) -> 0 | R12: =IFERROR(VLOOKUP($R$1,INDIRECT(A12&"!$A$2:$J$101"),9,FALSE),0) -> 0 | S12: =Global!M12
A13: Diciembre | B13: =IFERROR(VLOOKUP($B$1,INDIRECT(A13&"!$A$2:$J$101"),8,FALSE),0) -> 0 | C13: =IFERROR(VLOOKUP($C$1,INDIRECT(A13&"!$A$2:$J$101"),8,FALSE),0) -> 0 | D13: =IFERROR(VLOOKUP($D$1,INDIRECT(A13&"!$A$2:$J$101"),8,FALSE),0) -> 0 | E13: =IFERROR(VLOOKUP($E$1,INDIRECT(A13&"!$A$2:$J$101"),8,FALSE),0) -> 0 | F13: =IFERROR(VLOOKUP($E$1,INDIRECT(B13&"!$A$2:$J$101"),8,FALSE),0) -> 0 | G13: =IFERROR(VLOOKUP($G$1,INDIRECT(A13&"!$A$2:$J$101"),8,FALSE),0) -> 0 | H13: =IFERROR(VLOOKUP($H$1,INDIRECT(A13&"!$A$2:$J$101"),8,FALSE),0) -> 0 | I13: =IFERROR(VLOOKUP($I$1,INDIRECT(B13&"!$A$2:$J$101"),8,FALSE),0) -> 0 | K13: Diciembre | L13: =IFERROR(VLOOKUP($L$1,INDIRECT(A13&"!$A$2:$J$101"),9,FALSE),0) -> 0 | M13: =IFERROR(VLOOKUP($M$1,INDIRECT(A13&"!$A$2:$J$101"),9,FALSE),0) -> 0 | N13: =IFERROR(VLOOKUP($N$1,INDIRECT(A13&"!$A$2:$J$101"),9,FALSE),0) -> 0 | O13: =IFERROR(VLOOKUP($O$1,INDIRECT(A13&"!$A$2:$J$101"),9,FALSE),0) -> 0 | P13: =IFERROR(VLOOKUP($P$1,INDIRECT(A13&"!$A$2:$J$101"),9,FALSE),0) -> 0 | Q13: =IFERROR(VLOOKUP($Q$1,INDIRECT(A13&"!$A$2:$J$101"),9,FALSE),0) -> 0 | R13: =IFERROR(VLOOKUP($R$1,INDIRECT(A13&"!$A$2:$J$101"),9,FALSE),0) -> 0 | S13: =Global!M13
A14: Total | B14: =SUM(B2:B13) -> 0 | C14: =SUM(C2:C13) -> 0 | D14: =SUM(D2:D13) -> 1063643.6 | E14: =SUM(E2:E13) -> 617425.8 | F14: =SUM(F2:F13) -> 7770407.4 | G14: =SUM(G2:G13) -> 0 | H14: =SUM(H2:H13) -> 11078794 | I14: =SUM(I2:I13) -> 0 | K14: Promedio | L14: =AVERAGE(L2:L13) -> 0 | M14: =AVERAGE(M2:M13) -> 0 | N14: =AVERAGE(N2:N13) -> -8013.223 | O14: =AVERAGE(O2:O13) -> 0 | P14: =AVERAGE(P2:P13) -> 36243.347 | Q14: =AVERAGE(Q2:Q13) -> 0 | R14: =AVERAGE(R2:R13) -> 102974.67 | S14: =AVERAGE(S2:S13) -> 0.022457143
K15: Acumulado | L15: =SUM(L2:L13) -> 0 | M15: =SUM(M2:M13) -> 0 | N15: =SUM(N2:N13) -> -96158.676 | O15: =SUM(O2:O13) -> 0 | P15: =SUM(P2:P13) -> 434920.16 | Q15: =SUM(Q2:Q13) -> 0 | R15: =SUM(R2:R13) -> 1235696 | S15: =SUM(S2:S13) -> 0.1572
A17: P&L
A18: Mes | B18: Adcap Cobertura Clase A | C18: Megainver Liquidez Pesos Clase A | D18: Delta Recursos Naturales Clase A | E18: Gainvest Balanceado Clase A | F18: Schroder Renta Plus Clase A | G18: Schroder Liquidez Clase A | H18: Allaria Diversificado Clase A | I18: Schroder Renta Performance Clase A
A19: Enero | B19: -3865.58 | C19: 2035.2783 | D19: 4756 | E19: 0 | F19: 743.46 | G19: 0 | H19: 0 | I19: 0
A20: Febrero | B20: 0 | C20: 22798.276 | D20: -9724 | E20: 0 | F20: 0 | G20: 0 | H20: 0 | I20: 0
A21: Marzo | B21: 0 | C21: 0 | D21: 20000 | E21: 0 | F21: 0 | G21: 0 | H21: 0 | I21: 0
A22: Abril | B22: 0 | C22: 0 | D22: 2820 | E22: 0 | F22: 0 | G22: -5331.44 | H22: 0 | I22: 0
A23: Mayo | B23: 0 | C23: 0 | D23: 15040 | E23: 47862.334 | F23: 0 | G23: -2286.1581 | H23: 134154.28 | I23: 0
A24: Junio | B24: 0 | C24: 0 | D24: 21901.95 | E24: 21545.65 | F24: 0 | G24: 2934.319 | H24: =H7-H6 -> -35441.076 | I24: 0
A25: Julio | B25: =B8-B7 -> 0 | C25: =C7-C6 -> 0 | D25: =D8-D7 -> 15648.938 | E25: 0 | F25: =F8-F7 -> 25143.287 | G25: =G8-G7 -> 0 | H25: =H8-H7 -> 72353.481 | I25: =IFERROR(VLOOKUP($I$1,INDIRECT(B25&"!$A$2:$J$101"),8,FALSE),0) -> 0
A26: Agosto | B26: =B9-B8 -> 0 | C26: =C8-C7 -> 0 | D26: =D9-D8 -> -7171.378 | E26: 0 | F26: =F9-F8 -> -19946.938 | G26: =G9-G8 -> 0 | H26: =H9-H8 -> -36912.405 | I26: =IFERROR(VLOOKUP($I$1,INDIRECT(B26&"!$A$2:$J$101"),8,FALSE),0) -> 0
A27: Septiembre | B27: =B10-B9 -> 0 | C27: =C9-C8 -> 0 | H27: =H10-H9 -> 0 | I27: =IFERROR(VLOOKUP($I$1,INDIRECT(B27&"!$A$2:$J$101"),8,FALSE),0) -> 0
A28: Octubre | B28: =B11-B10 -> 0 | C28: =C10-C9 -> 0 | D28: =D11-D10 -> -116812.73 | E28: =E11-E10 -> 0 | F28: =F11-F10 -> -1122443.9 | G28: =G11-G10 -> 0 | H28: 0 | I28: =IFERROR(VLOOKUP($I$1,INDIRECT(B28&"!$A$2:$J$101"),8,FALSE),0) -> 0
A29: Noviembre | B29: =B12-B11 -> 0 | C29: =C11-C10 -> 0 | D29: =D12-D11 -> 0 | E29: =E12-E11 -> 0 | F29: =F12-F11 -> 0 | G29: =G12-G11 -> 0 | H29: =H12-H11 -> 0 | I29: =IFERROR(VLOOKUP($I$1,INDIRECT(B29&"!$A$2:$J$101"),8,FALSE),0) -> 0
A30: Diciembre | B30: =B13-B12 -> 0 | C30: =C12-C11 -> 0 | D30: =D13-D12 -> 0 | E30: =E13-E12 -> 0 | F30: =F13-F12 -> 0 | G30: =G13-G12 -> 0 | H30: =H13-H12 -> 0 | I30: =IFERROR(VLOOKUP($I$1,INDIRECT(B30&"!$A$2:$J$101"),8,FALSE),0) -> 0
A31: Total | B31: =SUM(B19:B30) -> -3865.58 | C31: =SUM(C19:C30) -> 24833.554 | D31: =SUM(D19:D30) -> -53541.225 | E31: =SUM(E19:E30) -> 69407.984 | F31: =SUM(F19:F30) -> -1116504.1 | G31: =SUM(G19:G30) -> -4683.279 | H31: =SUM(H19:H30) -> 134154.28 | I31: =SUM(I19:I30) -> 0
A32: Capital | B32: 109026.78 | C32: 290132.83 | D32: 44000 | E32: 617622.36 | F32: 240000 | G32: 114000 | H32: 1100000 | I32: 619063.54
F56: 1217862.3 | G56: =F56-F57 -> 47862.334
F57: 1170000

Sheet Bonos
A1: Mes | B1: AE38 | C1: AL29 | D1: AL30 | E1: TX24 | F1: TV24 | G1: TX26 | H1: TX28 | I1: BNA26 | K1: Mes | L1: AE38 | M1: AL29 | N1: AL30 | O1: TX24 | P1: TV24 | Q1: TX26 | R1: TX28 | S1: BNA26 | T1: INFLACION | V1: Acumulado
A2: Enero | B2: =IFERROR(VLOOKUP($B$1,INDIRECT(A2&"!$A$2:$J$101"),8,FALSE),0) -> 49320 | C2: =IFERROR(VLOOKUP($C$1,INDIRECT(A2&"!$A$2:$J$101"),8,FALSE),0) -> 49800 | D2: =IFERROR(VLOOKUP($D$1,INDIRECT(A2&"!$A$2:$J$101"),8,FALSE),0) -> 126488 | E2: =IFERROR(VLOOKUP($E$1,INDIRECT(A2&"!$A$2:$J$101"),8,FALSE),0) -> 0 | F2: =IFERROR(VLOOKUP($F$1,INDIRECT(A2&"!$A$2:$J$101"),8,FALSE),0) -> 0 | G2: =IFERROR(VLOOKUP($G$1,INDIRECT(A2&"!$A$2:$J$101"),8,FALSE),0) -> 0 | H2: {=IFERROR(VLOOKUP($I$1,INDIRECT(A2&"!$A$2:$J$101"),8,FALSE),0)} -> 0 | I2: =IFERROR(VLOOKUP($H$1,INDIRECT(A2&"!$A$2:$J$101"),8,FALSE),0) -> 0 | K2: Enero | L2: =IFERROR(VLOOKUP($L$1,INDIRECT(A2&"!$A$2:$J$101"),9,FALSE),0) -> 4920 | M2: =IFERROR(VLOOKUP($M$1,INDIRECT(A2&"!$A$2:$J$101"),9,FALSE),0) -> 240 | N2: =IFERROR(VLOOKUP($N$1,INDIRECT(A2&"!$A$2:$J$101"),9,FALSE),0) -> 978 | O2: =IFERROR(VLOOKUP($O$1,INDIRECT(A2&"!$A$2:$J$101"),9,FALSE),0) -> 0 | P2: =IFERROR(VLOOKUP($P$1,INDIRECT(A2&"!$A$2:$J$101"),9,FALSE),0) -> 0 | Q2: =IFERROR(VLOOKUP($Q$1,INDIRECT(A2&"!$A$2:$J$101"),9,FALSE),0) -> 0 | R2: =IFERROR(VLOOKUP($R$1,INDIRECT(A2&"!$A$2:$J$101"),9,FALSE),0) -> 0 | S2: =IFERROR(VLOOKUP($S$1,INDIRECT(A2&"!$A$2:$J$101"),9,FALSE),0) -> 0 | T2: =Global!M2 -> 0.022 | V2: AE38 | W2: =L15 -> 59160
A3: Febrero | B3: =IFERROR(VLOOKUP($B$1,INDIRECT(A3&"!$A$2:$J$101"),8,FALSE),0) -> 50160 | C3: =IFERROR(VLOOKUP($C$1,INDIRECT(A3&"!$A$2:$J$101"),8,FALSE),0) -> 51840 | D3: =IFERROR(VLOOKUP($D$1,INDIRECT(A3&"!$A$2:$J$101"),8,FALSE),0) -> 132030 | E3: =IFERROR(VLOOKUP($E$1,INDIRECT(A3&"!$A$2:$J$101"),8,FALSE),0) -> 0 | F3: =IFERROR(VLOOKUP($F$1,INDIRECT(A3&"!$A$2:$J$101"),8,FALSE),0) -> 0 | G3: =IFERROR(VLOOKUP($G$1,INDIRECT(A3&"!$A$2:$J$101"),8,FALSE),0) -> 0 | H3: =IFERROR(VLOOKUP($H$1,INDIRECT(A3&"!$A$2:$J$101"),8,FALSE),0) -> 0 | I3: =IFERROR(VLOOKUP($H$1,INDIRECT(A3&"!$A$2:$J$101"),8,FALSE),0) -> 0 | K3: Febrero | L3: =IFERROR(VLOOKUP($L$1,INDIRECT(A3&"!$A$2:$J$101"),9,FALSE),0) -> 5760 | M3: =IFERROR(VLOOKUP($M$1,INDIRECT(A3&"!$A$2:$J$101"),9,FALSE),0) -> 2280 | N3: =IFERROR(VLOOKUP($N$1,INDIRECT(A3&"!$A$2:$J$101"),9,FALSE),0) -> 6520 | O3: =IFERROR(VLOOKUP($O$1,INDIRECT(A3&"!$A$2:$J$101"),9,FALSE),0) -> 0 | P3: =IFERROR(VLOOKUP($P$1,INDIRECT(A3&"!$A$2:$J$101"),9,FALSE),0) -> 0 | Q3: =IFERROR(VLOOKUP($Q$1,INDIRECT(A3&"!$A$2:$J$101"),9,FALSE),0) -> 0 | R3: =IFERROR(VLOOKUP($R$1,INDIRECT(A3&"!$A$2:$J$101"),9,FALSE),0) -> 0 | S3: =IFERROR(VLOOKUP($S$1,INDIRECT(A3&"!$A$2:$J$101"),9,FALSE),0) -> 0 | T3: =Global!M3 -> 0.024 | V3: AL29 | W3: =M15 -> 2520
A4: Marzo | B4: =IFERROR(VLOOKUP($B$1,INDIRECT(A4&"!$A$2:$J$101"),8,FALSE),0) -> 49140 | C4: =IFERROR(VLOOKUP($C$1,INDIRECT(A4&"!$A$2:$J$101"),8,FALSE),0) -> 0 | D4: =IFERROR(VLOOKUP($D$1,INDIRECT(A4&"!$A$2:$J$101"),8,FALSE),0) -> 135290 | E4: =IFERROR(VLOOKUP($E$1,INDIRECT(A4&"!$A$2:$J$101"),8,FALSE),0) -> 0 | F4: =IFERROR(VLOOKUP($F$1,INDIRECT(A4&"!$A$2:$J$101"),8,FALSE),0) -> 0 | G4: =IFERROR(VLOOKUP($G$1,INDIRECT(A4&"!$A$2:$J$101"),8,FALSE),0) -> 0 | H4: =IFERROR(VLOOKUP($H$1,INDIRECT(A4&"!$A$2:$J$101"),8,FALSE),0) -> 0 | I4: =IFERROR(VLOOKUP($H$1,INDIRECT(A4&"!$A$2:$J$101"),8,FALSE),0) -> 0 | K4: Marzo | L4: =IFERROR(VLOOKUP($L$1,INDIRECT(A4&"!$A$2:$J$101"),9,FALSE),0) -> 4740 | M4: =IFERROR(VLOOKUP($M$1,INDIRECT(A4&"!$A$2:$J$101"),9,FALSE),0) -> 0 | N4: =IFERROR(VLOOKUP($N$1,INDIRECT(A4&"!$A$2:$J$101"),9,FALSE),0) -> 9780 | O4: =IFERROR(VLOOKUP($O$1,INDIRECT(A4&"!$A$2:$J$101"),9,FALSE),0) -> 0 | P4: =IFERROR(VLOOKUP($P$1,INDIRECT(A4&"!$A$2:$J$101"),9,FALSE),0) -> 0 | Q4: =IFERROR(VLOOKUP($Q$1,INDIRECT(A4&"!$A$2:$J$101"),9,FALSE),0) -> 0 | R4: =IFERROR(VLOOKUP($R$1,INDIRECT(A4&"!$A$2:$J$101"),9,FALSE),0) -> 0 | S4: =IFERROR(VLOOKUP($S$1,INDIRECT(A4&"!$A$2:$J$101"),9,FALSE),0) -> 0 | T4: =Global!M4 -> 0.03 | V4: AL30 | W4: =N15 -> 12388
A5: Abril | B5: =IFERROR(VLOOKUP($B$1,INDIRECT(A5&"!$A$2:$J$101"),8,FALSE),0) -> 49080 | C5: =IFERROR(VLOOKUP($C$1,INDIRECT(A5&"!$A$2:$J$101"),8,FALSE),0) -> 0 | D5: =IFERROR(VLOOKUP($D$1,INDIRECT(A5&"!$A$2:$J$101"),8,FALSE),0) -> 120620 | E5: =IFERROR(VLOOKUP($E$1,INDIRECT(A5&"!$A$2:$J$101"),8,FALSE),0) -> 0 | F5: =IFERROR(VLOOKUP($F$1,INDIRECT(A5&"!$A$2:$J$101"),8,FALSE),0) -> 0 | G5: =IFERROR(VLOOKUP($G$1,INDIRECT(A5&"!$A$2:$J$101"),8,FALSE),0) -> 0 | H5: =IFERROR(VLOOKUP($H$1,INDIRECT(A5&"!$A$2:$J$101"),8,FALSE),0) -> 0 | I5: =IFERROR(VLOOKUP($H$1,INDIRECT(A5&"!$A$2:$J$101"),8,FALSE),0) -> 0 | K5: Abril | L5: =IFERROR(VLOOKUP($L$1,INDIRECT(A5&"!$A$2:$J$101"),9,FALSE),0) -> 4680 | M5: =IFERROR(VLOOKUP($M$1,INDIRECT(A5&"!$A$2:$J$101"),9,FALSE),0) -> 0 | N5: =IFERROR(VLOOKUP($N$1,INDIRECT(A5&"!$A$2:$J$101"),9,FALSE),0) -> -4890 | O5: =IFERROR(VLOOKUP($O$1,INDIRECT(A5&"!$A$2:$J$101"),9,FALSE),0) -> 0 | P5: =IFERROR(VLOOKUP($P$1,INDIRECT(A5&"!$A$2:$J$101"),9,FALSE),0) -> 0 | Q5: =IFERROR(VLOOKUP($Q$1,INDIRECT(A5&"!$A$2:$J$101"),9,FALSE),0) -> 0 | R5: =IFERROR(VLOOKUP($R$1,INDIRECT(A5&"!$A$2:$J$101"),9,FALSE),0) -> 0 | S5: =IFERROR(VLOOKUP($S$1,INDIRECT(A5&"!$A$2:$J$101"),9,FALSE),0) -> 0 | T5: =Global!M5 -> 0.028 | V5: TX24 | W5: =O15 -> 0
A6: Mayo | B6: =IFERROR(VLOOKUP($B$1,INDIRECT(A6&"!$A$2:$J$101"),8,FALSE),0) -> 51180 | C6: =IFERROR(VLOOKUP($C$1,INDIRECT(A6&"!$A$2:$J$101"),8,FALSE),0) -> 0 | D6: =IFERROR(VLOOKUP($D$1,INDIRECT(A6&"!$A$2:$J$101"),8,FALSE),0) -> 0 | E6: =IFERROR(VLOOKUP($E$1,INDIRECT(A6&"!$A$2:$J$101"),8,FALSE),0) -> 0 | F6: =IFERROR(VLOOKUP($F$1,INDIRECT(A6&"!$A$2:$J$101"),8,FALSE),0) -> 0 | G6: =IFERROR(VLOOKUP($G$1,INDIRECT(A6&"!$A$2:$J$101"),8,FALSE),0) -> 0 | H6: =IFERROR(VLOOKUP($H$1,INDIRECT(A6&"!$A$2:$J$101"),8,FALSE),0) -> 0 | I6: =IFERROR(VLOOKUP($H$1,INDIRECT(A6&"!$A$2:$J$101"),8,FALSE),0) -> 0 | K6: Mayo | L6: =IFERROR(VLOOKUP($L$1,INDIRECT(A6&"!$A$2:$J$101"),9,FALSE),0) -> 6780 | M6: =IFERROR(VLOOKUP($M$1,INDIRECT(A6&"!$A$2:$J$101"),9,FALSE),0) -> 0 | N6: =IFERROR(VLOOKUP($N$1,INDIRECT(A6&"!$A$2:$J$101"),9,FALSE),0) -> 0 | O6: =IFERROR(VLOOKUP($O$1,INDIRECT(A6&"!$A$2:$J$101"),9,FALSE),0) -> 0 | P6: =IFERROR(VLOOKUP($P$1,INDIRECT(A6&"!$A$2:$J$101"),9,FALSE),0) -> 0 | Q6: =IFERROR(VLOOKUP($Q$1,INDIRECT(A6&"!$A$2:$J$101"),9,FALSE),0) -> 0 | R6: =IFERROR(VLOOKUP($R$1,INDIRECT(A6&"!$A$2:$J$101"),9,FALSE),0) -> 0 | S6: =IFERROR(VLOOKUP($S$1,INDIRECT(A6&"!$A$2:$J$101"),9,FALSE),0) -> 0 | T6: =Global!M6 -> 0.0172 | V6: TV24 | W6: =P15 -> 0
A7: Junio | B7: =IFERROR(VLOOKUP($B$1,INDIRECT(A7&"!$A$2:$J$101"),8,FALSE),0) -> 52740 | C7: =IFERROR(VLOOKUP($C$1,INDIRECT(A7&"!$A$2:$J$101"),8,FALSE),0) -> 0 | D7: =IFERROR(VLOOKUP($D$1,INDIRECT(A7&"!$A$2:$J$101"),8,FALSE),0) -> 0 | E7: =IFERROR(VLOOKUP($E$1,INDIRECT(A7&"!$A$2:$J$101"),8,FALSE),0) -> 0 | F7: =IFERROR(VLOOKUP($F$1,INDIRECT(A7&"!$A$2:$J$101"),8,FALSE),0) -> 0 | G7: =IFERROR(VLOOKUP($G$1,INDIRECT(A7&"!$A$2:$J$101"),8,FALSE),0) -> 0 | H7: =IFERROR(VLOOKUP($H$1,INDIRECT(A7&"!$A$2:$J$101"),8,FALSE),0) -> 0 | I7: =IFERROR(VLOOKUP($H$1,INDIRECT(A7&"!$A$2:$J$101"),8,FALSE),0) -> 0 | K7: Junio | L7: =IFERROR(VLOOKUP($L$1,INDIRECT(A7&"!$A$2:$J$101"),9,FALSE),0) -> 8340 | M7: =IFERROR(VLOOKUP($M$1,INDIRECT(A7&"!$A$2:$J$101"),9,FALSE),0) -> 0 | N7: =IFERROR(VLOOKUP($N$1,INDIRECT(A7&"!$A$2:$J$101"),9,FALSE),0) -> 0 | O7: =IFERROR(VLOOKUP($O$1,INDIRECT(A7&"!$A$2:$J$101"),9,FALSE),0) -> 0 | P7: =IFERROR(VLOOKUP($P$1,INDIRECT(A7&"!$A$2:$J$101"),9,FALSE),0) -> 0 | Q7: =IFERROR(VLOOKUP($Q$1,INDIRECT(A7&"!$A$2:$J$101"),9,FALSE),0) -> 0 | R7: =IFERROR(VLOOKUP($R$1,INDIRECT(A7&"!$A$2:$J$101"),9,FALSE),0) -> 0 | S7: =IFERROR(VLOOKUP($S$1,INDIRECT(A7&"!$A$2:$J$101"),9,FALSE),0) -> 0 | T7: =Global!M7 -> 0.016 | V7: TX26 | W7: =Q15 -> 0
A8: Julio | B8: =IFERROR(VLOOKUP($B$1,INDIRECT(A8&"!$A$2:$J$101"),8,FALSE),0) -> 54780 | C8: =IFERROR(VLOOKUP($C$1,INDIRECT(A8&"!$A$2:$J$101"),8,FALSE),0) -> 0 | D8: =IFERROR(VLOOKUP($D$1,INDIRECT(A8&"!$A$2:$J$101"),8,FALSE),0) -> 0 | E8: =IFERROR(VLOOKUP($E$1,INDIRECT(A8&"!$A$2:$J$101"),8,FALSE),0) -> 0 | F8: =IFERROR(VLOOKUP($F$1,INDIRECT(A8&"!$A$2:$J$101"),8,FALSE),0) -> 0 | G8: =IFERROR(VLOOKUP($G$1,INDIRECT(A8&"!$A$2:$J$101"),8,FALSE),0) -> 0 | H8: =IFERROR(VLOOKUP($H$1,INDIRECT(A8&"!$A$2:$J$101"),8,FALSE),0) -> 0 | I8: =IFERROR(VLOOKUP($H$1,INDIRECT(A8&"!$A$2:$J$101"),8,FALSE),0) -> 0 | K8: Julio | L8: =IFERROR(VLOOKUP($L$1,INDIRECT(A8&"!$A$2:$J$101"),9,FALSE),0) -> 10380 | M8: =IFERROR(VLOOKUP($M$1,INDIRECT(A8&"!$A$2:$J$101"),9,FALSE),0) -> 0 | N8: =IFERROR(VLOOKUP($N$1,INDIRECT(A8&"!$A$2:$J$101"),9,FALSE),0) -> 0 | O8: =IFERROR(VLOOKUP($O$1,INDIRECT(A8&"!$A$2:$J$101"),9,FALSE),0) -> 0 | P8: =IFERROR(VLOOKUP($P$1,INDIRECT(A8&"!$A$2:$J$101"),9,FALSE),0) -> 0 | Q8: =IFERROR(VLOOKUP($Q$1,INDIRECT(A8&"!$A$2:$J$101"),9,FALSE),0) -> 0 | R8: =IFERROR(VLOOKUP($R$1,INDIRECT(A8&"!$A$2:$J$101"),9,FALSE),0) -> 0 | S8: =IFERROR(VLOOKUP($S$1,INDIRECT(A8&"!$A$2:$J$101"),9,FALSE),0) -> 0 | T8: =Global!M8 -> 0.02 | V8: TX28 | W8: =R15 -> 0
A9: Agosto | B9: =IFERROR(VLOOKUP($B$1,INDIRECT(A9&"!$A$2:$J$101"),8,FALSE),0) -> 51180 | C9: =IFERROR(VLOOKUP($C$1,INDIRECT(A9&"!$A$2:$J$101"),8,FALSE),0) -> 0 | D9: =IFERROR(VLOOKUP($D$1,INDIRECT(A9&"!$A$2:$J$101"),8,FALSE),0) -> 0 | E9: =IFERROR(VLOOKUP($E$1,INDIRECT(A9&"!$A$2:$J$101"),8,FALSE),0) -> 0 | F9: =IFERROR(VLOOKUP($F$1,INDIRECT(A9&"!$A$2:$J$101"),8,FALSE),0) -> 0 | G9: =IFERROR(VLOOKUP($G$1,INDIRECT(A9&"!$A$2:$J$101"),8,FALSE),0) -> 0 | H9: =IFERROR(VLOOKUP($H$1,INDIRECT(A9&"!$A$2:$J$101"),8,FALSE),0) -> 0 | I9: =IFERROR(VLOOKUP($H$1,INDIRECT(A9&"!$A$2:$J$101"),8,FALSE),0) -> 0 | K9: Agosto | L9: =IFERROR(VLOOKUP($L$1,INDIRECT(A9&"!$A$2:$J$101"),9,FALSE),0) -> 6780 | M9: =IFERROR(VLOOKUP($M$1,INDIRECT(A9&"!$A$2:$J$101"),9,FALSE),0) -> 0 | N9: =IFERROR(VLOOKUP($N$1,INDIRECT(A9&"!$A$2:$J$101"),9,FALSE),0) -> 0 | O9: =IFERROR(VLOOKUP($O$1,INDIRECT(A9&"!$A$2:$J$101"),9,FALSE),0) -> 0 | P9: =IFERROR(VLOOKUP($P$1,INDIRECT(A9&"!$A$2:$J$101"),9,FALSE),0) -> 0 | Q9: =IFERROR(VLOOKUP($Q$1,INDIRECT(A9&"!$A$2:$J$101"),9,FALSE),0) -> 0 | R9: =IFERROR(VLOOKUP($R$1,INDIRECT(A9&"!$A$2:$J$101"),9,FALSE),0) -> 0 | S9: =IFERROR(VLOOKUP($S$1,INDIRECT(A9&"!$A$2:$J$101"),9,FALSE),0) -> 0 | T9: =Global!M9 | V9: BN26 | W9: =S15 -> 0
A10: Septiembre | B10: =IFERROR(VLOOKUP($B$1,INDIRECT(A10&"!$A$2:$J$101"),8,FALSE),0) -> 51180 | C10: =IFERROR(VLOOKUP($C$1,INDIRECT(A10&"!$A$2:$J$101"),8,FALSE),0) -> 0 | D10: =IFERROR(VLOOKUP($D$1,INDIRECT(A10&"!$A$2:$J$101"),8,FALSE),0) -> 0 | E10: =IFERROR(VLOOKUP($E$1,INDIRECT(A10&"!$A$2:$J$101"),8,FALSE),0) -> 0 | F10: =IFERROR(VLOOKUP($F$1,INDIRECT(A10&"!$A$2:$J$101"),8,FALSE),0) -> 0 | G10: =IFERROR(VLOOKUP($G$1,INDIRECT(A10&"!$A$2:$J$101"),8,FALSE),0) -> 0 | H10: =IFERROR(VLOOKUP($H$1,INDIRECT(A10&"!$A$2:$J$101"),8,FALSE),0) -> 0 | I10: =IFERROR(VLOOKUP($H$1,INDIRECT(A10&"!$A$2:$J$101"),8,FALSE),0) -> 0 | K10: Septiembre | L10: =IFERROR(VLOOKUP($L$1,INDIRECT(A10&"!$A$2:$J$101"),9,FALSE),0) -> 6780 | M10: =IFERROR(VLOOKUP($M$1,INDIRECT(A10&"!$A$2:$J$101"),9,FALSE),0) -> 0 | N10: =IFERROR(VLOOKUP($N$1,INDIRECT(A10&"!$A$2:$J$101"),9,FALSE),0) -> 0 | O10: =IFERROR(VLOOKUP($O$1,INDIRECT(A10&"!$A$2:$J$101"),9,FALSE),0) -> 0 | P10: =IFERROR(VLOOKUP($P$1,INDIRECT(A10&"!$A$2:$J$101"),9,FALSE),0) -> 0 | Q10: =IFERROR(VLOOKUP($Q$1,INDIRECT(A10&"!$A$2:$J$101"),9,FALSE),0) -> 0 | R10: =IFERROR(VLOOKUP($R$1,INDIRECT(A10&"!$A$2:$J$101"),9,FALSE),0) -> 0 | S10: =IFERROR(VLOOKUP($S$1,INDIRECT(A10&"!$A$2:$J$101"),9,FALSE),0) -> 0 | T10: =Global!M10 | V10: INFLACION | W10: =T15 -> 0.1572
A11: Octubre | B11: =IFERROR(VLOOKUP($B$1,INDIRECT(A11&"!$A$2:$J$101"),8,FALSE),0) -> 0 | C11: =IFERROR(VLOOKUP($C$1,INDIRECT(A11&"!$A$2:$J$101"),8,FALSE),0) -> 0 | D11: =IFERROR(VLOOKUP($D$1,INDIRECT(A11&"!$A$2:$J$101"),8,FALSE),0) -> 0 | E11: =IFERROR(VLOOKUP($E$1,INDIRECT(A11&"!$A$2:$J$101"),8,FALSE),0) -> 0 | F11: =IFERROR(VLOOKUP($F$1,INDIRECT(A11&"!$A$2:$J$101"),8,FALSE),0) -> 0 | G11: =IFERROR(VLOOKUP($G$1,INDIRECT(A11&"!$A$2:$J$101"),8,FALSE),0) -> 0 | H11: =IFERROR(VLOOKUP($H$1,INDIRECT(A11&"!$A$2:$J$101"),8,FALSE),0) -> 0 | I11: =IFERROR(VLOOKUP($H$1,INDIRECT(A11&"!$A$2:$J$101"),8,FALSE),0) -> 0 | K11: Octubre | L11: =IFERROR(VLOOKUP($L$1,INDIRECT(A11&"!$A$2:$J$101"),9,FALSE),0) -> 0 | M11: =IFERROR(VLOOKUP($M$1,INDIRECT(A11&"!$A$2:$J$101"),9,FALSE),0) -> 0 | N11: =IFERROR(VLOOKUP($N$1,INDIRECT(A11&"!$A$2:$J$101"),9,FALSE),0) -> 0 | O11: =IFERROR(VLOOKUP($O$1,INDIRECT(A11&"!$A$2:$J$101"),9,FALSE),0) -> 0 | P11: =IFERROR(VLOOKUP($P$1,INDIRECT(A11&"!$A$2:$J$101"),9,FALSE),0) -> 0 | Q11: =IFERROR(VLOOKUP($Q$1,INDIRECT(A11&"!$A$2:$J$101"),9,FALSE),0) -> 0 | R11: =IFERROR(VLOOKUP($R$1,INDIRECT(A11&"!$A$2:$J$101"),9,FALSE),0) -> 0 | S11: =IFERROR(VLOOKUP($S$1,INDIRECT(A11&"!$A$2:$J$101"),9,FALSE),0) -> 0 | T11: =Global!M11
A12: Noviembre | B12: =IFERROR(VLOOKUP($B$1,INDIRECT(A12&"!$A$2:$J$101"),8,FALSE),0) -> 0 | C12: =IFERROR(VLOOKUP($C$1,INDIRECT(A12&"!$A$2:$J$101"),8,FALSE),0) -> 0 | D12: =IFERROR(VLOOKUP($D$1,INDIRECT(A12&"!$A$2:$J$101"),8,FALSE),0) -> 0 | E12: =IFERROR(VLOOKUP($E$1,INDIRECT(A12&"!$A$2:$J$101"),8,FALSE),0) -> 0 | F12: =IFERROR(VLOOKUP($F$1,INDIRECT(A12&"!$A$2:$J$101"),8,FALSE),0) -> 0 | G12: =IFERROR(VLOOKUP($G$1,INDIRECT(A12&"!$A$2:$J$101"),8,FALSE),0) -> 0 | H12: =IFERROR(VLOOKUP($H$1,INDIRECT(A12&"!$A$2:$J$101"),8,FALSE),0) -> 0 | I12: =IFERROR(VLOOKUP($H$1,INDIRECT(A12&"!$A$2:$J$101"),8,FALSE),0) -> 0 | K12: Noviembre | L12: =IFERROR(VLOOKUP($L$1,INDIRECT(A12&"!$A$2:$J$101"),9,FALSE),0) -> 0 | M12: =IFERROR(VLOOKUP($M$1,INDIRECT(A12&"!$A$2:$J$101"),9,FALSE),0) -> 0 | N12: =IFERROR(VLOOKUP($N$1,INDIRECT(A12&"!$A$2:$J$101"),9,FALSE),0) -> 0 | O12: =IFERROR(VLOOKUP($O$1,INDIRECT(A12&"!$A$2:$J$101"),9,FALSE),0) -> 0 | P12: =IFERROR(VLOOKUP($P$1,INDIRECT(A12&"!$A$2:$J$101"),9,FALSE),0) -> 0 | Q12: =IFERROR(VLOOKUP($Q$1,INDIRECT(A12&"!$A$2:$J$101"),9,FALSE),0) -> 0 | R12: =IFERROR(VLOOKUP($R$1,INDIRECT(A12&"!$A$2:$J$101"),9,FALSE),0) -> 0 | S12: =IFERROR(VLOOKUP($S$1,INDIRECT(A12&"!$A$2:$J$101"),9,FALSE),0) -> 0 | T12: =Global!M12
A13: Diciembre | B13: =IFERROR(VLOOKUP($B$1,INDIRECT(A13&"!$A$2:$J$101"),8,FALSE),0) -> 0 | C13: =IFERROR(VLOOKUP($C$1,INDIRECT(A13&"!$A$2:$J$101"),8,FALSE),0) -> 0 | D13: =IFERROR(VLOOKUP($D$1,INDIRECT(A13&"!$A$2:$J$101"),8,FALSE),0) -> 0 | E13: =IFERROR(VLOOKUP($E$1,INDIRECT(A13&"!$A$2:$J$101"),8,FALSE),0) -> 0 | F13: =IFERROR(VLOOKUP($F$1,INDIRECT(A13&"!$A$2:$J$101"),8,FALSE),0) -> 0 | G13: =IFERROR(VLOOKUP($G$1,INDIRECT(A13&"!$A$2:$J$101"),8,FALSE),0) -> 0 | H13: =IFERROR(VLOOKUP($H$1,INDIRECT(A13&"!$A$2:$J$101"),8,FALSE),0) -> 0 | I13: =IFERROR(VLOOKUP($H$1,INDIRECT(A13&"!$A$2:$J$101"),8,FALSE),0) -> 0 | K13: Diciembre | L13: =IFERROR(VLOOKUP($L$1,INDIRECT(A13&"!$A$2:$J$101"),9,FALSE),0) -> 0 | M13: =IFERROR(VLOOKUP($M$1,INDIRECT(A13&"!$A$2:$J$101"),9,FALSE),0) -> 0 | N13: =IFERROR(VLOOKUP($N$1,INDIRECT(A13&"!$A$2:$J$101"),9,FALSE),0) -> 0 | O13: =IFERROR(VLOOKUP($O$1,INDIRECT(A13&"!$A$2:$J$101"),9,FALSE),0) -> 0 | P13: =IFERROR(VLOOKUP($P$1,INDIRECT(A13&"!$A$2:$J$101"),9,FALSE),0) -> 0 | Q13: =IFERROR(VLOOKUP($Q$1,INDIRECT(A13&"!$A$2:$J$101"),9,FALSE),0) -> 0 | R13: =IFERROR(VLOOKUP($R$1,INDIRECT(A13&"!$A$2:$J$101"),9,FALSE),0) -> 0 | S13: =IFERROR(VLOOKUP($S$1,INDIRECT(A13&"!$A$2:$J$101"),9,FALSE),0) -> 0 | T13: =Global!M13
A14: Total | B14: =SUM(B2:B13) -> 458760 | C14: =SUM(C2:C13) -> 101640 | D14: =SUM(D2:D13) -> 514428 | E14: =SUM(E2:E13) -> 0 | F14: =SUM(F2:F13) -> 0 | G14: =SUM(G2:G13) -> 0 | H14: =SUM(H2:H13) -> 0 | I14: =SUM(I2:I13) -> 0 | K14: Promedio | L14: =AVERAGE(L2:L13) -> 4930 | M14: =AVERAGE(M2:M13) -> 210 | N14: =AVERAGE(N2:N13) -> 1032.3333 | O14: =AVERAGE(O2:O13) -> 0 | P14: =AVERAGE(P2:P13) -> 0 | Q14: =AVERAGE(Q2:Q13) -> 0 | R14: =AVERAGE(R2:R13) -> 0 | S14: =AVERAGE(S2:S13) -> 0 | T14: =AVERAGE(T2:T13) -> 0.022457143
K15: Acumulado | L15: =SUM(L2:L13) -> 59160 | M15: =SUM(M2:M13) -> 2520 | N15: =SUM(N2:N13) -> 12388 | O15: =SUM(O2:O13) -> 0 | P15: =SUM(P2:P13) -> 0 | Q15: =SUM(Q2:Q13) -> 0 | R15: =SUM(R2:R13) -> 0 | S15: =SUM(S2:S13) -> 0 | T15: =SUM(T2:T13) -> 0.1572

Sheet Cripto
A1: Mes | B1: BTC | D1: Mes | E1: BTC | F1: INFLACION
A2: Enero | B2: =IFERROR(VLOOKUP($B$1,INDIRECT(A2&"!$A$2:$J$101"),8,FALSE),0) -> 22000 | D2: Enero | E2: =IFERROR(VLOOKUP($E$1,INDIRECT(A2&"!$A$2:$J$101"),9,FALSE),0) -> 0 | F2: =Global!M2 -> 0.022
A3: Febrero | B3: =IFERROR(VLOOKUP($B$1,INDIRECT(A3&"!$A$2:$J$101"),8,FALSE),0) -> 22160 | D3: Febrero | E3: =IFERROR(VLOOKUP($E$1,INDIRECT(A3&"!$A$2:$J$101"),9,FALSE),0) -> 160 | F3: =Global!M4 -> 0.03
A4: Marzo | B4: =IFERROR(VLOOKUP($B$1,INDIRECT(A4&"!$A$2:$J$101"),8,FALSE),0) -> 21408 | D4: Marzo | E4: =IFERROR(VLOOKUP($E$1,INDIRECT(A4&"!$A$2:$J$101"),9,FALSE),0) -> -592 | F4: =Global!M5 -> 0.028
A5: Abril | B5: =IFERROR(VLOOKUP($B$1,INDIRECT(A5&"!$A$2:$J$101"),8,FALSE),0) -> 23867 | D5: Abril | E5: =IFERROR(VLOOKUP($E$1,INDIRECT(A5&"!$A$2:$J$101"),9,FALSE),0) -> 3220 | F5: =Global!M6 -> 0.0172
A6: Mayo | B6: =IFERROR(VLOOKUP($B$1,INDIRECT(A6&"!$A$2:$J$101"),8,FALSE),0) -> 24930.7 | D6: Mayo | E6: =IFERROR(VLOOKUP($E$1,INDIRECT(A6&"!$A$2:$J$101"),9,FALSE),0) -> 2930.7 | F6: =Global!M7 -> 0.016
A7: Junio | B7: =IFERROR(VLOOKUP($B$1,INDIRECT(A7&"!$A$2:$J$101"),8,FALSE),0) -> 28000 | D7: Junio | E7: =IFERROR(VLOOKUP($E$1,INDIRECT(A7&"!$A$2:$J$101"),9,FALSE),0) -> 6000 | F7: =Global!M8 -> 0.02
A8: Julio | B8: =IFERROR(VLOOKUP($B$1,INDIRECT(A8&"!$A$2:$J$101"),8,FALSE),0) -> 31114.52 | D8: Julio | E8: =IFERROR(VLOOKUP($E$1,INDIRECT(A8&"!$A$2:$J$101"),9,FALSE),0) -> 9114.52 | F8: =Global!M9
A9: Agosto | B9: =IFERROR(VLOOKUP($B$1,INDIRECT(A9&"!$A$2:$J$101"),8,FALSE),0) -> 31430 | D9: Agosto | E9: =IFERROR(VLOOKUP($E$1,INDIRECT(A9&"!$A$2:$J$101"),9,FALSE),0) -> 9430 | F9: =Global!M10
A10: Septiembre | B10: =IFERROR(VLOOKUP($B$1,INDIRECT(A10&"!$A$2:$J$101"),8,FALSE),0) -> 31430 | D10: Septiembre | E10: =IFERROR(VLOOKUP($E$1,INDIRECT(A10&"!$A$2:$J$101"),9,FALSE),0) -> 9430 | F10: =Global!M11
A11: Octubre | B11: =IFERROR(VLOOKUP($B$1,INDIRECT(A11&"!$A$2:$J$101"),8,FALSE),0) -> 0 | D11: Octubre | E11: =IFERROR(VLOOKUP($E$1,INDIRECT(A11&"!$A$2:$J$101"),9,FALSE),0) -> 0 | F11: =Global!M12
A12: Noviembre | B12: =IFERROR(SUMIF(INDIRECT(A12&"!$B$2:$B$100"),"Cripto",INDIRECT(A12&"!$E$2:$E$100")),0) -> 0 | D12: Noviembre | E12: =IFERROR(VLOOKUP($E$1,INDIRECT(A12&"!$A$2:$J$101"),9,FALSE),0) -> 0 | F12: =Global!M13
A13: Diciembre | B13: =IFERROR(SUMIF(INDIRECT(A13&"!$B$2:$B$100"),"Cripto",INDIRECT(A13&"!$E$2:$E$100")),0) -> 0 | D13: Diciembre | E13: =IFERROR(((B13-B12)/B13),0) -> 0 | F13: =Global!N14
A14: Total | B14: =SUM(B1:B13) -> 236340.22 | D14: Total | E14: =AVERAGE(E2:E13) -> 3307.7683 | F14: =AVERAGE(F2:F13) -> 0.0222

Sheet Letras
A1: Mes | B1: Total | D1: Mes | E1: Ganancia | F1: Letras % | G1: INFLACION
A2: Enero | B2: =Global!H2 -> 28744.249 | D2: Enero | F2: =IFERROR(((B2-B1)/B2),0) -> 0 | G2: 0
A3: Febrero | B3: =Global!H3 -> 1126576.5 | D3: Febrero | E3: =IF(B3=0,0,B3-B2) -> 1097832.3 | F3: =IFERROR(((B3-B2)/B3),0) -> 0.97448531 | G3: 0
A4: Marzo | B4: =Global!H4 -> 1134591.6 | D4: Marzo | E4: =IF(B4=0,0,B4-B3) -> 8015.03 | F4: =IFERROR(((B4-B3)/B4),0) -> 0.0070642425 | G4: 0
A5: Abril | B5: =Global!H5 -> 2185113 | D5: Abril | E5: =IF(B5=0,0,B5-B4) -> 1050521.5 | F5: =IFERROR(((B5-B4)/B5),0) -> 0.48076298 | G5: 0
A6: Mayo | B6: =Global!H6 -> 2205766.2 | D6: Mayo | E6: =IF(B6=0,0,B6-B5) -> 20653.134 | F6: =IFERROR(((B6-B5)/B6),0) -> 0.0093632473 | G6: 0
A7: Junio | B7: =Global!H7 -> 3259732.2 | D7: Junio | E7: =IF(B7=0,0,B7-B6) -> 1053966 | F7: =IFERROR(((B7-B6)/B7),0) -> 0.32332902 | G7: 0
A8: Julio | B8: =Global!H8 -> 3375673.7 | D8: Julio | E8: 0 | F8: 0 | G8: 0
A9: Agosto | B9: =Global!H9 -> 2344814 | D9: Agosto | E9: =IF(B9=0,0,B9-B8) -> -1030859.6 | F9: =IFERROR(((B9-B8)/B9),0) -> -0.43963386 | G9: 0.04
A10: Septiembre | B10: =Global!H10 -> 1866788 | D10: Septiembre | E10: =IF(B10=0,0,B10-B9) -> -478026.07 | F10: =IFERROR(((B10-B9)/B10),0) -> -0.25606876 | G10: =Global!M10
A11: Octubre | B11: =Global!H11 | D11: Octubre | E11: =IF(B11=0,0,B11-B10) -> 0 | F11: =IFERROR(((B11-B10)/B11),0) -> 0 | G11: =Global!M11
A12: Noviembre | B12: =Global!H12 | D12: Noviembre | E12: =IF(B12=0,0,B12-B11) -> 0 | F12: =IFERROR(((B12-B11)/B12),0) -> 0 | G12: =Global!M12
A13: Diciembre | B13: =Global!H13 | D13: Diciembre | E13: =IF(B13=0,0,B13-B12) -> 0 | F13: =IFERROR(((B13-B12)/B13),0) -> 0 | G13: =Global!M13
A14: Total | B14: =SUM(B1:B13) -> 17527799 | D14: Total | F14: =AVERAGE(F2:F13) -> 0.091608515 | G14: =AVERAGE(G2:G13) -> 0.005
